Workbook

Sheet Index
A8: AusPlay survey results July 2024 - June 2025
A9: Released at: | D9: 13 November 2025
A10: Table name: | D10: Index
E11: Equivalent table number in national data tables
B12: Table number | D12: Table name
A13: Demographics of participants | B13: 1 | D13: Demographics of participants (adults) | E13: 1
B14: 2 | D14: Demographics of participants (children) (organised outside of school hours) | E14: 2
A16: Overall participation | B16: 3 | D16: Organisational nature of activity - overview (adults) | E16: 3
B17: 4 | D17: Organisational nature of activity - detail (adults) | E17: 4
B18: 5 | D18: Organised activity by type of entity (adults) | E18: 5
B19: 6 | D19: Organised activity by type of entity (children) | E19: 6
B20: 7 | D20: Places where activity took place (adults) | E20: 7
B21: 8 | D21: Places where activity took place (children) | E21: 8
B22: 9 | D22: Frequency of participation (adults) | E22: 9
B23: 10 | D23: Frequency of participation (children) | E23: 10
B24: 11 | D24: Motivations for participation (adults) | E24: 12
B25: 12 | D25: Barriers to participation (adults) | E25: 13
B26: 13 | D26: Barriers to participation (children) | E26: 14
B27: 14 | D27: Sport or non-sport related participation (adults) | E27: 15
B28: 15 | D28: Sport or non-sport related participation (children) | E28: 16
... B37: 24 | D37: Volunteers in non-playing roles by activity - top roles and top 5 activities (adults) | E37: 27
A39: Demographics of non-participants | B39: 25 | D39: Demographics of non-participants (adults) | E39: 30
B40: 26 | D40: Demographics of non-participants (children) | E40: 31
A42: Margin of error tables | B42: 27 | D42: Margins of error | E42: 38
A44: Key terms and definitions | B44: 28 | D44: Key terms and definitions | E44: 39

Sheet 1
A8: AusPlay survey results July 2024 - June 2025
A9: Released at: | B9: 13 November 2025
A10: Table number: | B10: 1
A11: Table name: | B11: Demographics of participants (adults)
A12: Base: | B12: Adult population
C13: At least once per year participation | K13: At least once per week participation | S13: At least three times per week participation
C14: Participation rate | G14: Estimated number of participants | K14: Participation rate | O14: Estimated number of participants | S14: Participation rate | W14: Estimated number of participants
C15: Total | D15: Males | E15: Females | G15: Total# | H15: Males | I15: Females | K15: Total | L15: Males | M15: Females | O15: Total# | P15: Males | Q15: Females | S15: Total | T15: Males | U15: Females | W15: Total# | X15: Males | Y15: Females
A16: Total | C16: 0.86963983 | D16: 0.87734998 | E16: 0.8644377 | G16: 5015652.8 | H16: 2468235.6 | I16: 2520330.1 | K16: 0.69587655 | L16: 0.69330247 | M16: 0.70039246 | O16: 4013472.1 | P16: 1950457.5 | Q16: 2042044.5 | S16: 0.50051291 | T16: 0.48381292 | U16: 0.51785436 | W16: 2886711.1 | X16: 1361103.7 | Y16: 1509841.5
A17: Age group
B18: 15-17 | C18: 0.84583468 | D18: 0.81985642 | E18: 0.88504676 | G18: 203601.17 | H18: 81119.411 | I18: 122481.76 | K18: 0.64605555 | L18: 0.6328725 | M18: 0.67124489 | O18: 155512.26 | P18: 62618.578 | Q18: 92893.684 | S18: 0.44760347 | T18: 0.46141719 | U18: 0.4486489 | W18: 107742.79 | X18: 45654.202 | Y18: 62088.59
B19: 18-24 | C19: 0.88919859 | D19: 0.88133157 | E19: 0.90036213 | G19: 603392.95 | H19: 321407.44 | I19: 274016 | K19: 0.6971593 | L19: 0.6706821 | M19: 0.72796411 | O19: 473078.8 | P19: 244586.97 | Q19: 221548.43 | S19: 0.47908839 | T19: 0.43906984 | U19: 0.52569605 | W19: 325100.1 | X19: 160121.7 | Y19: 159990.21
B20: 25-34 | C20: 0.91865092 | D20: 0.92020703 | E20: 0.91694021 | G20: 970562.03 | H20: 465225.36 | I20: 498542.5 | K20: 0.72103126 | L20: 0.69533249 | M20: 0.7457116 | O20: 761775.28 | P20: 351536.45 | Q20: 405445.12 | S20: 0.51492309 | T20: 0.47116949 | U20: 0.55700452 | W20: 544020.35 | X20: 238207.26 | Y20: 302844.64
B21: 35-44 | C21: 0.89233389 | D21: 0.88795492 | E21: 0.89883808 | G21: 896984.71 | H21: 449706.14 | I21: 443003.41 | K21: 0.69155327 | L21: 0.6721466 | M21: 0.71238105 | O21: 695157.63 | P21: 340409.68 | Q21: 351105.77 | S21: 0.4702791 | T21: 0.44343327 | U21: 0.49610314 | W21: 472730.19 | X21: 224577.46 | Y21: 244510.54
B22: 45-54 | C22: 0.89145479 | D22: 0.90325368 | E22: 0.87860481 | G22: 769097.39 | H22: 384156.93 | I22: 379973.22 | K22: 0.72534802 | L22: 0.72477687 | M22: 0.72731465 | O22: 625789.75 | P22: 308250.13 | Q22: 314544.25 | S22: 0.53644837 | T22: 0.51398847 | U22: 0.55894361 | W22: 462817.69 | X22: 218601.08 | Y22: 241728.25
B23: 55-64 | C23: 0.8752102 | D23: 0.87325812 | E23: 0.87649254 | G23: 652990.96 | H23: 323892.01 | I23: 327132.25 | K23: 0.74021626 | L23: 0.73669691 | M23: 0.74364566 | O23: 552272.5 | P23: 273241.37 | Q23: 277549.97 | S23: 0.5777315 | T23: 0.56162514 | U23: 0.59411259 | W23: 431043.24 | X23: 208307.13 | Y23: 221739.92
B24: 65+ | C24: 0.78038467 | D24: 0.81769266 | E24: 0.75356774 | G24: 919023.6 | H24: 442728.31 | I24: 475181 | K24: 0.63676215 | L24: 0.68302491 | M24: 0.60097093 | O24: 749885.89 | P24: 369814.33 | Q24: 378957.26 | S24: 0.46130398 | T24: 0.4906116 | U24: 0.43918547 | W24: 543256.77 | X24: 265634.82 | Y24: 276939.39
A25: Remoteness
B26: Major cities | C26: 0.87658462 | D26: 0.88840753 | E26: 0.86825896 | G26: 3901487 | H26: 1925550.6 | I26: 1957141.6 | K26: 0.7017332 | L26: 0.70537954 | M26: 0.70125271 | O26: 3123261.5 | P26: 1528852.4 | Q26: 1580693 | S26: 0.50191156 | T26: 0.49291365 | U26: 0.51311205 | W26: 2233898.9 | X26: 1068350 | Y26: 1156605.3
B27: Inner regional | C27: 0.84774107 | D27: 0.84160394 | E27: 0.85342258 | G27: 916261.95 | H27: 447348.05 | I27: 461592.14 | K27: 0.67431061 | L27: 0.6475125 | M27: 0.69862069 | O27: 728813.52 | P27: 344180.25 | Q27: 377864.18 | S27: 0.49778063 | T27: 0.45691556 | U27: 0.5339672 | W27: 538015.05 | X27: 242869.92 | Y27: 288807.76
B28: Outer regional | C28: 0.83721306 | D28: 0.83018759 | E28: 0.84241682 | G28: 195395.12 | H28: 92828.236 | I28: 101596.4 | K28: 0.68282113 | L28: 0.67423019 | M28: 0.69225989 | O28: 159361.96 | P28: 75389.708 | Q28: 83487.31 | S28: 0.48518268 | T28: 0.43215824 | U28: 0.53422781 | W28: 113235.61 | X28: 48322.196 | Y28: 64428.466
B29: Remote or very remote | C29: 1 | D29: 1 | E29: 0 | G29: 2508.7301 | H29: 2508.7301 | I29: 0 | K29: 0.81122657 | L29: 0.81122657 | M29: 0 | O29: 2035.1485 | P29: 2035.1485 | Q29: 0 | S29: 0.62245314 | T29: 0.62245314 | U29: 0 | W29: 1561.5669 | X29: 1561.5669 | Y29: 0
A30: Employment status
B31: Employed full-time | C31: 0.91182495 | D31: 0.91345778 | E31: 0.91025618 | G31: 2380731.8 | H31: 1409027.2 | I31: 964631.57 | K31: 0.72861135 | L31: 0.71459382 | M31: 0.75053382 | O31: 1902369.8 | P31: 1102275.5 | Q31: 795367.98 | S31: 0.52012828 | T31: 0.49620235 | U31: 0.55704218 | W31: 1358030.4 | X31: 765402.22 | Y31: 590317.85
B32: Employed part-time | C32: 0.88617522 | D32: 0.85854429 | E32: 0.90317732 | G32: 772508.71 | H32: 259305.4 | I32: 507728.18 | K32: 0.70713115 | L32: 0.66570814 | M32: 0.73116798 | O32: 616429.97 | P32: 201063.27 | Q32: 411031.79 | S32: 0.5108512 | T32: 0.46717878 | U32: 0.53511131 | W32: 445326.15 | X32: 141101.61 | Y32: 300817
B33: Employed casual | C33: 0.91392069 | D33: 0.92111811 | E33: 0.91037389 | G33: 305409.63 | H33: 117269.4 | I33: 184675.55 | K33: 0.76096055 | L33: 0.78104784 | M33: 0.74630319 | O33: 254294.14 | P33: 99436.769 | Q33: 151392.69 | S33: 0.53581952 | T33: 0.51754668 | U33: 0.54542333 | W33: 179057.59 | X33: 65889.908 | Y33: 110642.84
B34: Total employed | C34: 0.90615029 | D34: 0.90554129 | E34: 0.90808846 | G34: 3458650.2 | H34: 1785602 | I34: 1657035.3 | K34: 0.72653773 | L34: 0.71139658 | M34: 0.7440974 | O34: 2773093.9 | P34: 1402775.5 | Q34: 1357792.5 | S34: 0.51938329 | T34: 0.49313491 | U34: 0.54899419 | W34: 1982414.1 | X34: 972393.74 | Y34: 1001777.7
B35: Full-time student | C35: 0.90542577 | D35: 0.90724917 | E35: 0.91543538 | G35: 270095.49 | H35: 132096.77 | I35: 135494.25 | K35: 0.71709577 | L35: 0.68136427 | M35: 0.76153801 | O35: 213915.19 | P35: 99207.606 | Q35: 112715.79 | S35: 0.50330625 | T35: 0.46493645 | U35: 0.54356151 | W35: 150140.13 | X35: 67695.407 | Y35: 80452.932
B36: Engaged in home duties | C36: 0.80619077 | D36: 0.70855379 | E36: 0.8228526 | G36: 153533.14 | H36: 20282.99 | I36: 132692.52 | K36: 0.64374443 | L36: 0.58569696 | M36: 0.6528168 | O36: 122596.42 | P36: 16766.102 | Q36: 105272.69 | S36: 0.48560917 | T36: 0.3988446 | U36: 0.49923242 | W36: 92480.718 | X36: 11417.285 | Y36: 80505.803
B37: Unemployed | C37: 0.78256518 | D37: 0.7667054 | E37: 0.79481202 | G37: 191914.34 | H37: 86225.733 | I37: 103194.87 | K37: 0.57010446 | L37: 0.59182096 | M37: 0.55314225 | O37: 139811 | P37: 66557.763 | Q37: 71817.536 | S37: 0.43270667 | T37: 0.4197865 | U37: 0.44263603 | W37: 106115.91 | X37: 47210.309 | Y37: 57469.898
B38: Retired or on a pension | C38: 0.77773585 | D38: 0.81047546 | E38: 0.75436735 | G38: 891240.81 | H38: 418531.27 | I38: 468914.06 | K38: 0.63848153 | L38: 0.67248053 | M38: 0.61228765 | O38: 731663.33 | P38: 347270.39 | Q38: 380597.45 | S38: 0.46631252 | T38: 0.48817378 | U38: 0.4494842 | W38: 534367.48 | X38: 252093.99 | Y38: 279398.97
A39: Highest education completed
B40: University degree or higher (including postgraduate diploma) | C40: 0.93005806 | D40: 0.92570662 | E40: 0.93509455 | G40: 2292689.5 | H40: 1189383 | I40: 1093277.6 | K40: 0.77031153 | L40: 0.7636459 | M40: 0.77879662 | O40: 1898897.7 | P40: 981161.26 | Q40: 910539.91 | S40: 0.56435612 | T40: 0.54642987 | U40: 0.58476873 | W40: 1391196.3 | X40: 702073.85 | Y40: 683689.75
B41: Undergraduate diploma or associate diploma | C41: 0.86843374 | D41: 0.87201224 | E41: 0.87033897 | G41: 690329.26 | H41: 338015.12 | I41: 348864.79 | K41: 0.69152227 | L41: 0.67818051 | M41: 0.70978854 | O41: 549700.04 | P41: 262880.79 | Q41: 284510.1 | S41: 0.49263568 | T41: 0.46354264 | U41: 0.52547208 | W41: 391602.5 | X41: 179681.45 | Y41: 210629.09
B42: Certificate, trade qualification or apprenticeship | C42: 0.83550994 | D42: 0.84393972 | E42: 0.82817543 | G42: 780273.79 | H42: 355564.34 | I42: 420854.29 | K42: 0.64887467 | L42: 0.6310034 | M42: 0.66172844 | O42: 605977.11 | P42: 265851.11 | Q42: 336270.85 | S42: 0.45947396 | T42: 0.41422432 | U42: 0.49618206 | W42: 429097.81 | X42: 174518.86 | Y42: 252145.07
B43: Highest level of secondary school | C43: 0.84233493 | D43: 0.84041631 | E43: 0.84737292 | G43: 772700.45 | H43: 374369.4 | I43: 393452.44 | K43: 0.66310925 | L43: 0.64450096 | M43: 0.68353738 | O43: 608291.07 | P43: 287097.52 | Q43: 317380.27 | S43: 0.46953712 | T43: 0.44539327 | U43: 0.49318025 | W43: 430721.23 | X43: 198403.59 | Y43: 228993.6
B44: Did not complete highest level of school | C44: 0.68150517 | D44: 0.77798972 | E44: 0.61913844 | G44: 249417.18 | H44: 106412.43 | I44: 139305.9 | K44: 0.4904229 | L44: 0.54244116 | M44: 0.45631542 | O44: 179484.91 | P44: 74194.404 | Q44: 102670.79 | S44: 0.34731571 | T44: 0.3834435 | U44: 0.32019582 | W44: 127110.56 | X44: 52446.909 | Y44: 72043.932
B45: Still at secondary school | C45: 0.87876513 | D45: 0.88466411 | E45: 0.90426776 | G45: 175042.07 | H45: 77963.821 | I45: 96565.583 | K45: 0.68491443 | L45: 0.7176462 | M45: 0.68051446 | O45: 136428.77 | P45: 63244.839 | Q45: 72671.258 | S45: 0.47014074 | T45: 0.52399568 | U45: 0.44451341 | W45: 93647.787 | X45: 46178.775 | Y45: 47469.012
A46: Household structure
B47: Younger family (most children under 15 years) | C47: 0.91363686 | D47: 0.92719435 | E47: 0.90425039 | G47: 985151.1 | H47: 498600.73 | I47: 484958.18 | K47: 0.67225558 | L47: 0.64961653 | M47: 0.69833454 | O47: 724875.89 | P47: 349332.67 | Q47: 374523.53 | S47: 0.42528295 | T47: 0.4028978 | U47: 0.45106876 | W47: 458571.66 | X47: 216659.15 | Y47: 241912.51
B48: Mature family (most children 15 years or over) | C48: 0.87524937 | D48: 0.87545171 | E48: 0.87654181 | G48: 1200411.7 | H48: 584544.3 | I48: 608496.31 | K48: 0.713387 | L48: 0.70769164 | M48: 0.72049437 | O48: 978416.17 | P48: 472529.9 | Q48: 500168 | S48: 0.51399146 | T48: 0.49955513 | U48: 0.52803423 | W48: 704943.54 | X48: 333555.93 | Y48: 366561.95
B49: Mid family (equal number of children 15 years and over and under 15 years) | C49: 0.91544626 | D49: 0.9166083 | E49: 0.91309663 | G49: 180984.77 | H49: 85967.652 | I49: 93461.716 | K49: 0.73275821 | L49: 0.73919883 | M49: 0.72819512 | O49: 144867.13 | P49: 69328.619 | Q49: 74535.776 | S49: 0.51987021 | T49: 0.52275201 | U49: 0.51533303 | W49: 102778.93 | X49: 49028.317 | Y49: 52747.878
B50: Adult shared house | C50: 0.86460996 | D50: 0.87088566 | E50: 0.85814052 | G50: 581427.51 | H50: 308951.47 | I50: 267309.89 | K50: 0.67251582 | L50: 0.67141424 | M50: 0.67388748 | O50: 452249.24 | P50: 238187.88 | Q50: 209915.26 | S50: 0.498299 | T50: 0.47651915 | U50: 0.52411328 | W50: 335093 | X50: 169047.78 | Y50: 163260.75
B51: Single/couple - no children | C51: 0.85176428 | D51: 0.86518446 | E51: 0.84193645 | G51: 2026041.7 | H51: 970002.63 | I51: 1045795.4 | K51: 0.70816766 | L51: 0.72103145 | M51: 0.69893328 | O51: 1684476.8 | P51: 808385.31 | Q51: 868166.73 | S51: 0.53162702 | T51: 0.51955743 | U51: 0.54426868 | W51: 1264550 | X51: 582502.46 | Y51: 676053.03
A52: Aboriginal or Torres Strait Islander origin^
B53: Yes | C53: 0.80547125 | D53: 0.8380624 | E53: 0.75774748 | G53: 141953.82 | H53: 91709.203 | I53: 49213.683 | K53: 0.51148683 | L53: 0.54138712 | M53: 0.4676892 | O53: 90142.896 | P53: 59244.015 | Q53: 30375.169 | S53: 0.32797062 | T53: 0.3506092 | U53: 0.29115376 | W53: 57800.553 | X53: 38367.179 | Y53: 18909.662
B54: No | C54: 0.87509555 | D54: 0.88427222 | E54: 0.86742914 | G54: 4578240.1 | H54: 2235833.5 | I54: 2319809.4 | K54: 0.70737332 | L54: 0.70670447 | M54: 0.70906322 | O54: 3700767.2 | P54: 1786863.2 | Q54: 1896283.5 | S54: 0.51219406 | T54: 0.49519741 | U54: 0.52915716 | W54: 2679647.2 | X54: 1252079.3 | Y54: 1415151.6
B55: Refused / don't know | C55: 0.77285243 | D55: 0.77907661 | E55: 0.7608842 | G55: 91857.702 | H55: 59573.512 | I55: 28825.268 | K55: 0.56412879 | L55: 0.54574878 | M55: 0.59371255 | O55: 67049.765 | P55: 41731.674 | Q55: 22492.152 | S55: 0.34933675 | T55: 0.32697801 | U55: 0.36141092 | W55: 41520.566 | X55: 25002.969 | Y55: 13691.658
A56: Language spoken at home^
B57: Speaks only English at home | C57: 0.87284729 | D57: 0.88263982 | E57: 0.8640524 | G57: 3894862.3 | H57: 1887678.1 | I57: 1987978.1 | K57: 0.71156112 | L57: 0.71276444 | M57: 0.71086806 | O57: 3175163.2 | P57: 1524370.2 | Q57: 1635537.6 | S57: 0.51732584 | T57: 0.49812246 | U57: 0.53528555 | W57: 2308436.9 | X57: 1065321.1 | Y57: 1231564.2
B58: Speaks language other than English at home | C58: 0.87408776 | D58: 0.88140447 | E58: 0.87288644 | G58: 866172.75 | H58: 463457.35 | I58: 397161.98 | K58: 0.6519872 | L58: 0.64320424 | M58: 0.666702 | O58: 646083.35 | P58: 338207.65 | Q58: 303348.38 | S58: 0.44810763 | T58: 0.44260981 | U58: 0.45778456 | W58: 444049.94 | X58: 232731.71 | Y58: 208291.27
A59: Disability or physical condition that restricts life in some way^
B60: Yes | C60: 0.72730943 | D60: 0.72714474 | E60: 0.72410225 | G60: 637082.74 | H60: 260979.56 | I60: 364939.77 | K60: 0.5506781 | L60: 0.55207376 | M60: 0.5455857 | O60: 482363.48 | P60: 198144.83 | Q60: 274969.34 | S60: 0.37516753 | T60: 0.36486534 | U60: 0.37765897 | W60: 328625.95 | X60: 130953.84 | Y60: 190336.07
B61: No | C61: 0.90280328 | D61: 0.90816562 | E61: 0.89925641 | G61: 4084963.5 | H61: 2078335.1 | I61: 1993442.6 | K61: 0.73107895 | L61: 0.72266609 | M61: 0.74185364 | O61: 3307953 | P61: 1653819.8 | Q61: 1644517.3 | S61: 0.53068886 | T61: 0.50672548 | U61: 0.5568342 | W61: 2401236.9 | X61: 1159640.2 | Y61: 1234372.1
B62: Refused / don't know | C62: 0.71378407 | D62: 0.71416259 | E62: 0.69944697 | G62: 90005.442 | H62: 47801.576 | I62: 39465.972 | K62: 0.53644299 | L62: 0.53596755 | M62: 0.52573198 | O62: 67643.409 | P62: 35874.315 | Q62: 29664.183 | S62: 0.3894286 | T62: 0.37134436 | U62: 0.40841731 | W62: 49105.457 | X62: 24855.469 | Y62: 23044.758
A63: Annual household income~^
B64: <$40,000 | C64: 0.73349163 | D64: 0.78524542 | E64: 0.69365738 | G64: 519637.31 | H64: 227146.04 | I64: 285986.73 | K64: 0.53384417 | L64: 0.56138147 | M64: 0.51176682 | O64: 378198.38 | P64: 162389.45 | Q64: 210995.4 | S64: 0.39546179 | T64: 0.38395176 | U64: 0.40195218 | W64: 280162.3 | X64: 111064.79 | Y64: 165720.13
B65: $40,000 - $69,999 | C65: 0.82455526 | D65: 0.8101484 | E65: 0.84012993 | G65: 646534.82 | H65: 275911.79 | I65: 367153.95 | K65: 0.65208601 | L65: 0.64192261 | M65: 0.66422351 | O65: 511301.46 | P65: 218619.22 | Q65: 290279.25 | S65: 0.46381687 | T65: 0.43485863 | U65: 0.48895531 | W65: 363679.4 | X65: 148099.56 | Y65: 213683.47
B66: $70,000 - $99,999 | C66: 0.87543794 | D66: 0.87823842 | E66: 0.87829291 | G66: 714707.72 | H66: 371171.24 | I66: 339949.78 | K66: 0.69000117 | L66: 0.67080943 | M66: 0.71483241 | O66: 563317.1 | P66: 283505.21 | Q66: 276681.18 | S66: 0.48968652 | T66: 0.46287257 | U66: 0.52155409 | W66: 399780.18 | X66: 195624.54 | Y66: 201871.38
B67: $100,000 - $149,999 | C67: 0.92455066 | D67: 0.93527111 | E67: 0.91250424 | G67: 1017766.1 | H67: 554956.03 | I67: 459995.9 | K67: 0.73981688 | L67: 0.73604124 | M67: 0.74544325 | O67: 814406.98 | P67: 436740.24 | Q67: 375780 | S67: 0.51464578 | T67: 0.48828559 | U67: 0.54816842 | W67: 566533.59 | X67: 289731 | Y67: 276333.21
B68: $150,000 - $199,999 | C68: 0.93391613 | D68: 0.92350288 | E68: 0.94698265 | G68: 557307.5 | H68: 292518.58 | I68: 261750.42 | K68: 0.75287786 | L68: 0.72478507 | M68: 0.78568669 | O68: 449274.26 | P68: 229574.92 | Q68: 217167.46 | S68: 0.5484446 | T68: 0.5308731 | U68: 0.56654199 | W68: 327280.23 | X68: 168153.51 | Y68: 156594.85
B69: $200,000+ | C69: 0.93327068 | D69: 0.92858196 | E69: 0.93960388 | G69: 619677.21 | H69: 358975.14 | I69: 259778.92 | K69: 0.80064166 | L69: 0.78835589 | M69: 0.81898917 | O69: 531613.6 | P69: 304765.95 | Q69: 226431.72 | S69: 0.58826195 | T69: 0.57364904 | U69: 0.60915425 | W69: 390596.78 | X69: 221763.67 | Y69: 168417.18
B70: Not stated | C70: 0.86000229 | D70: 0.83914959 | E70: 0.87475292 | G70: 736421.03 | H70: 306437.38 | I70: 423232.68 | K70: 0.71218868 | L70: 0.69074597 | M70: 0.72714583 | O70: 609848.06 | P70: 252243.93 | Q70: 351815.78 | S70: 0.52660891 | T70: 0.49568522 | U70: 0.54798615 | W70: 450935.86 | X70: 181012.4 | Y70: 265132.75
A71: Sexual orientation^
B72: Straight (heterosexual) | C72: 0.8703032 | D72: 0.8822819 | E72: 0.8597357 | G72: 4227655.7 | H72: 2070915.2 | I72: 2152023.2 | K72: 0.69834947 | L72: 0.69801242 | M72: 0.69923779 | O72: 3392359.2 | P72: 1638393 | Q72: 1750277.4 | S72: 0.50040622 | T72: 0.48049646 | U72: 0.51960906 | W72: 2430814 | X72: 1127833.9 | Y72: 1300644.8
B73: Gay or Lesbian | C73: 0.90134489 | D73: 0.90140538 | E73: 0.9018767 | G73: 230622.83 | H73: 176883.08 | I73: 49370.359 | K73: 0.72244713 | L73: 0.73441668 | M73: 0.70060371 | O73: 184849.11 | P73: 144114.83 | Q73: 38352.312 | S73: 0.5690656 | T73: 0.59317087 | U73: 0.49973198 | W73: 145604.11 | X73: 116398.12 | Y73: 27356.231
B74: Bisexual | C74: 0.88862246 | D74: 0.85057814 | E74: 0.91721632 | G74: 163978.43 | H74: 57828.581 | I74: 99246.689 | K74: 0.73132595 | L74: 0.6384484 | M74: 0.78698784 | O74: 134952.34 | P74: 43406.435 | Q74: 85155.415 | S74: 0.54029157 | T74: 0.46391967 | U74: 0.58869255 | W74: 99700.566 | X74: 31540.684 | Y74: 63699.026
B75: Other | C75: 0.86690889 | D75: 1 | E75: 0.80456468 | G75: 21745.337 | H75: 6242.0243 | I75: 9649.9968 | K75: 0.7421486 | L75: 0.82107961 | M75: 0.71706992 | O75: 18615.88 | P75: 5125.1989 | Q75: 8600.5794 | S75: 0.58002947 | T75: 0.47699858 | U75: 0.63245626 | W75: 14549.322 | X75: 2977.4367 | Y75: 7585.7181
A77: NB. Estimated participant numbers have not been rounded but users must remember that they are estimates and are subject to margins of error. Refer to sheet number 27 for margin of error and relative margin of error statistics.
A78: ~ As is common in population surveys, a large proportion of respondents refused to provide or did not know their household income
A79: ^ Question asked of 18+ year olds only
A80: # AusPlay collects data on gender, including non-binary and self-described. Non-binary and self-described gender are included in Total columns but not reported separately due to sample size. The sum of male and female estimates is not therefore equal to the total.
A81: * Estimate has relative margin of error between 50% and 100% and should be used with caution
A82: ** Estimate has relative margin of error greater than 100% and is considered too unreliable to use

Sheet 2
A8: =Index!A8 -> AusPlay survey results July 2024 - June 2025
A9: Released at: | B9: =Index!D9 -> 13 November 2025
A10: Table number: | B10: =Index!B14 -> 2
A11: Table name: | B11: =Index!D14 -> Demographics of participants (children) (organised outside of school hours)
A12: Base: | B12: Child population
C13: At least once per year participation
C14: Participation rate | G14: Estimated number of participants
C15: Total | D15: Males | E15: Females | G15: Total# | H15: Males | I15: Females
A16: Total | C16: 0.73214143 | D16: 0.73432868 | E16: 0.73189896 | G16: 895893.56 | H16: 478087.93 | I16: 417206.92
A17: Age group
B18: 0-4 | C18: 0.49966693 | D18: 0.47976559 | E18: 0.52100406 | G18: 190197.74 | H18: 97826.679 | I18: 91772.349
B19: 5-8 | C19: 0.82201643 | D19: 0.82510263 | E19: 0.82368095 | G19: 275470.33 | H19: 140638.57 | I19: 134831.76
B20: 9-11 | C20: 0.85018509 | D20: 0.87466939 | E20: 0.82780859 | G20: 211466.22 | H20: 113824.18 | I20: 97642.039
B21: 12-14 | C21: 0.84408334 | D21: 0.85830895 | E21: 0.82821936 | G21: 218759.28 | H21: 125798.5 | I21: 92960.778
A22: Remoteness
B23: Major cities | C23: 0.73663157 | D23: 0.74913361 | E23: 0.72530239 | G23: 700762.27 | H23: 378656.7 | I23: 321506.85
B24: Inner regional | C24: 0.72690454 | D24: 0.68018163 | E24: 0.7789363 | G24: 165120.12 | H24: 81406.374 | I24: 83713.746
B25: Outer regional | C25: 0.66395816 | D25: 0.69562799 | E25: 0.62141442 | G25: 30011.176 | H25: 18024.853 | I25: 11986.322
B26: Remote or very remote | C26: 0 | D26: 0 | E26: 0 | G26: 0 | H26: 0 | I26: 0
A27: Household structure
B28: Younger family (most children under 15 years) | C28: 0.71811855 | D28: 0.71670231 | E28: 0.72179954 | G28: 743080 | H28: 395110.61 | I28: 347370.68
B29: Mature family (most children 15 years or over) | C29: 0.76824435 | D29: 0.80154546 | E29: 0.7209045 | G29: 58228.976 | H29: 35664.746 | I29: 22564.23
B30: Mid family (equal number of children 15 years and over and under 15 years) | C30: 0.83623615 | D30: 0.85603039 | E30: 0.82244858 | G30: 94584.587 | H30: 47312.576 | I30: 47272.011
A31: Aboriginal or Torres Strait Islander origin of parent/guardian interviewed^
B32: Yes | C32: 0.7684783 | D32: 0.81327073 | E32: 0.72922135 | G32: 60538.928 | H32: 33240.506 | I32: 27298.422
B33: No | C33: 0.72998407 | D33: 0.72751817 | E33: 0.73457735 | G33: 816298.19 | H33: 431777.97 | I33: 383921.51
B34: Refused / don't know | C34: 0.71524812 | D34: 0.7831938 | E34: 0.60136056 | G34: 19056.446 | H34: 13069.454 | I34: 5986.9921
A35: Language spoken at home by parent/guardian interviewed^
B36: Speaks only English at home | C36: 0.72538148 | D36: 0.72310327 | E36: 0.72872754 | G36: 690959.07 | H36: 370397.57 | I36: 319962.79
B37: Speaks language other than English at home | C37: 0.75812506 | D37: 0.77708446 | E37: 0.74031286 | G37: 195372.56 | H37: 102647.05 | I37: 92725.511
A38: Annual household income~^
B39: <$40,000 | C39: 0.58679854 | D39: 0.65186485 | E39: 0.54542137 | G39: 35155.6 | H39: 17329.704 | I39: 17825.896
B40: $40,000 - $69,999 | C40: 0.72075624 | D40: 0.74800837 | E40: 0.69666816 | G40: 66183.793 | H40: 37315.804 | I40: 28867.989
B41: $70,000 - $99,999 | C41: 0.69245134 | D41: 0.68732266 | E41: 0.70093041 | G41: 117731.3 | H41: 60048.877 | I41: 57682.427
B42: $100,000 - $149,999 | C42: 0.74443802 | D42: 0.74052585 | E42: 0.74848263 | G42: 262733.88 | H42: 146866.65 | I42: 115268.52
B43: $150,000 - $199,999 | C43: 0.68385274 | D43: 0.65888806 | E43: 0.71608741 | G43: 139190.48 | H43: 75577.191 | I43: 63613.287
B44: $200,000+ | C44: 0.81950357 | D44: 0.83945316 | E44: 0.80011713 | G44: 189379.27 | H44: 95606.111 | I44: 93773.163
B45: Not stated | C45: 0.74789595 | D45: 0.75204437 | E45: 0.74978835 | G45: 85519.237 | H45: 45343.594 | I45: 40175.644
A47: NB. Please note that for children 0-14 years, data was collected via the child's parent/guardian for organised participation outside of school hours
A48: NB. Estimated participant numbers have not been rounded but users must remember that they are estimates and are subject to margins of error. Refer to sheet number 27 for margin of error and relative margin of error statistics.
A49: # AusPlay collects data on gender, including non-binary and self-described. Non-binary and self-described gender are included in Total columns but not reported separately due to sample size. The sum of male and female estimates is not therefore equal to the total.
A50: ~ As is common in population surveys, a large proportion of respondents refused to provide or did not know their household income
A51: ^ Question asked of 18+ year olds only
A52: * Estimate has relative margin of error between 50% and 100% and should be used with caution
A53: ** Estimate has relative margin of error greater than 100% and is considered too unreliable to use

Sheet 3
A8: =Index!A8 -> AusPlay survey results July 2024 - June 2025
A9: Released at: | C9: 13 November 2025
A10: Table number: | C10: 3
A11: Table name: | C11: Organisational nature of activity - overview (adults)
A12: Base: | C12: Adult population
E13: Organisational nature of activity
C14: Total | E14: Informal only | F14: Mix of informal and organised | G14: Organised only | H14: Don't know | I14: Total informal | J14: Total organised
E15: (a) | F15: (b) | G15: (c) | H15: (d) | I15: (a + b) | J15: (b + c)
C16: Participation rate
A17: All# | B17: Total | C17: 0.86963983 | E17: 0.42890993 | F17: 0.36708204 | G17: 0.06694066 | H17: 0.006707196 | I17: 0.79599197 | J17: 0.4340227
B18: 15-17 | C18: 0.84583468 | E18: 0.21085199 | F18: 0.54794244 | G18: 0.052410273 | H18: 0.034629981 | I18: 0.75879443 | J18: 0.60035271
B19: 18-24 | C19: 0.88919859 | E19: 0.33648746 | F19: 0.48431627 | G19: 0.065496993 | H19: 0.0028978696 | I19: 0.82080373 | J19: 0.54981326
B20: 25-34 | C20: 0.91865092 | E20: 0.3770978 | F20: 0.46759545 | G20: 0.06819255 | H20: 0.005765119 | I20: 0.84469325 | J20: 0.535788
B21: 35-44 | C21: 0.89233389 | E21: 0.4392554 | F21: 0.36511301 | G21: 0.082833669 | H21: 0.005131807 | I21: 0.80436841 | J21: 0.44794668
B22: 45-54 | C22: 0.89145479 | E22: 0.51446195 | F22: 0.3242638 | G22: 0.048763049 | H22: 0.0039659985 | I22: 0.83872575 | J22: 0.37302685
B23: 55-64 | C23: 0.8752102 | E23: 0.53538838 | F23: 0.28875054 | G23: 0.043577101 | H23: 0.0074941824 | I23: 0.82413892 | J23: 0.33232764
B24: 65+ | C24: 0.78038467 | E24: 0.43425343 | F24: 0.25506469 | G24: 0.084172258 | H24: 0.0068942862 | I24: 0.68931812 | J24: 0.33923695
A26: Males | B26: Total | C26: 0.87734998 | E26: 0.44169811 | F26: 0.36410883 | G26: 0.065213506 | H26: 0.0063295288 | I26: 0.80580694 | J26: 0.42932234
B27: 15-17 | C27: 0.81985642 | E27: 0.15703661 | F27: 0.60428421 | G27: 0.031338435 | H27: 0.027197177 | I27: 0.76132081 | J27: 0.63562264
B28: 18-24 | C28: 0.88133157 | E28: 0.32876131 | F28: 0.47759893 | G28: 0.071064521 | H28: 0.0039068081 | I28: 0.80636024 | J28: 0.54866345
B29: 25-34 | C29: 0.92020703 | E29: 0.38129064 | F29: 0.46042584 | G29: 0.07389466 | H29: 0.0045958882 | I29: 0.84171648 | J29: 0.5343205
B30: 35-44 | C30: 0.88795492 | E30: 0.44169799 | F30: 0.34807441 | G30: 0.090208515 | H30: 0.0079739939 | I30: 0.78977241 | J30: 0.43828293
B31: 45-54 | C31: 0.90325368 | E31: 0.53869578 | F31: 0.30475072 | G31: 0.053906312 | H31: 0.0059008748 | I31: 0.84344649 | J31: 0.35865703
B32: 55-64 | C32: 0.87325812 | E32: 0.54025084 | F32: 0.28203281 | G32: 0.045713953 | H32: 0.0052605224 | I32: 0.82228365 | J32: 0.32774677
B33: 65+ | C33: 0.81769266 | E33: 0.48248767 | F33: 0.27169076 | G33: 0.058216697 | H33: 0.0052975354 | I33: 0.75417843 | J33: 0.32990746
A35: Females | B35: Total | C35: 0.8644377 | E35: 0.4168461 | F35: 0.37166088 | G35: 0.069154196 | H35: 0.0067765193 | I35: 0.78850698 | J35: 0.44081507
B36: 15-17 | C36: 0.88504676 | E36: 0.2544727 | F36: 0.52103031 | G36: 0.068754625 | H36: 0.040789123 | I36: 0.77550301 | J36: 0.58978493
B37: 18-24 | C37: 0.90036213 | E37: 0.33935105 | F37: 0.49996171 | G37: 0.059269497 | H37: 0.0017798797 | I37: 0.83931275 | J37: 0.5592312
B38: 25-34 | C38: 0.91694021 | E38: 0.37039181 | F38: 0.47704141 | G38: 0.063798419 | H38: 0.0057085731 | I38: 0.84743321 | J38: 0.54083982
B39: 35-44 | C39: 0.89883808 | E39: 0.43634748 | F39: 0.38397116 | G39: 0.076246761 | H39: 0.0022726681 | I39: 0.82031865 | J39: 0.46021792
B40: 45-54 | C40: 0.87860481 | E40: 0.49310941 | F40: 0.34133574 | G40: 0.043105286 | H40: 0.0010543762 | I40: 0.83444515 | J40: 0.38444102
B41: 55-64 | C41: 0.87649254 | E41: 0.53077722 | F41: 0.29427871 | G41: 0.041683206 | H41: 0.0097533992 | I41: 0.82505593 | J41: 0.33596192
B42: 65+ | C42: 0.75356774 | E42: 0.39495702 | F42: 0.24307167 | G42: 0.10721203 | H42: 0.0083270205 | I42: 0.63802869 | J42: 0.3502837
C43: Estimated number of participants
A44: All# | B44: Total | C44: 5015652.8 | E44: 2473740.6 | F44: 2117147.8 | G44: 386080.65 | H44: 38683.792 | I44: 4590888.4 | J44: 2503228.5
B45: 15-17 | C45: 203601.17 | E45: 50754.258 | F45: 131895.42 | G45: 12615.696 | H45: 8335.7952 | I45: 182649.68 | J45: 144511.12
B46: 18-24 | C46: 603392.95 | E46: 228333.87 | F46: 328647.64 | G46: 44444.991 | H46: 1966.4382 | I46: 556981.52 | J46: 373092.63
B47: 25-34 | C47: 970562.03 | E47: 398406.84 | F47: 494018.32 | G47: 72045.973 | H47: 6090.8942 | I47: 892425.16 | J47: 566064.3
B48: 35-44 | C48: 896984.71 | E48: 441544.79 | F48: 367015.97 | G48: 83265.396 | H48: 5158.5539 | I48: 808560.76 | J48: 450281.37
B49: 45-54 | C49: 769097.39 | E49: 443849.03 | F49: 279756.69 | G49: 42070.034 | H49: 3421.642 | I49: 723605.72 | J49: 321826.73
B50: 55-64 | C50: 652990.96 | E50: 399451.21 | F50: 215435.66 | G50: 32512.707 | H50: 5591.3806 | I50: 614886.87 | J50: 247948.37
B51: 65+ | C51: 919023.6 | E51: 511400.56 | F51: 300378.11 | G51: 99125.848 | H51: 8119.088 | I51: 811778.67 | J51: 399503.96
A53: Males | B53: Total | C53: 2468235.6 | E53: 1242622.7 | F53: 1024341.9 | G53: 183464.18 | H53: 17806.769 | I53: 2266964.7 | J53: 1207806.1
B54: 15-17 | C54: 81119.411 | E54: 15537.741 | F54: 59789.955 | G54: 3100.7324 | H54: 2690.9821 | I54: 75327.696 | J54: 62890.687
B55: 18-24 | C55: 321407.44 | E55: 119893.96 | F55: 174172.64 | G55: 25916.087 | H55: 1424.75 | I55: 294066.6 | J55: 200088.73
B56: 25-34 | C56: 465225.36 | E56: 192767.57 | F56: 232775.64 | G56: 37358.626 | H56: 2323.5247 | I56: 425543.21 | J56: 270134.27
B57: 35-44 | C57: 449706.14 | E57: 223698.63 | F57: 176282.82 | G57: 45686.242 | H57: 4038.4415 | I57: 399981.45 | J57: 221969.07
B58: 45-54 | C58: 384156.93 | E58: 229109.19 | F58: 129611.54 | G58: 22926.542 | H58: 2509.6626 | I58: 358720.73 | J58: 152538.08
B59: 55-64 | C59: 323892.01 | E59: 200379.39 | F59: 104606.16 | G59: 16955.335 | H59: 1951.1312 | I59: 304985.55 | J59: 121561.49
B60: 65+ | C60: 442728.31 | E60: 261236.23 | F60: 147103.18 | G60: 31520.62 | H60: 2868.2768 | I60: 408339.41 | J60: 178623.8
A62: Females | B62: Total | C62: 2520330.1 | E62: 1215344.7 | F62: 1083604 | G62: 201624.02 | H62: 19757.428 | I62: 2298948.7 | J62: 1285228
B63: 15-17 | C63: 122481.76 | E63: 35216.517 | F63: 72105.465 | G63: 9514.9632 | H63: 5644.8131 | I63: 107321.98 | J63: 81620.429
B64: 18-24 | C64: 274016 | E64: 103278.02 | F64: 152158.23 | G64: 18038.065 | H64: 541.68818 | I64: 255436.25 | J64: 170196.29
B65: 25-34 | C65: 498542.5 | E65: 201382.88 | F65: 259368.51 | G65: 34687.347 | H65: 3103.7643 | I65: 460751.39 | J65: 294055.86
B66: 35-44 | C66: 443003.41 | E66: 215059.23 | F66: 189244.92 | G66: 37579.155 | H66: 1120.1124 | I66: 404304.14 | J66: 226824.07
B67: 45-54 | C67: 379973.22 | E67: 213256.71 | F67: 147618.63 | G67: 18641.89 | H67: 455.98969 | I67: 360875.34 | J67: 166260.52
B68: 55-64 | C68: 327132.25 | E68: 198101.34 | F68: 109833.29 | G68: 15557.372 | H68: 3640.2494 | I68: 307934.63 | J68: 125390.66
B69: 65+ | C69: 475181 | E69: 249050.04 | F69: 153274.93 | G69: 67605.228 | H69: 5250.8112 | I69: 402324.96 | J69: 220880.16
A71: NB. Estimated participant numbers have not been rounded but users must remember that they are estimates and are subject to margins of error. Refer to sheet number 27 for margin of error and relative margin of error statistics.
A72: * Estimate has relative margin of error between 50% and 100% and should be used with caution
A73: ** Estimate has relative margin of error greater than 100% and is considered too unreliable to use
A74: # AusPlay collects data on gender, including non-binary and self-described. Non-binary and self-described gender are included in Total columns but not reported separately due to sample size. The sum of male and female estimates is not therefore equal to the total.

Sheet 4
A8: =Index!A8 -> AusPlay survey results July 2024 - June 2025
A9: Released at: | C9: 13 November 2025
A10: Table number: | C10: 4
A11: Table name: | C11: Organisational nature of activity - detail (adults)
A12: Base: | C12: Adult population
E13: Informal participation | H13: Organised participation | S13: Other
C14: Total | E14: Informally by myself | F14: Informally with family and friends | H14: Sports club or association | I14: Gym/fitness club/sports/ leisure centre | J14: Private or commercial business | K14: Community organisation | L14: Individual personal trainer or coach | M14: Event (e.g. marathon, parkrun) | N14: Recreation club or association | O14: Less formal group (e.g. social group) | P14: Work | Q14: Educational institution | S14: Other | T14: Don't know
C15: Participation rate
A16: All# | B16: Total | C16: 0.86963983 | E16: 0.69950717 | F16: 0.50707375 | H16: 0.13999695 | I16: 0.11429196 | J16: 0.11229376 | K16: 0.07460163 | L16: 0.070460771 | M16: 0.063409976 | N16: 0.065158253 | O16: 0.048988487 | P16: 0.046018059 | Q16: 0.044744842 | S16: 0.014171424 | T16: 0.012742963
B17: 15-17 | C17: 0.84583468 | E17: 0.6479657 | F17: 0.60810517 | H17: 0.2369585 | I17: 0.10024092 | J17: 0.076429833 | K17: 0.12257092 | L17: 0.067718353 | M17: 0.086748114 | N17: 0.09558657 | O17: 0.098657037 | P17: 0.045714415 | Q17: 0.27054284 | S17: 0.024051304 | T17: 0.068162694
B18: 18-24 | C18: 0.88919859 | E18: 0.71750543 | F18: 0.61087701 | H18: 0.23475734 | I18: 0.1315749 | J18: 0.13171769 | K18: 0.09922936 | L18: 0.10751977 | M18: 0.098525485 | N18: 0.10880481 | O18: 0.058736357 | P18: 0.059167243 | Q18: 0.12012419 | S18: 0.0038543278 | T18: 0.017235061
B19: 25-34 | C19: 0.91865092 | E19: 0.74652175 | F19: 0.57750683 | H19: 0.17954233 | I19: 0.17111296 | J19: 0.17936667 | K19: 0.10423881 | L19: 0.10774985 | M19: 0.098398332 | N19: 0.092267354 | O19: 0.055175782 | P19: 0.09584664 | Q19: 0.057760757 | S19: 0.0096514544 | T19: 0.016830559
B20: 35-44 | C20: 0.89233389 | E20: 0.71827903 | F20: 0.49528896 | H20: 0.13209301 | I20: 0.11533463 | J20: 0.13994641 | K20: 0.060043821 | L20: 0.064149244 | M20: 0.073980993 | N20: 0.059833415 | O20: 0.039351112 | P20: 0.050170723 | Q20: 0.029914127 | S20: 0.0074041933 | T20: 0.011351057
B21: 45-54 | C21: 0.89145479 | E21: 0.74623568 | F21: 0.50011619 | H21: 0.10639953 | I21: 0.091813734 | J21: 0.09575606 | K21: 0.047143617 | L21: 0.053081357 | M21: 0.064586823 | N21: 0.038522045 | O21: 0.042633447 | P21: 0.044287416 | Q21: 0.013823881 | S21: 0.015198725 | T21: 0.0074166429
B22: 55-64 | C22: 0.8752102 | E22: 0.74421363 | F22: 0.50430096 | H22: 0.087067694 | I22: 0.089229238 | J22: 0.087991421 | K22: 0.043513078 | L22: 0.047890956 | M22: 0.03519148 | N22: 0.032952641 | O22: 0.04618946 | P22: 0.023790412 | Q22: 0.005853597 | S22: 0.01901255 | T22: 0.0049744691
B23: 65+ | C23: 0.78038467 | E23: 0.57891345 | F23: 0.38033563 | H23: 0.094991581 | I23: 0.087685353 | J23: 0.052167453 | K23: 0.076255294 | L23: 0.048632696 | M23: 0.015009001 | N23: 0.053931025 | O23: 0.042323838 | P23: 0.0056061834 | Q23: 0.0034315428 | S23: 0.02410849 | T23: 0.0051715763
A25: Males | B25: Total | C25: 0.87734998 | E25: 0.7043859 | F25: 0.50149312 | H25: 0.18163806 | I25: 0.091070638 | J25: 0.078125531 | K25: 0.081764683 | L25: 0.066107034 | M25: 0.067575349 | N25: 0.077478785 | O25: 0.051702894 | P25: 0.05583289 | Q25: 0.052810091 | S25: 0.0091104394 | T25: 0.014103448
B26: 15-17 | C26: 0.81985642 | E26: 0.60335897 | F26: 0.61999149 | H26: 0.22257342 | I26: 0.09403515 | J26: 0.051415591 | K26: 0.1248395 | L26: 0.068459882 | M26: 0.06572958 | N26: 0.1099877 | O26: 0.10863404 | P26: 0.020077156 | Q26: 0.32323802 | S26: 0.041491322 | T26: 0.041491322
B27: 18-24 | C27: 0.88133157 | E27: 0.67417756 | F27: 0.58522429 | H27: 0.27517409 | I27: 0.11818611 | J27: 0.085346586 | K27: 0.11331675 | L27: 0.11238997 | M27: 0.10686851 | N27: 0.12110459 | O27: 0.070340582 | P27: 0.066141161 | Q27: 0.1378947 | S27: 0.0014593733 | T27: 0.018113091
B28: 25-34 | C28: 0.92020703 | E28: 0.73211225 | F28: 0.54109846 | H28: 0.23658044 | I28: 0.14903182 | J28: 0.12566921 | K28: 0.12918985 | L28: 0.10738437 | M28: 0.10475806 | N28: 0.12616724 | O28: 0.055862571 | P28: 0.12873199 | Q28: 0.072929351 | S28: 0.0034249193 | T28: 0.018095603
B29: 35-44 | C29: 0.88795492 | E29: 0.70775922 | F29: 0.47723342 | H29: 0.16994079 | I29: 0.10766307 | J29: 0.085458911 | K29: 0.069189835 | L29: 0.055336431 | M29: 0.075449248 | N29: 0.071573292 | O29: 0.040251034 | P29: 0.061794877 | Q29: 0.038115179 | S29: 0.0052144367 | T29: 0.017105831
B30: 45-54 | C30: 0.90325368 | E30: 0.75390408 | F30: 0.48079939 | H30: 0.13028131 | I30: 0.074921278 | J30: 0.07241366 | K30: 0.054393823 | L30: 0.045027298 | M30: 0.064154956 | N30: 0.044720538 | O30: 0.04101965 | P30: 0.050477972 | Q30: 0.015362332 | S30: 0.0058230554 | T30: 0.0081962508
B31: 55-64 | C31: 0.87325812 | E31: 0.74408211 | F31: 0.50357173 | H31: 0.11694859 | I31: 0.057671053 | J31: 0.059791721 | K31: 0.045704863 | L31: 0.04202668 | M31: 0.034599581 | N31: 0.044360918 | O31: 0.059116485 | P31: 0.024967922 | Q31: 0.0066940806 | S31: 0.0091840028 | T31: 0.0064544096
B32: 65+ | C32: 0.81769266 | E32: 0.64805962 | F32: 0.42398325 | H32: 0.15545086 | I32: 0.038188954 | J32: 0.043935348 | K32: 0.066322476 | L32: 0.039089322 | M32: 0.02463846 | N32: 0.050633666 | O32: 0.038886808 | P32: 0.007127369 | Q32: 0.0020482624 | S32: 0.019831443 | T32: 0.0097417568
A34: Females | B34: Total | C34: 0.8644377 | E34: 0.69566263 | F34: 0.51383389 | H34: 0.10122022 | I34: 0.13704474 | J34: 0.14576029 | K34: 0.068538912 | L34: 0.075082883 | M34: 0.059911789 | N34: 0.053768047 | O34: 0.045709409 | P34: 0.03665636 | Q34: 0.03738591 | S34: 0.018742677 | T34: 0.011181966
B35: 15-17 | C35: 0.88504676 | E35: 0.69566833 | F35: 0.6144449 | H35: 0.25302513 | I35: 0.1071237 | J35: 0.096178931 | K35: 0.12393976 | L35: 0.068840541 | M35: 0.10389221 | N35: 0.087622685 | O35: 0.093931147 | P35: 0.065159479 | Q35: 0.23946923 | S35: 0.012169247 | T35: 0.088894853
B36: 18-24 | C36: 0.90036213 | E36: 0.76738221 | F36: 0.64433346 | H36: 0.19070559 | I36: 0.14851089 | J36: 0.18821374 | K36: 0.085464764 | L36: 0.10506027 | M36: 0.09162214 | N36: 0.095795932 | O36: 0.043709877 | P36: 0.052668533 | Q36: 0.10097588 | S36: 0.0051606566 | T36: 0.016724156
B37: 25-34 | C37: 0.91694021 | E37: 0.75858533 | F37: 0.60976048 | H37: 0.1288957 | I37: 0.19299196 | J37: 0.23078626 | K37: 0.082425887 | L37: 0.10862464 | M37: 0.093794917 | N37: 0.061973862 | O37: 0.054435701 | P37: 0.065764888 | Q37: 0.044425235 | S37: 0.014669958 | T37: 0.014657825
B38: 35-44 | C38: 0.89883808 | E38: 0.72901044 | F38: 0.51662278 | H38: 0.094782458 | I38: 0.12359365 | J38: 0.197611 | K38: 0.051364184 | L38: 0.072968448 | M38: 0.072295001 | N38: 0.048485878 | O38: 0.036882001 | P38: 0.038826464 | Q38: 0.02184494 | S38: 0.0097429328 | T38: 0.0055734518
B39: 45-54 | C39: 0.87860481 | E39: 0.73904837 | F39: 0.51678766 | H39: 0.083192681 | I39: 0.10737775 | J39: 0.11769584 | K39: 0.039612008 | L39: 0.061611563 | M39: 0.064810273 | N39: 0.031590855 | O39: 0.041318427 | P39: 0.037430252 | Q39: 0.012469713 | S39: 0.023539147 | T39: 0.0054572337
B40: 55-64 | C40: 0.87649254 | E40: 0.74299648 | F40: 0.5063837 | H40: 0.057831982 | I40: 0.11969096 | J40: 0.11510909 | K40: 0.041564254 | L40: 0.052601214 | M40: 0.035965125 | N40: 0.021789167 | O40: 0.033586462 | P40: 0.021446213 | Q40: 0.0050492014 | S40: 0.028879973 | T40: 0.0035299728
B41: 65+ | C41: 0.75356774 | E41: 0.52295591 | F41: 0.34626201 | H41: 0.043929058 | I41: 0.13096964 | J41: 0.059702743 | K41: 0.085466462 | L41: 0.057262257 | M41: 0.0068751023 | N41: 0.057244935 | O41: 0.045653794 | P41: 0.0043502088 | Q41: 0.0046499924 | S41: 0.027996694 | T41: 0.0012937272
C42: Estimated number of participants
A43: All# | B43: Total | C43: 5015652.8 | E43: 4034411.7 | F43: 2924550.8 | H43: 807433.26 | I43: 659179.57 | J43: 647654.94 | K43: 430265.34 | L43: 406382.91 | M43: 365717.41 | N43: 375800.6 | O43: 282541.39 | P43: 265409.42 | Q43: 258066.14 | S43: 81733.768 | T43: 73495.111
B44: 15-17 | C44: 203601.17 | E44: 155972.06 | F44: 146377.21 | H44: 57038.365 | I44: 24129.027 | J44: 18397.452 | K44: 29504.091 | L44: 16300.509 | M44: 20881.17 | N44: 23008.677 | O44: 23747.771 | P44: 11003.933 | Q44: 65122.463 | S44: 5789.3979 | T44: 16407.466
B45: 18-24 | C45: 603392.95 | E45: 486885.3 | F45: 414529.31 | H45: 159301.79 | I45: 89284.177 | J45: 89381.075 | K45: 67335.123 | L45: 72960.831 | M45: 66857.487 | N45: 73832.837 | O45: 39857.355 | P45: 40149.746 | Q45: 81513.947 | S45: 2615.4722 | T45: 11695.379
B46: 25-34 | C46: 970562.03 | E46: 788706.19 | F46: 610140.58 | H46: 189687.91 | I46: 180782.21 | J46: 189502.32 | K46: 110129.14 | L46: 113838.58 | M46: 103958.62 | N46: 97481.197 | O46: 58293.655 | P46: 101262.74 | Q46: 61024.701 | S46: 10196.839 | T46: 17781.62
B47: 35-44 | C47: 896984.71 | E47: 722022.69 | F47: 497870.39 | H47: 132781.48 | I47: 115935.75 | J47: 140675.81 | K47: 60356.769 | L47: 64483.589 | M47: 74366.581 | N47: 60145.266 | O47: 39556.209 | P47: 50432.211 | Q47: 30070.039 | S47: 7442.7838 | T47: 11410.219
B48: 45-54 | C48: 769097.39 | E48: 643810.46 | F48: 431472.31 | H48: 91795.574 | I48: 79211.761 | J48: 82612.979 | K48: 40672.879 | L48: 45795.629 | M48: 55721.902 | N48: 33234.668 | O48: 36781.756 | P48: 38208.709 | Q48: 11926.473 | S48: 13112.611 | T48: 6398.6651
B49: 55-64 | C49: 652990.96 | E49: 555254.92 | F49: 376257 | H49: 64960.871 | I49: 66573.59 | J49: 65650.06 | K49: 32464.94 | L49: 35731.257 | M49: 26256.227 | N49: 24585.838 | O49: 34461.778 | P49: 17749.935 | Q49: 4367.3462 | S49: 14185.19 | T49: 3711.4322
B50: 65+ | C50: 919023.6 | E50: 681760.1 | F50: 447904.01 | H50: 111867.27 | I50: 103263.06 | J50: 61435.242 | K50: 89802.399 | L50: 57272.519 | M50: 17675.419 | N50: 63512.121 | O50: 49842.863 | P50: 6602.1478 | Q50: 4041.1723 | S50: 28391.475 | T50: 6090.3307
A52: Males | B52: Total | C52: 2468235.6 | E52: 1981638.3 | F52: 1410843.1 | H52: 510999.65 | I52: 256207.67 | J52: 219789.39 | K52: 230027.36 | L52: 185977.93 | M52: 190108.72 | N52: 217969.91 | O52: 145454.98 | P52: 157073.84 | Q52: 148569.84 | S52: 25630.263 | T52: 39677.02
B53: 15-17 | C53: 81119.411 | E53: 59698.409 | F53: 61344.087 | H53: 22022.178 | I53: 9304.1608 | J53: 5087.2352 | K53: 12352.049 | L53: 6773.6558 | M53: 6503.5104 | N53: 10882.56 | O53: 10748.625 | P53: 1986.5027 | Q53: 31982.28 | S53: 4105.2939 | T53: 4105.2939
B54: 18-24 | C54: 321407.44 | E54: 245861.7 | F54: 213421.88 | H54: 100351.56 | I54: 43100.572 | J54: 31124.526 | K54: 41324.796 | L54: 40986.815 | M54: 38973.226 | N54: 44164.893 | O54: 25652.078 | P54: 24120.617 | Q54: 50287.976 | S54: 532.20996 | T54: 6605.5528
B55: 25-34 | C55: 465225.36 | E55: 370131.04 | F55: 273560.97 | H55: 119607.02 | I55: 75345.415 | J55: 63534.078 | K55: 65313.993 | L55: 54289.883 | M55: 52962.111 | N55: 63785.865 | O55: 28242.215 | P55: 65082.516 | Q55: 36870.599 | S55: 1731.5227 | T55: 9148.5212
B56: 35-44 | C56: 449706.14 | E56: 358445.75 | F56: 241695.6 | H56: 86066.775 | I56: 54526.129 | J56: 43280.797 | K56: 35041.298 | L56: 28025.221 | M56: 38211.388 | N56: 36248.404 | O56: 20385.198 | P56: 31296.111 | Q56: 19303.491 | S56: 2640.8595 | T56: 8663.2743
B57: 45-54 | C57: 384156.93 | E57: 320638.03 | F57: 204485.65 | H57: 55409.095 | I57: 31864.28 | J57: 30797.782 | K57: 23133.882 | L57: 19150.266 | M57: 27285.326 | N57: 19019.801 | O57: 17445.8 | P57: 21468.457 | Q57: 6533.6532 | S57: 2476.5657 | T57: 3485.894
B58: 55-64 | C58: 323892.01 | E58: 275980.54 | F58: 186775.09 | H58: 43376.31 | I58: 21390.231 | J58: 22176.789 | K58: 16951.964 | L58: 15587.723 | M58: 12833.008 | N58: 16453.494 | O58: 21926.343 | P58: 9260.6185 | Q58: 2482.8389 | S58: 3406.3527 | T58: 2393.9448
B59: 65+ | C59: 442728.31 | E59: 350882.86 | F59: 229559.83 | H59: 84166.707 | I59: 20676.877 | J59: 23788.183 | K59: 35909.381 | L59: 21164.369 | M59: 13340.152 | N59: 27414.894 | O59: 21054.721 | P59: 3859.0147 | Q59: 1109.0032 | S59: 10737.459 | T59: 5274.5386
A61: Females | B61: Total | C61: 2520330.1 | E61: 2028254.3 | F61: 1498119.6 | H61: 295114.82 | I61: 399563.77 | J61: 424974.58 | K61: 199830.12 | L61: 218909.53 | M61: 174677.12 | N61: 156764.6 | O61: 133269.06 | P61: 106874.25 | Q61: 109001.3 | S61: 54645.62 | T61: 32601.824
B62: 15-17 | C62: 122481.76 | E62: 96273.648 | F62: 85033.126 | H62: 35016.187 | I62: 14824.866 | J62: 13310.217 | K62: 17152.042 | L62: 9526.8532 | M62: 14377.659 | N62: 12126.117 | O62: 12999.146 | P62: 9017.4304 | Q62: 33140.183 | S62: 1684.104 | T62: 12302.173
B63: 18-24 | C63: 274016 | E63: 233544.92 | F63: 196096.29 | H63: 58039.295 | I63: 45197.77 | J63: 57280.925 | K63: 26010.326 | L63: 31974.017 | M63: 27884.261 | N63: 29154.511 | O63: 13302.654 | P63: 16029.129 | Q63: 30730.975 | S63: 1570.593 | T63: 5089.8258
B64: 25-34 | C64: 498542.5 | E64: 412444.59 | F64: 331528.18 | H64: 70080.887 | I64: 104930.17 | J64: 125479.02 | K64: 44815.145 | L64: 59059.468 | M64: 50996.512 | N64: 33695.332 | O64: 29596.816 | P64: 35756.521 | Q64: 24154.103 | S64: 7976.0899 | T64: 7969.4933
B65: 35-44 | C65: 443003.41 | E65: 359301.77 | F65: 254623.9 | H65: 46714.701 | I65: 60914.65 | J65: 97395.013 | K65: 25315.47 | L65: 35963.398 | M65: 35631.481 | N65: 23896.862 | O65: 18177.748 | P65: 19136.101 | Q65: 10766.548 | S65: 4801.9244 | T65: 2746.9443
B66: 45-54 | C66: 379973.22 | E66: 319618.77 | F66: 223496.92 | H66: 35978.623 | I66: 46438.022 | J66: 50900.32 | K66: 17131.14 | L66: 26645.363 | M66: 28028.72 | N66: 13662.205 | O66: 17869.121 | P66: 16187.589 | Q66: 5392.8194 | S66: 10180.055 | T66: 2360.1085
B67: 55-64 | C67: 327132.25 | E67: 277307.68 | F67: 188996.97 | H67: 21584.561 | I67: 44672.112 | J67: 42962.025 | K67: 15512.976 | L67: 19632.287 | M67: 13423.22 | N67: 8132.3444 | O67: 12535.435 | P67: 8004.3442 | Q67: 1884.5073 | S67: 10778.838 | T67: 1317.4875
B68: 65+ | C68: 475181 | E68: 329762.94 | F68: 218344.18 | H68: 27700.567 | I68: 82586.183 | J68: 37647.059 | K68: 53893.017 | L68: 36108.149 | M68: 4335.2679 | N68: 36097.227 | O68: 28788.143 | P68: 2743.1331 | Q68: 2932.1691 | S68: 17654.016 | T68: 815.79205
A70: NB. Estimated participant numbers have not been rounded but users must remember that they are estimates and are subject to margins of error. Refer to sheet number 27 for margin of error and relative margin of error statistics.
A71: * Estimate has relative margin of error between 50% and 100% and should be used with caution
A72: ** Estimate has relative margin of error greater than 100% and is considered too unreliable to use
A73: # AusPlay collects data on gender, including non-binary and self-described. Non-binary and self-described gender are included in Total columns but not reported separately due to sample size. The sum of male and female estimates is not therefore equal to the total.

Sheet 5
A8: =Index!A8 -> AusPlay survey results July 2024 - June 2025
A9: Released at: | C9: 13 November 2025
A10: Table number: | C10: 5
A11: Table name: | C11: Organised activity by type of entity (adults)
A12: Base: | C12: Adult population
E13: Type of entity organising the activity
C14: Total organised | E14: Sports club or association | F14: Gym/fitness club/sports/ leisure centre | G14: Private or commercial business | H14: Community organisation | I14: Individual personal trainer or coach | J14: Event (e.g. marathon, parkrun) | K14: Recreation club or association | L14: Less formal group (e.g. social group) | M14: Work | N14: Educational institution
C15: Participation rate
A16: All# | B16: Total | C16: 0.4340227 | E16: 0.13999695 | F16: 0.11429196 | G16: 0.11229376 | H16: 0.07460163 | I16: 0.070460771 | J16: 0.063409976 | K16: 0.065158253 | L16: 0.048988487 | M16: 0.046018059 | N16: 0.044744842
B17: 15-17 | C17: 0.60035271 | E17: 0.2369585 | F17: 0.10024092 | G17: 0.076429833 | H17: 0.12257092 | I17: 0.067718353 | J17: 0.086748114 | K17: 0.09558657 | L17: 0.098657037 | M17: 0.045714415 | N17: 0.27054284
B18: 18-24 | C18: 0.54981326 | E18: 0.23475734 | F18: 0.1315749 | G18: 0.13171769 | H18: 0.09922936 | I18: 0.10751977 | J18: 0.098525485 | K18: 0.10880481 | L18: 0.058736357 | M18: 0.059167243 | N18: 0.12012419
B19: 25-34 | C19: 0.535788 | E19: 0.17954233 | F19: 0.17111296 | G19: 0.17936667 | H19: 0.10423881 | I19: 0.10774985 | J19: 0.098398332 | K19: 0.092267354 | L19: 0.055175782 | M19: 0.09584664 | N19: 0.057760757
B20: 35-44 | C20: 0.44794668 | E20: 0.13209301 | F20: 0.11533463 | G20: 0.13994641 | H20: 0.060043821 | I20: 0.064149244 | J20: 0.073980993 | K20: 0.059833415 | L20: 0.039351112 | M20: 0.050170723 | N20: 0.029914127
B21: 45-54 | C21: 0.37302685 | E21: 0.10639953 | F21: 0.091813734 | G21: 0.09575606 | H21: 0.047143617 | I21: 0.053081357 | J21: 0.064586823 | K21: 0.038522045 | L21: 0.042633447 | M21: 0.044287416 | N21: 0.013823881
B22: 55-64 | C22: 0.33232764 | E22: 0.087067694 | F22: 0.089229238 | G22: 0.087991421 | H22: 0.043513078 | I22: 0.047890956 | J22: 0.03519148 | K22: 0.032952641 | L22: 0.04618946 | M22: 0.023790412 | N22: 0.005853597
B23: 65+ | C23: 0.33923695 | E23: 0.094991581 | F23: 0.087685353 | G23: 0.052167453 | H23: 0.076255294 | I23: 0.048632696 | J23: 0.015009001 | K23: 0.053931025 | L23: 0.042323838 | M23: 0.0056061834 | N23: 0.0034315428
A25: Males | B25: Total | C25: 0.42932234 | E25: 0.18163806 | F25: 0.091070638 | G25: 0.078125531 | H25: 0.081764683 | I25: 0.066107034 | J25: 0.067575349 | K25: 0.077478785 | L25: 0.051702894 | M25: 0.05583289 | N25: 0.052810091
B26: 15-17 | C26: 0.63562264 | E26: 0.22257342 | F26: 0.09403515 | G26: 0.051415591 | H26: 0.1248395 | I26: 0.068459882 | J26: 0.06572958 | K26: 0.1099877 | L26: 0.10863404 | M26: 0.020077156 | N26: 0.32323802
B27: 18-24 | C27: 0.54866345 | E27: 0.27517409 | F27: 0.11818611 | G27: 0.085346586 | H27: 0.11331675 | I27: 0.11238997 | J27: 0.10686851 | K27: 0.12110459 | L27: 0.070340582 | M27: 0.066141161 | N27: 0.1378947
B28: 25-34 | C28: 0.5343205 | E28: 0.23658044 | F28: 0.14903182 | G28: 0.12566921 | H28: 0.12918985 | I28: 0.10738437 | J28: 0.10475806 | K28: 0.12616724 | L28: 0.055862571 | M28: 0.12873199 | N28: 0.072929351
B29: 35-44 | C29: 0.43828293 | E29: 0.16994079 | F29: 0.10766307 | G29: 0.085458911 | H29: 0.069189835 | I29: 0.055336431 | J29: 0.075449248 | K29: 0.071573292 | L29: 0.040251034 | M29: 0.061794877 | N29: 0.038115179
B30: 45-54 | C30: 0.35865703 | E30: 0.13028131 | F30: 0.074921278 | G30: 0.07241366 | H30: 0.054393823 | I30: 0.045027298 | J30: 0.064154956 | K30: 0.044720538 | L30: 0.04101965 | M30: 0.050477972 | N30: 0.015362332
B31: 55-64 | C31: 0.32774677 | E31: 0.11694859 | F31: 0.057671053 | G31: 0.059791721 | H31: 0.045704863 | I31: 0.04202668 | J31: 0.034599581 | K31: 0.044360918 | L31: 0.059116485 | M31: 0.024967922 | N31: 0.0066940806
B32: 65+ | C32: 0.32990746 | E32: 0.15545086 | F32: 0.038188954 | G32: 0.043935348 | H32: 0.066322476 | I32: 0.039089322 | J32: 0.02463846 | K32: 0.050633666 | L32: 0.038886808 | M32: 0.007127369 | N32: 0.0020482624
A34: Females | B34: Total | C34: 0.44081507 | E34: 0.10122022 | F34: 0.13704474 | G34: 0.14576029 | H34: 0.068538912 | I34: 0.075082883 | J34: 0.059911789 | K34: 0.053768047 | L34: 0.045709409 | M34: 0.03665636 | N34: 0.03738591
B35: 15-17 | C35: 0.58978493 | E35: 0.25302513 | F35: 0.1071237 | G35: 0.096178931 | H35: 0.12393976 | I35: 0.068840541 | J35: 0.10389221 | K35: 0.087622685 | L35: 0.093931147 | M35: 0.065159479 | N35: 0.23946923
B36: 18-24 | C36: 0.5592312 | E36: 0.19070559 | F36: 0.14851089 | G36: 0.18821374 | H36: 0.085464764 | I36: 0.10506027 | J36: 0.09162214 | K36: 0.095795932 | L36: 0.043709877 | M36: 0.052668533 | N36: 0.10097588
B37: 25-34 | C37: 0.54083982 | E37: 0.1288957 | F37: 0.19299196 | G37: 0.23078626 | H37: 0.082425887 | I37: 0.10862464 | J37: 0.093794917 | K37: 0.061973862 | L37: 0.054435701 | M37: 0.065764888 | N37: 0.044425235
B38: 35-44 | C38: 0.46021792 | E38: 0.094782458 | F38: 0.12359365 | G38: 0.197611 | H38: 0.051364184 | I38: 0.072968448 | J38: 0.072295001 | K38: 0.048485878 | L38: 0.036882001 | M38: 0.038826464 | N38: 0.02184494
B39: 45-54 | C39: 0.38444102 | E39: 0.083192681 | F39: 0.10737775 | G39: 0.11769584 | H39: 0.039612008 | I39: 0.061611563 | J39: 0.064810273 | K39: 0.031590855 | L39: 0.041318427 | M39: 0.037430252 | N39: 0.012469713
B40: 55-64 | C40: 0.33596192 | E40: 0.057831982 | F40: 0.11969096 | G40: 0.11510909 | H40: 0.041564254 | I40: 0.052601214 | J40: 0.035965125 | K40: 0.021789167 | L40: 0.033586462 | M40: 0.021446213 | N40: 0.0050492014
B41: 65+ | C41: 0.3502837 | E41: 0.043929058 | F41: 0.13096964 | G41: 0.059702743 | H41: 0.085466462 | I41: 0.057262257 | J41: 0.0068751023 | K41: 0.057244935 | L41: 0.045653794 | M41: 0.0043502088 | N41: 0.0046499924
C42: Estimated number of participants
A43: All# | B43: Total | C43: 2503228.5 | E43: 807433.26 | F43: 659179.57 | G43: 647654.94 | H43: 430265.34 | I43: 406382.91 | J43: 365717.41 | K43: 375800.6 | L43: 282541.39 | M43: 265409.42 | N43: 258066.14
B44: 15-17 | C44: 144511.12 | E44: 57038.365 | F44: 24129.027 | G44: 18397.452 | H44: 29504.091 | I44: 16300.509 | J44: 20881.17 | K44: 23008.677 | L44: 23747.771 | M44: 11003.933 | N44: 65122.463
B45: 18-24 | C45: 373092.63 | E45: 159301.79 | F45: 89284.177 | G45: 89381.075 | H45: 67335.123 | I45: 72960.831 | J45: 66857.487 | K45: 73832.837 | L45: 39857.355 | M45: 40149.746 | N45: 81513.947
B46: 25-34 | C46: 566064.3 | E46: 189687.91 | F46: 180782.21 | G46: 189502.32 | H46: 110129.14 | I46: 113838.58 | J46: 103958.62 | K46: 97481.197 | L46: 58293.655 | M46: 101262.74 | N46: 61024.701
B47: 35-44 | C47: 450281.37 | E47: 132781.48 | F47: 115935.75 | G47: 140675.81 | H47: 60356.769 | I47: 64483.589 | J47: 74366.581 | K47: 60145.266 | L47: 39556.209 | M47: 50432.211 | N47: 30070.039
B48: 45-54 | C48: 321826.73 | E48: 91795.574 | F48: 79211.761 | G48: 82612.979 | H48: 40672.879 | I48: 45795.629 | J48: 55721.902 | K48: 33234.668 | L48: 36781.756 | M48: 38208.709 | N48: 11926.473
B49: 55-64 | C49: 247948.37 | E49: 64960.871 | F49: 66573.59 | G49: 65650.06 | H49: 32464.94 | I49: 35731.257 | J49: 26256.227 | K49: 24585.838 | L49: 34461.778 | M49: 17749.935 | N49: 4367.3462
B50: 65+ | C50: 399503.96 | E50: 111867.27 | F50: 103263.06 | G50: 61435.242 | H50: 89802.399 | I50: 57272.519 | J50: 17675.419 | K50: 63512.121 | L50: 49842.863 | M50: 6602.1478 | N50: 4041.1723
A52: Males | B52: Total | C52: 1207806.1 | E52: 510999.65 | F52: 256207.67 | G52: 219789.39 | H52: 230027.36 | I52: 185977.93 | J52: 190108.72 | K52: 217969.91 | L52: 145454.98 | M52: 157073.84 | N52: 148569.84
B53: 15-17 | C53: 62890.687 | E53: 22022.178 | F53: 9304.1608 | G53: 5087.2352 | H53: 12352.049 | I53: 6773.6558 | J53: 6503.5104 | K53: 10882.56 | L53: 10748.625 | M53: 1986.5027 | N53: 31982.28
B54: 18-24 | C54: 200088.73 | E54: 100351.56 | F54: 43100.572 | G54: 31124.526 | H54: 41324.796 | I54: 40986.815 | J54: 38973.226 | K54: 44164.893 | L54: 25652.078 | M54: 24120.617 | N54: 50287.976
B55: 25-34 | C55: 270134.27 | E55: 119607.02 | F55: 75345.415 | G55: 63534.078 | H55: 65313.993 | I55: 54289.883 | J55: 52962.111 | K55: 63785.865 | L55: 28242.215 | M55: 65082.516 | N55: 36870.599
B56: 35-44 | C56: 221969.07 | E56: 86066.775 | F56: 54526.129 | G56: 43280.797 | H56: 35041.298 | I56: 28025.221 | J56: 38211.388 | K56: 36248.404 | L56: 20385.198 | M56: 31296.111 | N56: 19303.491
B57: 45-54 | C57: 152538.08 | E57: 55409.095 | F57: 31864.28 | G57: 30797.782 | H57: 23133.882 | I57: 19150.266 | J57: 27285.326 | K57: 19019.801 | L57: 17445.8 | M57: 21468.457 | N57: 6533.6532
B58: 55-64 | C58: 121561.49 | E58: 43376.31 | F58: 21390.231 | G58: 22176.789 | H58: 16951.964 | I58: 15587.723 | J58: 12833.008 | K58: 16453.494 | L58: 21926.343 | M58: 9260.6185 | N58: 2482.8389
B59: 65+ | C59: 178623.8 | E59: 84166.707 | F59: 20676.877 | G59: 23788.183 | H59: 35909.381 | I59: 21164.369 | J59: 13340.152 | K59: 27414.894 | L59: 21054.721 | M59: 3859.0147 | N59: 1109.0032
A61: Females | B61: Total | C61: 1285228 | E61: 295114.82 | F61: 399563.77 | G61: 424974.58 | H61: 199830.12 | I61: 218909.53 | J61: 174677.12 | K61: 156764.6 | L61: 133269.06 | M61: 106874.25 | N61: 109001.3
B62: 15-17 | C62: 81620.429 | E62: 35016.187 | F62: 14824.866 | G62: 13310.217 | H62: 17152.042 | I62: 9526.8532 | J62: 14377.659 | K62: 12126.117 | L62: 12999.146 | M62: 9017.4304 | N62: 33140.183
B63: 18-24 | C63: 170196.29 | E63: 58039.295 | F63: 45197.77 | G63: 57280.925 | H63: 26010.326 | I63: 31974.017 | J63: 27884.261 | K63: 29154.511 | L63: 13302.654 | M63: 16029.129 | N63: 30730.975
B64: 25-34 | C64: 294055.86 | E64: 70080.887 | F64: 104930.17 | G64: 125479.02 | H64: 44815.145 | I64: 59059.468 | J64: 50996.512 | K64: 33695.332 | L64: 29596.816 | M64: 35756.521 | N64: 24154.103
B65: 35-44 | C65: 226824.07 | E65: 46714.701 | F65: 60914.65 | G65: 97395.013 | H65: 25315.47 | I65: 35963.398 | J65: 35631.481 | K65: 23896.862 | L65: 18177.748 | M65: 19136.101 | N65: 10766.548
B66: 45-54 | C66: 166260.52 | E66: 35978.623 | F66: 46438.022 | G66: 50900.32 | H66: 17131.14 | I66: 26645.363 | J66: 28028.72 | K66: 13662.205 | L66: 17869.121 | M66: 16187.589 | N66: 5392.8194
B67: 55-64 | C67: 125390.66 | E67: 21584.561 | F67: 44672.112 | G67: 42962.025 | H67: 15512.976 | I67: 19632.287 | J67: 13423.22 | K67: 8132.3444 | L67: 12535.435 | M67: 8004.3442 | N67: 1884.5073
B68: 65+ | C68: 220880.16 | E68: 27700.567 | F68: 82586.183 | G68: 37647.059 | H68: 53893.017 | I68: 36108.149 | J68: 4335.2679 | K68: 36097.227 | L68: 28788.143 | M68: 2743.1331 | N68: 2932.1691
A70: NB. Estimated participant numbers have not been rounded but users must remember that they are estimates and are subject to margins of error. Refer to sheet number 27 for margin of error and relative margin of error statistics.
A71: * Estimate has relative margin of error between 50% and 100% and should be used with caution
A72: ** Estimate has relative margin of error greater than 100% and is considered too unreliable to use
A73: # AusPlay collects data on gender, including non-binary and self-described. Non-binary and self-described gender are included in Total columns but not reported separately due to sample size. The sum of male and female estimates is not therefore equal to the total.

Sheet 6
A8: =Index!A8 -> AusPlay survey results July 2024 - June 2025
A9: Released at: | C9: 13 November 2025
A10: Table number: | C10: 6
A11: Table name: | C11: Organised activity by type of entity (children)
A12: Base: | C12: Child population
E13: Type of entity organising the activity
C14: Total | E14: Sports club or association | F14: Private or commercial business | G14: Gym/fitness club/sports/ leisure centre | H14: Educational institution | I14: Recreation club or association | J14: Individual personal trainer or coach | K14: Community organisation | L14: Event (e.g. marathon, parkrun) | M14: Less formal group (e.g. social group)
C15: Participation rate
A16: All# | B16: Total | C16: 0.73214143 | E16: 0.29415288 | F16: 0.1708277 | G16: 0.15594189 | H16: 0.1263659 | I16: 0.11265287 | J16: 0.099630494 | K16: 0.11499198 | L16: 0.052779329 | M16: 0.07028996
A17: Age group | B17: 0-4 | C17: 0.49966693 | E17: 0.098603386 | F17: 0.13316321 | G17: 0.14868622 | H17: 0.045297035 | I17: 0.048907478 | J17: 0.05024255 | K17: 0.085186972 | L17: 0.039389435 | M17: 0.055258628
B18: 5-8 | C18: 0.82201643 | E18: 0.32769588 | F18: 0.20578539 | G18: 0.20090938 | H18: 0.12269435 | I18: 0.12397403 | J18: 0.11192861 | K18: 0.14080248 | L18: 0.044180848 | M18: 0.061101161
B19: 9-11 | C19: 0.85018509 | E19: 0.3975925 | F19: 0.19565946 | G19: 0.14635232 | H19: 0.18163684 | I19: 0.16642993 | J19: 0.1266067 | K19: 0.11845365 | L19: 0.063154941 | M19: 0.096953301
B20: 12-14 | C20: 0.84408334 | E20: 0.43871734 | F20: 0.1571134 | G20: 0.11765697 | H20: 0.19713724 | I20: 0.14002812 | J20: 0.13037661 | K20: 0.1220713 | L20: 0.073606028 | M20: 0.07865908
A22: Males | B22: Total | C22: 0.73432868 | E22: 0.32278295 | F22: 0.15094883 | G22: 0.1574399 | H22: 0.1381435 | I22: 0.12268576 | J22: 0.10715417 | K22: 0.10947546 | L22: 0.056342305 | M22: 0.076814972
A23: Age group | B23: 0-4 | C23: 0.47976559 | E23: 0.11411611 | F23: 0.12413615 | G23: 0.14626089 | H23: 0.053055219 | I23: 0.053310009 | J23: 0.037462122 | K23: 0.073634059 | L23: 0.035035104 | M23: 0.047568397
B24: 5-8 | C24: 0.82510263 | E24: 0.36274476 | F24: 0.16599271 | G24: 0.18855983 | H24: 0.14705215 | I24: 0.14682954 | J24: 0.1189951 | K24: 0.12899949 | L24: 0.046042366 | M24: 0.069324887
B25: 9-11 | C25: 0.87466939 | E25: 0.437334 | F25: 0.18068333 | G25: 0.17315266 | H25: 0.17681702 | I25: 0.16543615 | J25: 0.16368496 | K25: 0.12294735 | L25: 0.078118346 | M25: 0.11791003
B26: 12-14 | C26: 0.85830895 | E26: 0.46490221 | F26: 0.14435484 | G26: 0.12284995 | H26: 0.21182198 | I26: 0.15316695 | J26: 0.14014767 | K26: 0.1246716 | L26: 0.07862905 | M26: 0.089726259
A28: Females | B28: Total | C28: 0.73189896 | E28: 0.26173145 | F28: 0.19430339 | G28: 0.15493512 | H28: 0.1134849 | I28: 0.10170266 | J28: 0.09148733 | K28: 0.12181183 | L28: 0.048948258 | M28: 0.063154916
A29: Age group | B29: 0-4 | C29: 0.52100406 | E29: 0.077582083 | F29: 0.14406553 | G29: 0.15199915 | H29: 0.036470145 | I29: 0.043977354 | J29: 0.065207909 | K29: 0.09885014 | L29: 0.04456388 | M29: 0.064348641
B30: 5-8 | C30: 0.82368095 | E30: 0.29314518 | F30: 0.24844149 | G30: 0.21496086 | H30: 0.098059412 | I30: 0.10091098 | J30: 0.1052347 | K30: 0.15392815 | L30: 0.042504688 | M30: 0.052900635
B31: 9-11 | C31: 0.82780859 | E31: 0.35591493 | F31: 0.21324926 | G31: 0.11758231 | H31: 0.18794497 | I31: 0.16843395 | J31: 0.086389634 | K31: 0.11414184 | L31: 0.046990604 | M31: 0.074360998
B32: 12-14 | C32: 0.82821936 | E32: 0.40593457 | F32: 0.17427831 | G32: 0.11125396 | H32: 0.17859522 | I32: 0.12332128 | J32: 0.11803641 | K32: 0.11906802 | L32: 0.067283433 | M32: 0.064460245
C33: Estimated number of participants
A34: All# | B34: Total | C34: 895893.56 | E34: 359943.67 | F34: 209035.34 | G34: 190820.15 | H34: 154629.13 | I34: 137849.03 | J34: 121914.04 | K34: 140711.3 | L34: 64584.053 | M34: 86011.145
A35: Age group | B35: 0-4 | C35: 190197.74 | E35: 37533.284 | F35: 50688.45 | G35: 56597.267 | H35: 17242.273 | I35: 18616.585 | J35: 19124.778 | K35: 32426.339 | L35: 14993.551 | M35: 21034.144
B36: 5-8 | C36: 275470.33 | E36: 109815.92 | F36: 68961.844 | G36: 67327.819 | H36: 41116.761 | I36: 41545.601 | J36: 37508.995 | K36: 47185.074 | L36: 14805.681 | M36: 20475.937
B37: 9-11 | C37: 211466.22 | E37: 98893.032 | F37: 48666.304 | G37: 36402.157 | H37: 45178.463 | I37: 41396.053 | J37: 31490.837 | K37: 29462.931 | L37: 15708.505 | M37: 24115.158
B38: 12-14 | C38: 218759.28 | E38: 113701.44 | F38: 40718.744 | G38: 30492.905 | H38: 51091.637 | I38: 36290.79 | J38: 33789.427 | K38: 31636.96 | L38: 19076.317 | M38: 20385.906
A40: Males | B40: Total | C40: 478087.93 | E40: 210149.27 | F40: 98275.904 | G40: 102501.94 | H40: 89938.937 | I40: 79875.104 | J40: 69763.195 | K40: 71274.481 | L40: 36681.907 | M40: 50010.727
A41: Age group | B41: 0-4 | C41: 97826.679 | E41: 23268.864 | F41: 25312.003 | G41: 29823.35 | H41: 10818.233 | I41: 10870.186 | J41: 7638.7201 | K41: 15014.365 | L41: 7143.8385 | M41: 9699.4415
B42: 5-8 | C42: 140638.57 | E42: 61829.768 | F42: 28293.423 | G42: 32139.984 | H42: 25065.008 | I42: 25027.064 | J42: 20282.689 | K42: 21987.935 | L42: 7847.9116 | M42: 11816.412
B43: 9-11 | C43: 113824.18 | E43: 56911.999 | F43: 23513.035 | G43: 22533.038 | H43: 23009.896 | I43: 21528.859 | J43: 21300.969 | K43: 15999.623 | L43: 10165.849 | M43: 15344.097
B44: 12-14 | C44: 125798.5 | E44: 68138.637 | F44: 21157.443 | G44: 18005.568 | H44: 31045.8 | I44: 22448.995 | J44: 20540.816 | K44: 18272.558 | L44: 11524.308 | M44: 13150.776
A46: Females | B46: Total | C46: 417206.92 | E46: 149195.69 | F46: 110759.44 | G46: 88318.209 | H46: 64690.197 | I46: 57973.925 | J46: 52150.843 | K46: 69436.823 | L46: 27902.146 | M46: 36000.418
A47: Age group | B47: 0-4 | C47: 91772.349 | E47: 13665.709 | F47: 25376.447 | G47: 26773.917 | H47: 6424.0399 | I47: 7746.3986 | J47: 11486.058 | K47: 17411.975 | L47: 7849.7122 | M47: 11334.702
B48: 5-8 | C48: 134831.76 | E48: 47986.152 | F48: 40668.42 | G48: 35187.836 | H48: 16051.753 | I48: 16518.537 | J48: 17226.306 | K48: 25197.139 | L48: 6957.769 | M48: 8659.5247
B49: 9-11 | C49: 97642.039 | E49: 41981.033 | F49: 25153.27 | G49: 13869.119 | H49: 22168.567 | I49: 19867.194 | J49: 10189.868 | K49: 13463.308 | L49: 5542.6561 | M49: 8771.0609
B50: 12-14 | C50: 92960.778 | E50: 45562.8 | F50: 19561.3 | G50: 12487.337 | H50: 20045.838 | I50: 13841.795 | J50: 13248.611 | K50: 13364.401 | L50: 7552.0092 | M50: 7235.1297
A52: NB. Please note that for children 0-14 years, data was collected via the child's parent/guardian for organised participation outside of school hours
A53: NB. Estimated participant numbers have not been rounded but users must remember that they are estimates and are subject to margins of error. Refer to sheet number 27 for margin of error and relative margin of error statistics.
A54: * Estimate has relative margin of error between 50% and 100% and should be used with caution
A55: ** Estimate has relative margin of error greater than 100% and is considered too unreliable to use
A56: # AusPlay collects data on gender, including non-binary and self-described. Non-binary and self-described gender are included in Total columns but not reported separately due to sample size. The sum of male and female estimates is not therefore equal to the total.

Sheet 7
A8: =Index!A8 -> AusPlay survey results July 2024 - June 2025
A9: Released at: | C9: 13 November 2025
A10: Table number: | C10: 7
A11: Table name: | C11: Places where activity took place (adults)
A12: Base: | C12: Adult population
C13: Total | E13: Public space | F13: Home environment | G13: Gym/fitness club/sports/ leisure centre | H13: Free community facilities | I13: Sports club or association facilities | J13: Private or commercial premises | K13: Recreation club or association facilities | L13: Educational institution facilities | M13: Workplace
C14: Participation rate
A15: All# | B15: Total | C15: 0.86963983 | E15: 0.62703703 | F15: 0.29549357 | G15: 0.29835973 | H15: 0.2169757 | I15: 0.20193379 | J15: 0.16610904 | K15: 0.099510054 | L15: 0.069293788 | M15: 0.065911354
B16: 15-17 | C16: 0.84583468 | E16: 0.58422972 | F16: 0.37406514 | G16: 0.26609016 | H16: 0.39331415 | I16: 0.34458279 | J16: 0.17584778 | K16: 0.16202015 | L16: 0.36541547 | M16: 0.07666368
B17: 18-24 | C17: 0.88919859 | E17: 0.56609598 | F17: 0.37605381 | G17: 0.42006251 | H17: 0.3353897 | I17: 0.31718209 | J17: 0.21279522 | K17: 0.15628244 | L17: 0.18563492 | M17: 0.076757978
B18: 25-34 | C18: 0.91865092 | E18: 0.61391422 | F18: 0.34294366 | G18: 0.42251939 | H18: 0.29742987 | I18: 0.2517973 | J18: 0.25458804 | K18: 0.13876205 | L18: 0.085954388 | M18: 0.11376044
B19: 35-44 | C19: 0.89233389 | E19: 0.61673064 | F19: 0.3085517 | G19: 0.31173778 | H19: 0.23864723 | I19: 0.1992741 | J19: 0.18836189 | K19: 0.087440176 | L19: 0.04370732 | M19: 0.070371314
B20: 45-54 | C20: 0.89145479 | E20: 0.67589523 | F20: 0.30970315 | G20: 0.26892717 | H20: 0.19173825 | I20: 0.15303572 | J20: 0.14424445 | K20: 0.080007511 | L20: 0.039322156 | M20: 0.079573834
B21: 55-64 | C21: 0.8752102 | E21: 0.71794333 | F21: 0.28428968 | G21: 0.22328741 | H21: 0.14237809 | I21: 0.14800542 | J21: 0.11914988 | K21: 0.04943658 | L21: 0.011035597 | M21: 0.048758624
B22: 65+ | C22: 0.78038467 | E22: 0.59808548 | F22: 0.17598716 | G22: 0.18114622 | H22: 0.08777447 | I22: 0.13389368 | J22: 0.084614377 | K22: 0.075119714 | L22: 0.0074891096 | M22: 0.011587873
A24: Males | B24: Total | C24: 0.87734998 | E24: 0.60583453 | F24: 0.28452822 | G24: 0.28988569 | H24: 0.21778531 | I24: 0.26775545 | J24: 0.135442 | K24: 0.11883481 | L24: 0.080959792 | M24: 0.074564253
B25: 15-17 | C25: 0.81985642 | E25: 0.53221396 | F25: 0.38261435 | G25: 0.23864255 | H25: 0.3685753 | I25: 0.38923716 | J25: 0.13502984 | K25: 0.22217576 | L25: 0.40633447 | M25: 0.078349892
B26: 18-24 | C26: 0.88133157 | E26: 0.50206537 | F26: 0.35917969 | G26: 0.39246395 | H26: 0.33672798 | I26: 0.37884498 | J26: 0.1632322 | K26: 0.1768267 | L26: 0.20860065 | M26: 0.084217691
B27: 25-34 | C27: 0.92020703 | E27: 0.55729311 | F27: 0.32358962 | G27: 0.42005016 | H27: 0.29521531 | I27: 0.32914636 | J27: 0.20989829 | K27: 0.17860662 | L27: 0.10887547 | M27: 0.1319037
B28: 35-44 | C28: 0.88795492 | E28: 0.57115815 | F28: 0.26708602 | G28: 0.32350652 | H28: 0.23505513 | I28: 0.27536128 | J28: 0.14277351 | K28: 0.10988589 | L28: 0.052051037 | M28: 0.075461071
B29: 45-54 | C29: 0.90325368 | E29: 0.65812874 | F29: 0.28811446 | G29: 0.26410211 | H29: 0.18895948 | I29: 0.18934193 | J29: 0.12043332 | K29: 0.097621428 | L29: 0.055441525 | M29: 0.092995354
B30: 55-64 | C30: 0.87325812 | E30: 0.72036098 | F30: 0.28157012 | G30: 0.21456907 | H30: 0.14718867 | I30: 0.20748331 | J30: 0.097106495 | K30: 0.055143934 | L30: 0.01054882 | M30: 0.050085252
B31: 65+ | C31: 0.81769266 | E31: 0.64741129 | F31: 0.19537323 | G31: 0.14901646 | H31: 0.092665473 | I31: 0.20917602 | J31: 0.078468379 | K31: 0.073741965 | L31: 0.0047807127 | M31: 0.01528187
A33: Females | B33: Total | C33: 0.8644377 | E33: 0.64898907 | F33: 0.30692033 | G33: 0.30750975 | H33: 0.21652181 | I33: 0.14014627 | J33: 0.1961154 | K33: 0.081658128 | L33: 0.058420125 | M33: 0.057479929
B34: 15-17 | C34: 0.88504676 | E34: 0.63567432 | F34: 0.37708011 | G34: 0.2922068 | H34: 0.42059845 | I34: 0.32106464 | J34: 0.20932173 | K34: 0.12296464 | L34: 0.34507628 | M34: 0.077328726
B35: 18-24 | C35: 0.90036213 | E35: 0.63777241 | F35: 0.39641405 | G35: 0.45974332 | H35: 0.33302777 | I35: 0.25025986 | J35: 0.277255 | K35: 0.13461099 | L35: 0.16035716 | M35: 0.065372572
B36: 25-34 | C36: 0.91694021 | E36: 0.66592015 | F36: 0.3620103 | G36: 0.42477469 | H36: 0.29974299 | I36: 0.18156392 | J36: 0.29617606 | K36: 0.10355994 | L36: 0.064922254 | M36: 0.09599776
B37: 35-44 | C37: 0.89883808 | E37: 0.66455456 | F37: 0.35278628 | G37: 0.30002398 | H37: 0.24303269 | I37: 0.12347378 | J37: 0.23650869 | K37: 0.064359395 | L37: 0.0356566 | M37: 0.065983363
B38: 45-54 | C38: 0.87860481 | E38: 0.69559132 | F38: 0.32987162 | G38: 0.27223335 | H38: 0.19455773 | I38: 0.11686815 | J38: 0.16489534 | K38: 0.062661474 | L38: 0.023921669 | M38: 0.067288786
B39: 55-64 | C39: 0.87649254 | E39: 0.71535388 | F39: 0.287191 | G39: 0.23312797 | H39: 0.13834778 | I39: 0.089678452 | J39: 0.14031381 | K39: 0.04402533 | L39: 0.011577489 | M39: 0.047697201
B40: 65+ | C40: 0.75356774 | E40: 0.55931807 | F40: 0.16091658 | G40: 0.2103553 | H40: 0.084360427 | I40: 0.070451664 | J40: 0.090648848 | K40: 0.076975007 | L40: 0.0098816697 | M40: 0.0085197738
C41: Estimated number of participants
A42: All# | B42: Total | C42: 5015652.8 | E42: 3616439.8 | F42: 1704260.9 | G42: 1720791.5 | H42: 1251408.6 | I42: 1164654.3 | J42: 958034.86 | K42: 573924.82 | L42: 399652.33 | M42: 380144.12
B43: 15-17 | C43: 203601.17 | E43: 140630.14 | F43: 90041.353 | G43: 64050.659 | H43: 94674.791 | I43: 82944.647 | J43: 42328.382 | K43: 38999.929 | L43: 87959.288 | M43: 18453.742
B44: 18-24 | C44: 603392.95 | E44: 384141.77 | F44: 255182.83 | G44: 285046.29 | H44: 227588.96 | I44: 215233.62 | J44: 144398.72 | K44: 106050.23 | L44: 125968.26 | M44: 52086.478
B45: 25-34 | C45: 970562.03 | E45: 648605.28 | F45: 362322.72 | G45: 446395.11 | H45: 314237.03 | I45: 266025.86 | J45: 268974.3 | K45: 146603.21 | L45: 90811.497 | M45: 120188.82
B46: 35-44 | C46: 896984.71 | E46: 619945.03 | F46: 310159.87 | G46: 313362.55 | H46: 239891.06 | I46: 200312.72 | J46: 189343.63 | K46: 87895.913 | L46: 43935.122 | M46: 70738.088
B47: 45-54 | C47: 769097.39 | E47: 583124.64 | F47: 267194.58 | G47: 232015.33 | H47: 165421.05 | I47: 132030.67 | J47: 124446.05 | K47: 69026.011 | L47: 33924.959 | M47: 68651.859
B48: 55-64 | C48: 652990.96 | E48: 535654.75 | F48: 212107.44 | G48: 166593.88 | H48: 106227.75 | I48: 110426.28 | J48: 88897.264 | K48: 36884.442 | L48: 8233.6167 | M48: 36378.621
B49: 65+ | C49: 919023.6 | E49: 704338.13 | F49: 207252.09 | G49: 213327.69 | H49: 103368.01 | I49: 157680.51 | J49: 99646.512 | K49: 88465.078 | L49: 8819.5845 | M49: 13646.513
A51: Males | B51: Total | C51: 2468235.6 | E51: 1704385.2 | F51: 800459 | G51: 815531.08 | H51: 612692.16 | I51: 753272.4 | J51: 381036.95 | K51: 334316.21 | L51: 227762.98 | M51: 209770.5
B52: 15-17 | C52: 81119.411 | E52: 52659.077 | F52: 37857.178 | G52: 23612.114 | H52: 36468.106 | I52: 38512.461 | J52: 13360.316 | K52: 21982.833 | L52: 40204.128 | M52: 7752.2075
B53: 18-24 | C53: 321407.44 | E53: 183095.16 | F53: 130987.05 | G53: 143125.28 | H53: 122799.28 | I53: 138158.67 | J53: 59528.156 | K53: 64485.85 | L53: 76073.298 | M53: 30712.836
B54: 25-34 | C54: 465225.36 | E54: 281748.44 | F54: 163595.9 | G54: 212363.07 | H54: 149250.81 | I54: 166405.2 | J54: 106117.43 | K54: 90297.429 | L54: 55043.734 | M54: 66686.025
B55: 35-44 | C55: 449706.14 | E55: 289263.93 | F55: 135266.13 | G55: 163840.38 | H55: 119044.03 | I55: 139457.14 | J55: 72307.863 | K55: 55651.881 | L55: 26361.328 | M55: 38217.376
B56: 45-54 | C56: 384156.93 | E56: 279904.44 | F56: 122536.08 | G56: 112323.55 | H56: 80365.124 | I56: 80527.783 | J56: 51220.71 | K56: 41518.733 | L56: 23579.473 | M56: 39551.248
B57: 55-64 | C57: 323892.01 | E57: 267182.36 | F57: 104434.54 | G57: 79583.808 | H57: 54592.375 | I57: 76955.695 | J57: 36016.863 | K57: 20452.921 | L57: 3912.5644 | M57: 18576.653
B58: 65+ | C58: 442728.31 | E58: 350531.83 | F58: 105782.12 | G58: 80682.889 | H58: 50172.431 | I58: 113255.45 | J58: 42485.612 | K58: 39926.561 | L58: 2588.4503 | M58: 8274.156
A60: Females | B60: Total | C60: 2520330.1 | E60: 1892174.2 | F60: 894848.26 | G60: 896566.76 | H60: 631284.88 | I60: 408606.51 | J60: 571788.52 | K60: 238080.13 | L60: 170328.07 | M60: 167586.86
B61: 15-17 | C61: 122481.76 | E61: 87971.068 | F61: 52184.175 | G61: 40438.545 | H61: 58206.685 | I61: 44432.186 | J61: 28968.067 | K61: 17017.096 | L61: 47755.16 | M61: 10701.534
B62: 18-24 | C62: 274016 | E62: 194099.5 | F62: 120644.56 | G62: 139918.17 | H62: 101353.59 | I62: 76164.027 | J62: 84379.721 | K62: 40967.477 | L62: 48803.061 | M62: 19895.473
B63: 25-34 | C63: 498542.5 | E63: 362062.32 | F63: 196825.84 | G63: 230950.98 | H63: 162970.95 | I63: 98716.724 | J63: 161031.61 | K63: 56305.78 | L63: 35298.379 | M63: 52194.203
B64: 35-44 | C64: 443003.41 | E64: 327533.9 | F64: 173875.06 | G64: 147870.51 | H64: 119781.65 | I64: 60855.572 | J64: 116566.22 | K64: 31720.32 | L64: 17573.794 | M64: 32520.713
B65: 45-54 | C65: 379973.22 | E65: 300824.75 | F65: 142660.71 | G65: 117733.68 | H65: 84141.045 | I65: 50542.365 | J65: 71312.852 | K65: 27099.421 | L65: 10345.486 | M65: 29100.611
B66: 55-64 | C66: 327132.25 | E66: 266990.66 | F66: 107187.95 | G66: 87010.071 | H66: 51635.373 | I66: 33470.58 | J66: 52369.155 | K66: 16431.521 | L66: 4321.0523 | M66: 17801.968
B67: 65+ | C67: 475181 | E67: 352692.01 | F67: 101469.98 | G67: 132644.8 | H67: 53195.579 | I67: 44425.06 | J67: 57160.9 | K67: 48538.518 | L67: 6231.1342 | M67: 5372.3566
A69: NB. Estimated participant numbers have not been rounded but users must remember that they are estimates and are subject to margins of error. Refer to sheet number 27 for margin of error and relative margin of error statistics.
A70: * Estimate has relative margin of error between 50% and 100% and should be used with caution
A71: ** Estimate has relative margin of error greater than 100% and is considered too unreliable to use
A72: # AusPlay collects data on gender, including non-binary and self-described. Non-binary and self-described gender are included in Total columns but not reported separately due to sample size. The sum of male and female estimates is not therefore equal to the total.

Sheet 8
A8: =Index!A8 -> AusPlay survey results July 2024 - June 2025
A9: Released at: | C9: 13 November 2025
A10: Table number: | C10: 8
A11: Table name: | C11: Places where activity took place (children)
A12: Base: | C12: Child population
C13: Total | E13: Public space | F13: Home environment | G13: Gym/fitness club/sports/ leisure centre | H13: Free community facilities | I13: Sports club or association facilities | J13: Private or commercial premises | K13: Recreation club or association facilities | L13: Educational institution facilities
C14: Participation rate
A15: All# | B15: Total | C15: 0.73214143 | E15: 0.16234613 | F15: 0.11891082 | G15: 0.20081421 | H15: 0.14240245 | I15: 0.29566526 | J15: 0.17797343 | K15: 0.12133398 | L15: 0.15038405
B16: 0-4 | C16: 0.49966693 | E16: 0.11150203 | F16: 0.098760909 | G16: 0.1618736 | H16: 0.074227715 | I16: 0.098060484 | J16: 0.13290477 | K16: 0.059995077 | L16: 0.065457928
B17: 5-8 | C17: 0.82201643 | E17: 0.14030567 | F17: 0.11194928 | G17: 0.26936484 | H17: 0.15340182 | I17: 0.32500187 | J17: 0.23362004 | K17: 0.13168052 | L17: 0.15655241
B18: 9-11 | C18: 0.85018509 | E18: 0.23289398 | F18: 0.14399315 | G18: 0.21745909 | H18: 0.18339856 | I18: 0.41341775 | J18: 0.19722075 | K18: 0.1620703 | L18: 0.19585002
B19: 12-14 | C19: 0.84408334 | E19: 0.19781548 | F19: 0.13343518 | G19: 0.15339421 | H19: 0.18896546 | I19: 0.43495099 | J19: 0.15374176 | K19: 0.15895044 | L19: 0.22350733
A21: Males | B21: Total | C21: 0.73432868 | E21: 0.17448139 | F21: 0.12995241 | G21: 0.19887493 | H21: 0.16649166 | I21: 0.3231512 | J21: 0.14823442 | K21: 0.11327297 | L21: 0.15903373
B22: 0-4 | C22: 0.47976559 | E22: 0.10157533 | F22: 0.093280274 | G22: 0.15583289 | H22: 0.075052412 | I22: 0.11478137 | J22: 0.12172605 | K22: 0.053949786 | L22: 0.065355264
B23: 5-8 | C23: 0.82510263 | E23: 0.1468584 | F23: 0.12448969 | G23: 0.23950978 | H23: 0.18740012 | I23: 0.35880666 | J23: 0.18578473 | K23: 0.11844159 | L23: 0.17348412
B24: 9-11 | C24: 0.87466939 | E24: 0.25677135 | F24: 0.17782097 | G24: 0.25491328 | H24: 0.23922161 | I24: 0.4438144 | J24: 0.16374493 | K24: 0.14488231 | L24: 0.18820444
B25: 12-14 | C25: 0.85830895 | E25: 0.23496997 | F25: 0.14482243 | G25: 0.16174342 | H25: 0.20481212 | I25: 0.46443846 | J25: 0.12767233 | K25: 0.1617282 | L25: 0.2466557
A27: Females | B27: Total | C27: 0.73189896 | E27: 0.14816879 | F27: 0.1068368 | G27: 0.2039359 | H27: 0.11553235 | I27: 0.26560771 | J27: 0.21274299 | K27: 0.1300383 | L27: 0.14118402
B28: 0-4 | C28: 0.52100406 | E28: 0.11997316 | F28: 0.10544096 | G28: 0.16941651 | H28: 0.073525345 | I28: 0.079037741 | J28: 0.14629697 | K28: 0.063798047 | L28: 0.065799261
B29: 5-8 | C29: 0.82368095 | E29: 0.13431513 | F29: 0.099555669 | G29: 0.30205051 | H29: 0.11891075 | I29: 0.29173062 | J29: 0.28481588 | K29: 0.14624725 | L29: 0.13985096
B30: 9-11 | C30: 0.82780859 | E30: 0.20782074 | F30: 0.10745702 | G30: 0.17732273 | H30: 0.12281055 | I30: 0.38213643 | J30: 0.2352293 | K30: 0.18191722 | L30: 0.20535325
B31: 12-14 | C31: 0.82821936 | E31: 0.14993459 | F31: 0.11899439 | G31: 0.14298461 | H31: 0.16887996 | I31: 0.39784358 | J31: 0.18827721 | K31: 0.1558339 | L31: 0.19399821
C32: Estimated number of participants
A33: All# | B33: Total | C33: 895893.56 | E33: 198656.77 | F33: 145506.64 | G33: 245728.69 | H33: 174252.45 | I33: 361794.31 | J33: 217779.3 | K33: 148471.76 | L33: 184019.23
B34: 0-4 | C34: 190197.74 | E34: 42443.139 | F34: 37593.246 | G34: 61617.031 | H34: 28254.709 | I34: 37326.629 | J34: 50590.074 | K34: 22837.068 | L34: 24916.498
B35: 5-8 | C35: 275470.33 | E35: 47018.585 | F35: 37515.922 | G35: 90268.294 | H35: 51407.306 | I35: 108913.12 | J35: 78289.662 | K35: 44128.165 | L35: 52463.116
B36: 9-11 | C36: 211466.22 | E36: 57927.631 | F36: 35815.362 | G36: 54088.519 | H36: 45616.655 | I36: 102829.24 | J36: 49054.642 | K36: 40311.686 | L36: 48713.702
B37: 12-14 | C37: 218759.28 | E37: 51267.415 | F37: 34582.112 | G37: 39754.85 | H37: 48973.775 | I37: 112725.32 | J37: 39844.923 | K37: 41194.846 | L37: 57925.917
A39: Males | B39: Total | C39: 478087.93 | E39: 113596.88 | F39: 84606.09 | G39: 129478.4 | H39: 108395.13 | I39: 210389.02 | J39: 96508.673 | K39: 73746.869 | L39: 103539.61
B40: 0-4 | C40: 97826.679 | E40: 20711.735 | F40: 19020.329 | G40: 31775.13 | H40: 15303.574 | I40: 23404.513 | J40: 24820.569 | K40: 11000.64 | L40: 13326.276
B41: 5-8 | C41: 140638.57 | E41: 25031.983 | F41: 21219.241 | G41: 40824.392 | H41: 31942.311 | I41: 61158.52 | J41: 31666.968 | K41: 20188.344 | L41: 29570.331
B42: 9-11 | C42: 113824.18 | E42: 33414.669 | F42: 23140.544 | G42: 33172.87 | H42: 31130.853 | I42: 57755.319 | J42: 21308.774 | K42: 18854.106 | L42: 24491.786
B43: 12-14 | C43: 125798.5 | E43: 34438.497 | F43: 21225.975 | G43: 23706.009 | H43: 30018.396 | I43: 68070.667 | J43: 18712.362 | K43: 23703.779 | L43: 36151.222
A45: Females | B45: Total | C45: 417206.92 | E45: 84461.176 | F45: 60900.552 | G45: 116250.29 | H45: 65857.312 | I45: 151405.29 | J45: 121270.63 | K45: 74126.184 | L45: 80479.618
B46: 0-4 | C46: 91772.349 | E46: 21132.693 | F46: 18572.916 | G46: 29841.9 | H46: 12951.134 | I46: 13922.116 | J46: 25769.505 | K46: 11237.718 | L46: 11590.222
B47: 5-8 | C47: 134831.76 | E47: 21986.602 | F47: 16296.681 | G47: 49443.902 | H47: 19464.995 | I47: 47754.597 | J47: 46622.694 | K47: 23939.82 | L47: 22892.785
B48: 9-11 | C48: 97642.039 | E48: 24512.963 | F48: 12674.818 | G48: 20915.648 | H48: 14485.803 | I48: 45073.923 | J48: 27745.868 | K48: 21457.579 | L48: 24221.916
B49: 12-14 | C49: 92960.778 | E49: 16828.918 | F49: 13356.137 | G49: 16048.841 | H49: 18955.38 | I49: 44654.654 | J49: 21132.561 | K49: 17491.067 | L49: 21774.695
A51: NB. Please note that for children 0-14 years, data was collected via the child's parent/guardian for organised participation outside of school hours
A52: NB. Estimated participant numbers have not been rounded but users must remember that they are estimates and are subject to margins of error. Refer to sheet number 27 for margin of error and relative margin of error statistics.
A53: * Estimate has relative margin of error between 50% and 100% and should be used with caution
A54: ** Estimate has relative margin of error greater than 100% and is considered too unreliable to use
A55: # AusPlay collects data on gender, including non-binary and self-described. Non-binary and self-described gender are included in Total columns but not reported separately due to sample size. The sum of male and female estimates is not therefore equal to the total.

Sheet 9
A8: =Index!A8 -> AusPlay survey results July 2024 - June 2025
A9: Released at: | C9: 13 November 2025
A10: Table number: | C10: 9
A11: Table name: | C11: Frequency of participation (adults)
A12: Base: | C12: Adult population
C13: 1+ per year | D13: 1+ per month | E13: 1+ per fortnight | F13: 1+ per week | G13: 2+ per week | H13: 3+ per week | I13: 4+ per week | J13: 5+ per week | K13: 6+ per week | L13: 7+ per week
C14: Participation rate
A15: All | B15: Total | C15: 0.86963983 | D15: 0.8171353 | E15: 0.77222214 | F15: 0.69587655 | G15: 0.59510744 | H15: 0.50051291 | I15: 0.40920595 | J15: 0.33822001 | K15: 0.25788474 | L15: 0.19587427
A16: Age group | B16: 15-17 | C16: 0.84583468 | D16: 0.77018314 | E16: 0.71914429 | F16: 0.64605555 | G16: 0.52918113 | H16: 0.44760347 | I16: 0.36008207 | J16: 0.31273713 | K16: 0.26277146 | L16: 0.20240423
B17: 18-24 | C17: 0.88919859 | D17: 0.83066302 | E17: 0.77873471 | F17: 0.6971593 | G17: 0.57879601 | H17: 0.47908839 | I17: 0.38622871 | J17: 0.32851292 | K17: 0.24805689 | L17: 0.18406607
B18: 25-34 | C18: 0.91865092 | D18: 0.85615696 | E18: 0.80734147 | F18: 0.72103126 | G18: 0.61186879 | H18: 0.51492309 | I18: 0.42246992 | J18: 0.34196081 | K18: 0.2595666 | L18: 0.20817463
B19: 35-44 | C19: 0.89233389 | D19: 0.82789501 | E19: 0.77271705 | F19: 0.69155327 | G19: 0.58077596 | H19: 0.4702791 | I19: 0.36475184 | J19: 0.29188362 | K19: 0.21708316 | L19: 0.16408618
B20: 45-54 | C20: 0.89145479 | D20: 0.8419701 | E20: 0.79728021 | F20: 0.72534802 | G20: 0.62578542 | H20: 0.53644837 | I20: 0.44874346 | J20: 0.37526799 | K20: 0.29216316 | L20: 0.21914411
B21: 55-64 | C21: 0.8752102 | D21: 0.83729241 | E21: 0.803058 | F21: 0.74021626 | G21: 0.65275286 | H21: 0.5777315 | I21: 0.48286978 | J21: 0.39903712 | K21: 0.30256411 | L21: 0.22941298
B22: 65+ | C22: 0.78038467 | D22: 0.74378146 | E22: 0.70949621 | F22: 0.63676215 | G22: 0.55618191 | H22: 0.46130398 | I22: 0.38289755 | J22: 0.31954595 | K22: 0.24244849 | L22: 0.17914637
A24: Males | B24: Total | C24: 0.87734998 | D24: 0.82369864 | E24: 0.77541357 | F24: 0.69330247 | G24: 0.57997334 | H24: 0.48381292 | I24: 0.39295092 | J24: 0.32568054 | K24: 0.24716663 | L24: 0.18701729
A25: Age group | B25: 15-17 | C25: 0.81985642 | D25: 0.76870371 | E25: 0.71728812 | F25: 0.6328725 | G25: 0.51293749 | H25: 0.46141719 | I25: 0.36547742 | J25: 0.33164125 | K25: 0.24886738 | L25: 0.2158319
B26: 18-24 | C26: 0.88133157 | D26: 0.81576551 | E26: 0.75887877 | F26: 0.6706821 | G26: 0.53759604 | H26: 0.43906984 | I26: 0.34632798 | J26: 0.29211479 | K26: 0.22443824 | L26: 0.16090224
B27: 25-34 | C27: 0.92020703 | D27: 0.85706581 | E27: 0.80032161 | F27: 0.69533249 | G27: 0.57593665 | H27: 0.47116949 | I27: 0.36689149 | J27: 0.28950747 | K27: 0.20937656 | L27: 0.16246799
B28: 35-44 | C28: 0.88795492 | D28: 0.81730769 | E28: 0.76000445 | F28: 0.6721466 | G28: 0.54937548 | H28: 0.44343327 | I28: 0.34655871 | J28: 0.27098024 | K28: 0.19334749 | L28: 0.1447405
B29: 45-54 | C29: 0.90325368 | D29: 0.84698584 | E29: 0.7977019 | F29: 0.72477687 | G29: 0.61198869 | H29: 0.51398847 | I29: 0.43508379 | J29: 0.36412625 | K29: 0.29023353 | L29: 0.22651279
B30: 55-64 | C30: 0.87325812 | D30: 0.83970699 | E30: 0.79960312 | F30: 0.73669691 | G30: 0.63664243 | H30: 0.56162514 | I30: 0.48898942 | J30: 0.41514495 | K30: 0.31357433 | L30: 0.24091908
B31: 65+ | C31: 0.81769266 | D31: 0.78465479 | E31: 0.75424985 | F31: 0.68302491 | G31: 0.58918846 | H31: 0.4906116 | I31: 0.39821679 | J31: 0.34065653 | K31: 0.26847183 | L31: 0.19386089
A33: Females | B33: Total | C33: 0.8644377 | D33: 0.81286345 | E33: 0.77119576 | F33: 0.70039246 | G33: 0.61106752 | H33: 0.51785436 | I33: 0.42575063 | J33: 0.35071958 | K33: 0.26949899 | L33: 0.20588759
A34: Age group | B34: 15-17 | C34: 0.88504676 | D34: 0.79003361 | E34: 0.73801875 | F34: 0.67124489 | G34: 0.55370689 | H34: 0.4486489 | I34: 0.36501073 | J34: 0.30685233 | K34: 0.27912403 | L34: 0.19774272
B35: 18-24 | C35: 0.90036213 | D35: 0.84841289 | E35: 0.8007955 | F35: 0.72796411 | G35: 0.62517774 | H35: 0.52569605 | I35: 0.43140564 | J35: 0.36904704 | K35: 0.27760361 | L35: 0.21280496
B36: 25-34 | C36: 0.91694021 | D36: 0.85514777 | E36: 0.81503961 | F36: 0.7457116 | G36: 0.64554297 | H36: 0.55700452 | I36: 0.47509645 | J36: 0.39147273 | K36: 0.30709739 | L36: 0.25183182
B37: 35-44 | C37: 0.89883808 | D37: 0.84000758 | E37: 0.78763749 | F37: 0.71238105 | G37: 0.61260255 | H37: 0.49610314 | I37: 0.38142603 | J37: 0.31047076 | K37: 0.24092442 | L37: 0.18497619
B38: 45-54 | C38: 0.87860481 | D38: 0.83755473 | E38: 0.79686944 | F38: 0.72731465 | G38: 0.63961482 | H38: 0.55894361 | I38: 0.46398925 | J38: 0.38838993 | K38: 0.29621429 | L38: 0.21441462
B39: 55-64 | C39: 0.87649254 | D39: 0.83403552 | E39: 0.80545355 | F39: 0.74364566 | G39: 0.66953332 | H39: 0.59411259 | I39: 0.47666365 | J39: 0.38246336 | K39: 0.2919176 | L39: 0.21788821
B40: 65+ | C40: 0.75356774 | D40: 0.71357562 | E40: 0.67565173 | F40: 0.60097093 | G40: 0.53173648 | H40: 0.43918547 | I40: 0.37208827 | J40: 0.30319702 | K40: 0.22179885 | L40: 0.16811523
C41: Estimated number of participants
A42: All# | B42: Total | C42: 5015652.8 | D42: 4712832.6 | E42: 4453795.7 | F42: 4013472.1 | G42: 3432285.7 | H42: 2886711.1 | I42: 2360097.7 | J42: 1950685.9 | K42: 1487351.8 | L42: 1129706
A43: Age group | B43: 15-17 | C43: 203601.17 | D43: 185391.06 | E43: 173105.48 | F43: 155512.26 | G43: 127379.38 | H43: 107742.79 | I43: 86675.483 | J43: 75279.066 | K43: 63251.811 | L43: 48720.795
B44: 18-24 | C44: 603392.95 | D44: 563671.84 | E44: 528434.3 | F44: 473078.8 | G44: 392759.77 | H44: 325100.1 | I44: 262087.32 | J44: 222922.51 | K44: 168326.6 | L44: 124903.67
B45: 25-34 | C45: 970562.03 | D45: 904536.67 | E45: 852962.71 | F45: 761775.28 | G45: 646444.27 | H45: 544020.35 | I45: 446342.84 | J45: 361284.32 | K45: 274234.19 | L45: 219938.16
B46: 35-44 | C46: 896984.71 | D46: 832209.98 | E46: 776744.44 | F46: 695157.63 | G46: 583802.95 | H46: 472730.19 | I46: 366652.92 | J46: 293404.91 | K46: 218214.59 | L46: 164941.39
B47: 45-54 | C47: 769097.39 | D47: 726404.77 | E47: 687848.83 | F47: 625789.75 | G47: 539892.7 | H47: 462817.69 | I47: 387150.79 | J47: 323760.26 | K47: 252062.05 | L47: 189065.3
B48: 55-64 | C48: 652990.96 | D48: 624700.64 | E48: 599158.48 | F48: 552272.5 | G48: 487016.39 | H48: 431043.24 | I48: 360267.28 | J48: 297720.06 | K48: 225741.92 | L48: 171164.14
B49: 65+ | C49: 919023.6 | D49: 875917.68 | E49: 835541.49 | F49: 749885.89 | G49: 654990.2 | H49: 543256.77 | I49: 450921.07 | J49: 376314.77 | K49: 285520.59 | L49: 210972.55
A51: Males | B51: Total | C51: 2468235.6 | D51: 2317299.1 | E51: 2181459.4 | F51: 1950457.5 | G51: 1631630.4 | H51: 1361103.7 | I51: 1105483 | J51: 916232.21 | K51: 695350.19 | L51: 526132.95
A52: Age group | B52: 15-17 | C52: 81119.411 | D52: 76058.185 | E52: 70970.95 | F52: 62618.578 | G52: 50751.797 | H52: 45654.202 | I52: 36161.591 | J52: 32813.724 | K52: 24623.793 | L52: 21355.149
B53: 18-24 | C53: 321407.44 | D53: 297496.55 | E53: 276750.87 | F53: 244586.97 | G53: 196052.62 | H53: 160121.7 | I53: 126300.24 | J53: 106529.56 | K53: 81849.014 | L53: 58678.458
B54: 25-34 | C54: 465225.36 | D54: 433303.32 | E54: 404615.37 | F54: 351536.45 | G54: 291173.97 | H54: 238207.26 | I54: 185487.85 | J54: 146365.13 | K54: 105853.67 | L54: 82138.289
B55: 35-44 | C55: 449706.14 | D55: 413926.74 | E55: 384905.43 | F55: 340409.68 | G55: 278232.06 | H55: 224577.46 | I55: 175515.2 | J55: 137238.36 | K55: 97921.134 | L55: 73304.048
B56: 45-54 | C56: 384156.93 | D56: 360226.03 | E56: 339265.39 | F56: 308250.13 | G56: 260280.92 | H56: 218601.08 | I56: 185042.65 | J56: 154864.16 | K56: 123437.33 | L56: 96336.677
B57: 55-64 | C57: 323892.01 | D57: 311447.87 | E57: 296573.32 | F57: 273241.37 | G57: 236131.09 | H57: 208307.13 | I57: 181366.5 | J57: 153977.53 | K57: 116304.92 | L57: 89357.044
B58: 65+ | C58: 442728.31 | D58: 424840.41 | E58: 408378.09 | F58: 369814.33 | G58: 319007.89 | H58: 265634.82 | I58: 215608.94 | J58: 184443.74 | K58: 145360.33 | L58: 104963.28
A60: Females | B60: Total | C60: 2520330.1 | D60: 2369961.7 | E60: 2248476.6 | F60: 2042044.5 | G60: 1781611.2 | H60: 1509841.5 | I60: 1241306.5 | J60: 1022548.1 | K60: 785743.64 | L60: 600280.04
A61: Age group | B61: 15-17 | C61: 122481.76 | D61: 109332.87 | E61: 102134.53 | F61: 92893.684 | G61: 76627.583 | H61: 62088.59 | I61: 50513.892 | J61: 42465.341 | K61: 38628.018 | L61: 27365.646
B62: 18-24 | C62: 274016 | D62: 258205.78 | E62: 243713.91 | F62: 221548.43 | G62: 190266.45 | H62: 159990.21 | I62: 131293.89 | J62: 112315.69 | K62: 84485.817 | L62: 64765.011
B63: 25-34 | C63: 498542.5 | D63: 464945.81 | E63: 443138.91 | F63: 405445.12 | G63: 350983.2 | H63: 302844.64 | I63: 258311.04 | J63: 212844.62 | K63: 166969.56 | L63: 136921.54
B64: 35-44 | C64: 443003.41 | D64: 414008.08 | E64: 388196.83 | F64: 351105.77 | G64: 301928.71 | H64: 244510.54 | I64: 187990.52 | J64: 153019.34 | K64: 118742.57 | L64: 91167.794
B65: 45-54 | C65: 379973.22 | D65: 362220.15 | E65: 344624.84 | F65: 314544.25 | G65: 276616.4 | H65: 241728.25 | I65: 200663.01 | J65: 167968.32 | K65: 128104.81 | L65: 92728.621
B66: 55-64 | C66: 327132.25 | D66: 311286.07 | E66: 300618.45 | F66: 277549.97 | G66: 249889.11 | H66: 221739.92 | I66: 177904.6 | J66: 142746.34 | K66: 108952.05 | L66: 81322.154
B67: 65+ | C67: 475181 | D67: 449962.97 | E67: 426049.11 | F67: 378957.26 | G67: 335299.75 | H67: 276939.39 | I67: 234629.57 | J67: 191188.47 | K67: 139860.82 | L67: 106009.27
A69: NB. Estimated participant numbers have not been rounded but users must remember that they are estimates and are subject to margins of error. Refer to sheet number 27 for margin of error and relative margin of error statistics.
A70: * Estimate has relative margin of error between 50% and 100% and should be used with caution
A71: ** Estimate has relative margin of error greater than 100% and is considered too unreliable to use
A72: # AusPlay collects data on gender, including non-binary and self-described. Non-binary and self-described gender are included in Total columns but not reported separately due to sample size. The sum of male and female estimates is not therefore equal to the total.

Sheet 10
A8: =Index!A8 -> AusPlay survey results July 2024 - June 2025
A9: Released at: | C9: 13 November 2025
A10: Table number: | C10: 10
A11: Table name: | C11: Frequency of participation (children)
A12: Base: | C12: Child population
C13: 1+ per year | D13: 1+ per month | E13: 1+ per fortnight | F13: 1+ per week | G13: 2+ per week | H13: 3+ per week | I13: 4+ per week | J13: 5+ per week | K13: 6+ per week | L13: 7+ per week
C14: Participation rate
A15: All | B15: Total | C15: 0.73214143 | D15: 0.6234584 | E15: 0.55117045 | F15: 0.43185378 | G15: 0.24038797 | H15: 0.13103425 | I15: 0.075779465 | J15: 0.046694339 | K15: 0.030716461 | L15: 0.022252014
A16: Age group | B16: 0-4 | C16: 0.49966693 | D16: 0.36735875 | E16: 0.3179163 | F16: 0.21953089 | G16: 0.083170473 | H16: 0.047884368 | I16: 0.034893974 | J16: 0.019931506 | K16: 0.016971276 | L16: 0.016971276
B17: 5-8 | C17: 0.82201643 | D17: 0.70634376 | E17: 0.6112376 | F17: 0.48414459 | G17: 0.23799134 | H17: 0.10953139 | I17: 0.055899621 | J17: 0.034913257 | K17: 0.026249579 | L17: 0.021799573
B18: 9-11 | C18: 0.85018509 | D18: 0.76632044 | E18: 0.69334121 | F18: 0.56515464 | G18: 0.3464153 | H18: 0.18431202 | I18: 0.096194528 | J18: 0.065528716 | K18: 0.038449436 | L18: 0.029235101
B19: 12-14 | C19: 0.84408334 | D19: 0.75531853 | E19: 0.67964495 | F19: 0.54815362 | G19: 0.37264086 | H19: 0.22983161 | I19: 0.14194212 | J19: 0.083159512 | K19: 0.049258853 | L19: 0.023891209
A21: Males | B21: Total | C21: 0.73432868 | D21: 0.61279138 | E21: 0.52995615 | F21: 0.40526975 | G21: 0.22884862 | H21: 0.11924489 | I21: 0.068752948 | J21: 0.045935812 | K21: 0.024230345 | L21: 0.015630612
A22: Age group | B22: 0-4 | C22: 0.47976559 | D22: 0.32917626 | E22: 0.26565816 | F22: 0.17148567 | G22: 0.052852717 | H22: 0.021875369 | I22: 0.01311888 | J22: 0.0076760189 | K22: 0.0050880242 | L22: 0.0050880242
B23: 5-8 | C23: 0.82510263 | D23: 0.70821664 | E23: 0.58797287 | F23: 0.4353221 | G23: 0.21158763 | H23: 0.085235369 | I23: 0.056137953 | J23: 0.041388635 | K23: 0.027300291 | L23: 0.021932602
B24: 9-11 | C24: 0.87466939 | D24: 0.77654079 | E24: 0.70957943 | F24: 0.57832924 | G24: 0.36561563 | H24: 0.17735704 | I24: 0.088774797 | J24: 0.052473998 | K24: 0.021172026 | L24: 0.0133698
B25: 12-14 | C25: 0.85830895 | D25: 0.75099589 | E25: 0.67069659 | F25: 0.54190795 | G25: 0.37233785 | H25: 0.24266206 | I25: 0.14304582 | J25: 0.098646668 | K25: 0.050006784 | L25: 0.024976081
A27: Females | B27: Total | C27: 0.73189896 | D27: 0.63845677 | E27: 0.57788881 | F27: 0.46416633 | G27: 0.25465291 | H27: 0.14509095 | I27: 0.084146868 | J27: 0.047771526 | K27: 0.038263172 | L27: 0.029915018
A28: Age group | B28: 0-4 | C28: 0.52100406 | D28: 0.41280733 | E28: 0.37949076 | F28: 0.27589409 | G28: 0.11854892 | H28: 0.07815507 | I28: 0.060219366 | J28: 0.034186169 | K28: 0.030784981 | L28: 0.030784981
B29: 5-8 | C29: 0.82368095 | D29: 0.70858524 | E29: 0.63908972 | F29: 0.53785504 | G29: 0.26689703 | H29: 0.13548009 | I29: 0.055983178 | J29: 0.028377827 | K29: 0.025311277 | L29: 0.02179042
B30: 9-11 | C30: 0.82780859 | D30: 0.75922364 | E30: 0.67920706 | F30: 0.55370146 | G30: 0.3271212 | H30: 0.1929904 | I30: 0.10490512 | J30: 0.080289012 | K30: 0.057720847 | L30: 0.046898318
B31: 12-14 | C31: 0.82821936 | D31: 0.76338971 | E31: 0.69351329 | F31: 0.55807031 | G31: 0.37423374 | H31: 0.21381597 | I31: 0.14095692 | J31: 0.063203519 | K31: 0.048440461 | L31: 0.022551338
C32: Estimated number of participants
A33: All# | B33: Total | C33: 895893.56 | D33: 762902.28 | E33: 674446.27 | F33: 528443.02 | G33: 294153.6 | H33: 160341.61 | I33: 92728.444 | J33: 57138.083 | K33: 37586.563 | L33: 27228.941
A34: Age group | B34: 0-4 | C34: 190197.74 | D34: 139834.76 | E34: 121014.53 | F34: 83564.225 | G34: 31658.761 | H34: 18227.139 | I34: 13282.358 | J34: 7586.9085 | K34: 6460.1001 | L34: 6460.1001
B35: 5-8 | C35: 275470.33 | D35: 236706.64 | E35: 204835.1 | F35: 162244.29 | G35: 79754.551 | H35: 36705.65 | I35: 18732.821 | J35: 11699.969 | K35: 8796.637 | L35: 7305.3717
B36: 9-11 | C36: 211466.22 | D36: 190606.59 | E36: 172454.5 | F36: 140570.7 | G36: 86163.747 | H36: 45843.858 | I36: 23926.429 | J36: 16298.933 | K36: 9563.5138 | L36: 7271.6357
B37: 12-14 | C37: 218759.28 | D37: 195754.29 | E37: 176142.13 | F37: 142063.8 | G37: 96576.537 | H37: 59564.968 | I37: 36786.836 | J37: 21552.273 | K37: 12766.312 | L37: 6191.8338
A39: Males | B39: Total | C39: 478087.93 | D39: 398960.54 | E39: 345030.29 | F39: 263852.66 | G39: 148992.91 | H39: 77634.915 | I39: 44761.911 | J39: 29906.713 | K39: 15775.273 | L39: 10176.379
A40: Age group | B40: 0-4 | C40: 97826.679 | D40: 67120.738 | E40: 54169.07 | F40: 34966.813 | G40: 10776.942 | H40: 4460.5007 | I40: 2675.0073 | J40: 1565.1799 | K40: 1037.4744 | L40: 1037.4744
B41: 5-8 | C41: 140638.57 | D41: 120715.38 | E41: 100219.85 | F41: 74200.56 | G41: 36065.067 | H41: 14528.351 | I41: 9568.7022 | J41: 7054.6842 | K41: 4653.3289 | L41: 3738.4074
B42: 9-11 | C42: 113824.18 | D42: 101054.32 | E42: 92340.371 | F42: 75260.266 | G42: 47579.005 | H42: 23080.171 | I42: 11552.615 | J42: 6828.6484 | K42: 2755.1993 | L42: 1739.8649
B43: 12-14 | C43: 125798.5 | D43: 110070.11 | E43: 98301 | F43: 79425.025 | G43: 54571.894 | H43: 35565.893 | I43: 20965.586 | J43: 14458.201 | K43: 7329.2706 | L43: 3660.6325
A45: Females | B45: Total | C45: 417206.92 | D45: 363941.74 | E45: 329415.98 | F45: 264590.35 | G45: 145160.69 | H45: 82706.7 | I45: 47966.533 | J45: 27231.37 | K45: 21811.29 | L45: 17052.562
A46: Age group | B46: 0-4 | C46: 91772.349 | D46: 72714.018 | E46: 66845.464 | F46: 48597.412 | G46: 20881.819 | H46: 13766.638 | I46: 10607.35 | J46: 6021.7286 | K46: 5422.6257 | L46: 5422.6257
B47: 5-8 | C47: 134831.76 | D47: 115991.26 | E47: 104615.25 | F47: 88043.726 | G47: 43689.484 | H47: 22177.299 | I47: 9164.119 | J47: 4645.2844 | K47: 4143.3081 | L47: 3566.9643
B48: 9-11 | C48: 97642.039 | D48: 89552.277 | E48: 80114.127 | F48: 65310.435 | G48: 38584.743 | H48: 22763.688 | I48: 12373.814 | J48: 9470.2845 | K48: 6808.3145 | L48: 5531.7708
B49: 12-14 | C49: 92960.778 | D49: 85684.185 | E49: 77841.134 | F49: 62638.78 | G49: 42004.644 | H49: 23999.076 | I49: 15821.249 | J49: 7094.0726 | K49: 5437.0414 | L49: 2531.2013
A51: NB. Please note that for children 0-14 years, data was collected via the child's parent/guardian for organised participation outside of school hours
A52: NB. Estimated participant numbers have not been rounded but users must remember that they are estimates and are subject to margins of error. Refer to sheet number 27 for margin of error and relative margin of error statistics.
A53: * Estimate has relative margin of error between 50% and 100% and should be used with caution
A54: ** Estimate has relative margin of error greater than 100% and is considered too unreliable to use
A55: # AusPlay collects data on gender, including non-binary and self-described. Non-binary and self-described gender are included in Total columns but not reported separately due to sample size. The sum of male and female estimates is not therefore equal to the total.

Sheet 11
A8: =Index!A8 -> AusPlay survey results July 2024 - June 2025
A9: Released at: | C9: 13 November 2025
A10: Table number: | C10: 11
A11: Table name: | C11: Motivations for participation (adults)
A12: Base: | C12: Adult players
C13: Physical health or fitness | D13: Fun/enjoyment | E13: To lose weight/ keep weight off/tone | F13: To be outdoors/to enjoy nature | G13: Social reasons | H13: Psychological/ mental health/ therapy | I13: Sense of achievement | J13: Hobby | K13: Walk the dog | L13: Training purposes | M13: Learn a new skill | N13: Performance or competition | O13: Way of getting around | P13: Physio/rehab/ physical therapy/post-op | Q13: To be a good role model | R13: Professional/ part of my job
C14: Proportion of participants
A15: All | B15: Total | C15: 0.6398854 | D15: 0.58130013 | E15: 0.52062685 | F15: 0.49963317 | G15: 0.43667965 | H15: 0.36497883 | I15: 0.31257808 | J15: 0.29270092 | K15: 0.21927799 | L15: 0.20189523 | M15: 0.14521284 | N15: 0.14219475 | O15: 0.12881774 | P15: 0.12827661 | Q15: 0.089386679 | R15: 0.043699091
A16: Age group | B16: 15-17 | C16: 0.5385761 | D16: 0.73576457 | E16: 0.34800406 | F16: 0.51211556 | G16: 0.59825663 | H16: 0.21231121 | I16: 0.33811109 | J16: 0.53984653 | K16: 0.18839305 | L16: 0.31840931 | M16: 0.29510998 | N16: 0.30319098 | O16: 0.2485254 | P16: 0.059698998 | Q16: 0.090451067 | R16: 0.05294986
B17: 18-24 | C17: 0.5900289 | D17: 0.65522064 | E17: 0.49627859 | F17: 0.45875768 | G17: 0.54249718 | H17: 0.35314105 | I17: 0.35473813 | J17: 0.47248405 | K17: 0.17531508 | L17: 0.32157222 | M17: 0.27133317 | N17: 0.24567267 | O17: 0.15080857 | P17: 0.099736168 | Q17: 0.10494009 | R17: 0.086041065
B18: 25-34 | C18: 0.57844224 | D18: 0.60492228 | E18: 0.54803242 | F18: 0.48001078 | G18: 0.49851129 | H18: 0.40326878 | I18: 0.34149334 | J18: 0.41732714 | K18: 0.2250307 | L18: 0.26975337 | M18: 0.21929794 | N18: 0.18120603 | O18: 0.14026833 | P18: 0.13002832 | Q18: 0.10669086 | R18: 0.068039159
B19: 35-44 | C19: 0.60509389 | D19: 0.58462561 | E19: 0.52112573 | F19: 0.45757151 | G19: 0.39176285 | H19: 0.38813389 | I19: 0.28474881 | J19: 0.29817458 | K19: 0.19209717 | L19: 0.20159563 | M19: 0.11761525 | N19: 0.12387253 | O19: 0.13059039 | P19: 0.12177793 | Q19: 0.11270443 | R19: 0.046228151
B20: 45-54 | C20: 0.65337467 | D20: 0.55565339 | E20: 0.55891605 | F20: 0.50619382 | G20: 0.37115003 | H20: 0.39745031 | I20: 0.27520029 | J20: 0.20738374 | K20: 0.24928028 | L20: 0.18318933 | M20: 0.09968061 | N20: 0.095327059 | O20: 0.14393839 | P20: 0.1238352 | Q20: 0.11729262 | R20: 0.030291079
B21: 55-64 | C21: 0.69247599 | D21: 0.5676784 | E21: 0.61163683 | F21: 0.55704179 | G21: 0.36269626 | H21: 0.40327246 | I21: 0.27869592 | J21: 0.17329232 | K21: 0.27618984 | L21: 0.14109049 | M21: 0.077294503 | N21: 0.079947383 | O21: 0.11504036 | P21: 0.14092598 | Q21: 0.056246569 | R21: 0.022032117
B22: 65+ | C22: 0.7452536 | D22: 0.50149564 | E22: 0.44871862 | F22: 0.53920003 | G22: 0.41735541 | H22: 0.28915324 | I22: 0.33122032 | J22: 0.13919417 | K22: 0.20989297 | L22: 0.084994131 | M22: 0.064257238 | N22: 0.098722291 | O22: 0.071171733 | P22: 0.16142987 | Q22: 0.038099453 | R22: 0.012291861
A24: Males | B24: Total | C24: 0.61200642 | D24: 0.59258546 | E24: 0.49293973 | F24: 0.46037627 | G24: 0.42519752 | H24: 0.30822538 | I24: 0.30972573 | J24: 0.32436349 | K24: 0.17441172 | L24: 0.24497469 | M24: 0.13542983 | N24: 0.18973889 | O24: 0.12080946 | P24: 0.10979586 | Q24: 0.093282902 | R24: 0.052776867
A25: Age group | B25: 15-17 | C25: 0.5415508 | D25: 0.74578727 | E25: 0.20056701 | F25: 0.34526914 | G25: 0.64374572 | H25: 0.13124748 | I25: 0.25829617 | J25: 0.52773036 | K25: 0.068042971 | L25: 0.4139472 | M25: 0.24633658 | N25: 0.35304299 | O25: 0.14323393 | P25: 0.02078936 | Q25: 0.10093722 | R25: 0.041923561
B26: 18-24 | C26: 0.54034106 | D26: 0.65060147 | E26: 0.43705333 | F26: 0.38895301 | G26: 0.52519402 | H26: 0.2778415 | I26: 0.34795964 | J26: 0.50809701 | K26: 0.11328761 | L26: 0.36987296 | M26: 0.25798079 | N26: 0.29482822 | O26: 0.13351687 | P26: 0.10057109 | Q26: 0.1300422 | R26: 0.100423
B27: 25-34 | C27: 0.52654849 | D27: 0.59971814 | E27: 0.48115268 | F27: 0.41110069 | G27: 0.48584827 | H27: 0.33036767 | I27: 0.320803 | J27: 0.43620152 | K27: 0.15219042 | L27: 0.30850397 | M27: 0.20592108 | N27: 0.2411848 | O27: 0.13262603 | P27: 0.11087098 | Q27: 0.10745417 | R27: 0.080392548
B28: 35-44 | C28: 0.56206515 | D28: 0.58967535 | E28: 0.47653522 | F28: 0.41773592 | G28: 0.38428095 | H28: 0.31716992 | I28: 0.2779729 | J28: 0.34167197 | K28: 0.14134371 | L28: 0.25213338 | M28: 0.11991594 | N28: 0.16281165 | O28: 0.11896014 | P28: 0.1068522 | Q28: 0.11134756 | R28: 0.054800137
B29: 45-54 | C29: 0.60345029 | D29: 0.54369836 | E29: 0.54760677 | F29: 0.46571281 | G29: 0.35938838 | H29: 0.3422632 | I29: 0.28206499 | J29: 0.23917787 | K29: 0.20022447 | L29: 0.21218103 | M29: 0.086742826 | N29: 0.13959936 | O29: 0.14071635 | P29: 0.09723272 | Q29: 0.11627416 | R29: 0.03889606
B30: 55-64 | C30: 0.69684955 | D30: 0.59637997 | E30: 0.61569469 | F30: 0.52792199 | G30: 0.34880524 | H30: 0.36908029 | I30: 0.27173554 | J30: 0.22021584 | K30: 0.25508563 | L30: 0.19960065 | M30: 0.070577427 | N30: 0.11879341 | O30: 0.12791615 | P30: 0.12504387 | Q30: 0.058015133 | R30: 0.032808291
B31: 65+ | C31: 0.76282596 | D31: 0.55750138 | E31: 0.4788909 | F31: 0.5743642 | G31: 0.4033781 | H31: 0.25630209 | I31: 0.36379967 | J31: 0.16872244 | K31: 0.21379778 | L31: 0.11096309 | M31: 0.057516394 | N31: 0.15222579 | O31: 0.07446453 | P31: 0.13440728 | Q31: 0.037805207 | R31: 0.01575477
A33: Females | B33: Total | C33: 0.66798976 | D33: 0.57128144 | E33: 0.54898174 | F33: 0.53816032 | G33: 0.44850117 | H33: 0.42004899 | I33: 0.31456468 | J33: 0.26204321 | K33: 0.26308851 | L33: 0.16067743 | M33: 0.15479426 | N33: 0.096242534 | O33: 0.13556334 | P33: 0.1461899 | Q33: 0.086159328 | R33: 0.034469504
A34: Age group | B34: 15-17 | C34: 0.53660596 | D34: 0.72912656 | E34: 0.4456513 | F34: 0.62261759 | G34: 0.5681293 | H34: 0.26599955 | I34: 0.39097234 | J34: 0.54787105 | K34: 0.26810066 | L34: 0.25513477 | M34: 0.32741249 | N34: 0.27017409 | O34: 0.31825972 | P34: 0.085468769 | Q34: 0.083506111 | R34: 0.060252555
B35: 18-24 | C35: 0.6472525 | D35: 0.65806239 | E35: 0.56764706 | F35: 0.53565486 | G35: 0.56344384 | H35: 0.44215441 | I35: 0.36075233 | J35: 0.43553847 | K35: 0.24471011 | L35: 0.26849435 | M35: 0.28565006 | N35: 0.19004512 | O35: 0.16312961 | P35: 0.099822965 | Q35: 0.078548625 | R35: 0.069802177
B36: 25-34 | C36: 0.62568698 | D36: 0.61057001 | E36: 0.61148032 | F36: 0.54113591 | G36: 0.51260913 | H36: 0.46856156 | I36: 0.35808238 | J36: 0.39999866 | K36: 0.29345659 | L36: 0.23625245 | M36: 0.23382792 | N36: 0.12668887 | O36: 0.14540837 | P36: 0.14784462 | Q36: 0.10660072 | R36: 0.056588691
B37: 35-44 | C37: 0.6512897 | D37: 0.58063578 | E37: 0.57030267 | F37: 0.50009726 | G37: 0.40089652 | H37: 0.46059385 | I37: 0.29098695 | J37: 0.25350832 | K37: 0.24175634 | L37: 0.15105653 | M37: 0.11523259 | N37: 0.085539675 | O37: 0.14365686 | P37: 0.13692251 | Q37: 0.11398728 | R37: 0.03548382
B38: 45-54 | C38: 0.70462699 | D38: 0.5710506 | E38: 0.56968029 | F38: 0.54996853 | G38: 0.38137818 | H38: 0.45324605 | I38: 0.26796143 | J38: 0.17687721 | K38: 0.30213497 | L38: 0.15519979 | M38: 0.11299055 | N38: 0.050740086 | O38: 0.14664263 | P38: 0.14956245 | Q38: 0.11985562 | R38: 0.021987335
B39: 55-64 | C39: 0.68926366 | D39: 0.54267396 | E39: 0.60973347 | F39: 0.58617503 | G39: 0.37706739 | H39: 0.43650337 | I39: 0.28577865 | J39: 0.12787539 | K39: 0.29570014 | L39: 0.084008102 | M39: 0.084409736 | N39: 0.041966763 | O39: 0.10298371 | P39: 0.15593521 | Q39: 0.054833674 | R39: 0.011495136
B40: 65+ | C40: 0.7298227 | D40: 0.45049083 | E40: 0.42102906 | F40: 0.50770182 | G40: 0.43135682 | H40: 0.32043887 | I40: 0.3016427 | J40: 0.11200895 | K40: 0.20674703 | L40: 0.06099804 | M40: 0.070688396 | N40: 0.049104338 | O40: 0.068270716 | P40: 0.18607692 | Q40: 0.038462945 | R40: 0.0090942769
C41: Estimated number of participants
A42: All# | B42: Total | C42: 3209443 | D42: 2915599.6 | E42: 2611283.5 | F42: 2505986.5 | G42: 2190233.5 | H42: 1830607.1 | I42: 1567783.1 | J42: 1468086.2 | K42: 1099822.3 | L42: 1012636.4 | M42: 728337.21 | N42: 713199.48 | O42: 646105.05 | P42: 643390.96 | Q42: 448332.55 | R42: 219179.47
A43: Age group | B43: 15-17 | C43: 109654.72 | D43: 149802.53 | E43: 70854.033 | F43: 104267.33 | G43: 121805.75 | H43: 43226.811 | I43: 68839.813 | J43: 109913.39 | K43: 38357.046 | L43: 64828.508 | M43: 60084.736 | N43: 61730.037 | O43: 50600.062 | P43: 12154.786 | Q43: 18415.943 | R43: 10780.653
B44: 18-24 | C44: 356019.28 | D44: 395355.51 | E44: 299451 | F44: 276811.15 | G44: 327338.97 | H44: 213082.82 | I44: 214046.49 | J44: 285093.54 | K44: 105783.88 | L44: 194034.41 | M44: 163720.52 | N44: 148237.16 | O44: 90996.827 | P44: 60180.1 | Q44: 63320.109 | R44: 51916.572
B45: 25-34 | C45: 561414.07 | D45: 587114.59 | E45: 531899.46 | F45: 465880.24 | G45: 483836.13 | H45: 391397.36 | I45: 331440.46 | J45: 405041.88 | K45: 218406.25 | L45: 261812.38 | M45: 212842.25 | N45: 175871.69 | O45: 136139.12 | P45: 126200.55 | Q45: 103550.1 | R45: 66036.224
B46: 35-44 | C46: 542759.97 | D46: 524400.23 | E46: 467441.81 | F46: 410434.65 | G46: 351405.29 | H46: 348150.17 | I46: 255415.33 | J46: 267458.04 | K46: 172308.22 | L46: 180828.2 | M46: 105499.08 | N46: 111111.77 | O46: 117137.59 | P46: 109232.94 | Q46: 101094.15 | R46: 41465.945
B47: 45-54 | C47: 502508.76 | D47: 427351.57 | E47: 429860.87 | F47: 389312.35 | G47: 285450.52 | H47: 305678 | I47: 211655.83 | J47: 159498.29 | K47: 191720.82 | L47: 140890.43 | M47: 76664.097 | N47: 73315.793 | O47: 110702.64 | P47: 95241.328 | Q47: 90209.452 | R47: 23296.79
B48: 55-64 | C48: 452180.56 | D48: 370688.86 | E48: 399393.32 | F48: 363743.26 | G48: 236837.38 | H48: 263333.27 | I48: 181985.92 | J48: 113158.32 | K48: 180349.47 | L48: 92130.814 | M48: 50472.612 | N48: 52204.918 | O48: 75120.312 | P48: 92023.394 | Q48: 36728.501 | R48: 14386.773
B49: 65+ | C49: 684905.65 | D49: 460886.33 | E49: 412383 | F49: 495537.55 | G49: 383559.47 | H49: 265738.65 | I49: 304399.3 | J49: 127922.73 | K49: 192896.59 | L49: 78111.613 | M49: 59053.919 | N49: 90728.115 | O49: 65408.503 | P49: 148357.86 | Q49: 35014.296 | R49: 11296.51
A51: Males | B51: Total | C51: 1510576 | D51: 1462640.5 | E51: 1216691.4 | F51: 1136317.1 | G51: 1049487.6 | H51: 760772.85 | I51: 764476.07 | J51: 800605.52 | K51: 430489.21 | L51: 604655.25 | M51: 334272.72 | N51: 468320.27 | O51: 298186.2 | P51: 271002.04 | Q51: 230244.18 | R51: 130265.74
A52: Age group | B52: 15-17 | C52: 43930.281 | D52: 60497.824 | E52: 16269.878 | F52: 28008.029 | G52: 52220.274 | H52: 10646.718 | I52: 20952.833 | J52: 42809.176 | K52: 5519.6057 | L52: 33579.153 | M52: 19982.678 | N52: 28638.639 | O52: 11619.052 | P52: 1686.4206 | Q52: 8187.9676 | R52: 3400.8145
B53: 18-24 | C53: 173669.64 | D53: 209108.15 | E53: 140472.19 | F53: 125012.39 | G53: 168801.26 | H53: 89300.324 | I53: 111836.82 | J53: 163306.16 | K53: 36411.48 | L53: 118879.92 | M53: 82916.944 | N53: 94759.983 | O53: 42913.316 | P53: 32324.296 | Q53: 41796.529 | R53: 32276.7
B54: 25-34 | C54: 244963.71 | D54: 279004.09 | E54: 223844.43 | F54: 191254.47 | G54: 226028.94 | H54: 153695.42 | I54: 149245.69 | J54: 202932.01 | K54: 70802.845 | L54: 143523.87 | M54: 95799.708 | N54: 112205.29 | O54: 61700.992 | P54: 51579.994 | Q54: 49990.404 | R54: 37400.653
B55: 35-44 | C55: 252764.15 | D55: 265180.63 | E55: 214300.81 | F55: 187858.41 | G55: 172813.5 | H55: 142633.26 | I55: 125006.12 | J55: 153651.98 | K55: 63563.132 | L55: 113385.93 | M55: 53926.935 | N55: 73217.399 | O55: 53497.106 | P55: 48052.091 | Q55: 50073.68 | R55: 24643.958
B56: 45-54 | C56: 231819.61 | D56: 208865.49 | E56: 210366.94 | F56: 178906.81 | G56: 138061.54 | H56: 131482.78 | I56: 108357.22 | J56: 91881.837 | K56: 76917.618 | L56: 81510.815 | M56: 33322.858 | N56: 53628.063 | O56: 54057.162 | P56: 37352.623 | Q56: 44667.525 | R56: 14942.191
B57: 55-64 | C57: 225704 | D57: 193162.71 | E57: 199418.59 | F57: 170989.72 | G57: 112975.23 | H57: 119542.16 | I57: 88012.97 | J57: 71326.152 | K57: 82620.198 | L57: 64649.055 | M57: 22859.465 | N57: 38476.237 | O57: 41431.019 | P57: 40500.711 | Q57: 18790.638 | R57: 10626.343
B58: 65+ | C58: 337724.65 | D58: 246821.64 | E58: 212018.56 | F58: 254287.29 | G58: 178586.91 | H58: 113472.19 | I58: 161064.42 | J58: 74698.202 | K58: 94654.331 | L58: 49126.503 | M58: 25464.136 | N58: 67394.667 | O58: 32967.556 | P58: 59505.909 | Q58: 16737.435 | R58: 6975.0828
A60: Females | B60: Total | C60: 1683554.7 | D60: 1439817.8 | E60: 1383615.2 | F60: 1356341.7 | G60: 1130371 | H60: 1058662.1 | I60: 792806.84 | J60: 660435.39 | K60: 663069.9 | L60: 404960.18 | M60: 390132.64 | N60: 242562.96 | O60: 341664.38 | P60: 368446.81 | Q60: 217149.95 | R60: 86874.529
A61: Age group | B61: 15-17 | C61: 65724.442 | D61: 89304.704 | E61: 54584.155 | F61: 76259.298 | G61: 69585.476 | H61: 32580.093 | I61: 47886.979 | J61: 67104.21 | K61: 32837.441 | L61: 31249.355 | M61: 40102.058 | N61: 33091.398 | O61: 38981.01 | P61: 10468.365 | Q61: 10227.975 | R61: 7379.8389
B62: 18-24 | C62: 177357.54 | D62: 180319.62 | E62: 155544.38 | F62: 146778 | G62: 154392.63 | H62: 121157.38 | I62: 98851.91 | J62: 119344.51 | K62: 67054.486 | L62: 73571.747 | M62: 78272.687 | N62: 52075.403 | O62: 44700.122 | P62: 27353.09 | Q62: 21523.58 | R62: 19126.913
B63: 25-34 | C63: 311931.56 | D63: 304395.1 | E63: 304848.93 | F63: 269779.25 | G63: 255557.44 | H63: 233597.85 | I63: 178519.29 | J63: 199416.33 | K63: 146300.58 | L63: 117781.89 | M63: 116573.16 | N63: 63159.787 | O63: 72492.255 | P63: 73706.828 | Q63: 53144.99 | R63: 28211.868
B64: 35-44 | C64: 288523.56 | D64: 257223.63 | E64: 252646.03 | F64: 221544.79 | G64: 177598.53 | H64: 204044.65 | I64: 128908.21 | J64: 112305.05 | K64: 107098.88 | L64: 66918.558 | M64: 51048.431 | N64: 37894.368 | O64: 63640.481 | P64: 60657.141 | Q64: 50496.755 | R64: 15719.453
B65: 45-54 | C65: 267739.38 | D65: 216983.93 | E65: 216463.25 | F65: 208973.31 | G65: 144913.49 | H65: 172221.36 | I65: 101818.17 | J65: 67208.601 | K65: 114803.2 | L65: 58971.762 | M65: 42933.383 | N65: 19279.874 | O65: 55720.272 | P65: 56829.726 | Q65: 45541.927 | R65: 8354.5986
B66: 55-64 | C66: 225480.37 | D66: 177526.15 | E66: 199463.48 | F66: 191756.76 | G66: 123350.9 | H66: 142794.33 | I66: 93487.412 | J66: 41832.164 | K66: 96733.051 | L66: 27481.759 | M66: 27613.147 | N66: 13728.681 | O66: 33689.293 | P66: 51011.436 | Q66: 17937.863 | R66: 3760.4298
B67: 65+ | C67: 346797.88 | D67: 214064.68 | E67: 200065.01 | F67: 241250.26 | G67: 204972.57 | H67: 152266.46 | I67: 143334.88 | J67: 53224.527 | K67: 98242.263 | L67: 28985.11 | M67: 33589.783 | N67: 23333.449 | O67: 32440.947 | P67: 88420.219 | Q67: 18276.861 | R67: 4321.4276
A69: NB. Please note that motivations for participation were collected for adults (15 years and over) only
A70: NB. This table presents all the motivations presented to respondents in the online AusPlay questionnaire.
A71: NB. Estimated participant numbers have not been rounded but users must remember that they are estimates and are subject to margins of error. Refer to sheet number 27 for margin of error and relative margin of error statistics.
A72: * Estimate has relative margin of error between 50% and 100% and should be used with caution
A73: ** Estimate has relative margin of error greater than 100% and is considered too unreliable to use
A74: # AusPlay collects data on gender, including non-binary and self-described. Non-binary and self-described gender are included in Total columns but not reported separately due to sample size. The sum of male and female estimates is not therefore equal to the total.

Sheet 12
A8: =Index!A8 -> AusPlay survey results July 2024 - June 2025
A9: Released at: | C9: 13 November 2025
A10: Table number: | C10: 12
A11: Table name: | C11: Barriers to participation (adults)
A12: Base: | C12: Adult non-players
C13: Poor health or injury | D13: Increasing age/ too old | E13: Disability | F13: Too lazy | G13: Not enough time/ too many other commitments | H13: Don’t like sport/physical activity | I13: Not a priority | J13: Nobody to do it with | K13: Can't afford it | L13: Fear of injury | M13: Physical job | N13: The weather | O13: Not good enough | P13: Too busy doing children's activities | Q13: Looking after child/ren | R13: Not value for money/not worth it | S13: No transport/ can't get there | T13: No opportunities/ facilities/clubs in my areas | U13: Too competitive | V13: Fear of discrimination | W13: Not familiar with activity/rules | X13: Pregnancy | Y13: No longer interested/ don't like it | Z13: Not culturally appropriate
C14: Proportion of non-participants
A15: All | B15: Total | C15: 0.30104044 | D15: 0.2004934 | E15: 0.16302272 | F15: 0.16167305 | G15: 0.16073832 | H15: 0.14965674 | I15: 0.13001295 | J15: 0.077725305 | K15: 0.057537505 | L15: 0.069389863 | M15: 0.054542261 | N15: 0.059156764 | O15: 0.046063335 | P15: 0.026326144 | Q15: 0.029193362 | R15: 0.039348905 | S15: 0.021909755 | T15: 0.022047707 | U15: 0.030848998 | V15: 0.025729902 | W15: 0.016917037 | X15: 0.01368939 | Y15: 0.014047786 | Z15: 0.0085606554
A17: Males^ | B17: Total | C17: 0.24652521 | D17: 0.17115256 | E17: 0.12263895 | F17: 0.1585509 | G17: 0.14627068 | H17: 0.11099159 | I17: 0.1393139 | J17: 0.072532397 | K17: 0.040255634 | L17: 0.089250701 | M17: 0.070530482 | N17: 0.052943823 | O17: 0.047968415 | P17: 0.0272745 | Q17: 0.023614186 | R17: 0.046224067 | S17: 0.011221909 | T17: 0.019075428 | U17: 0.032797045 | V17: 0.023708953 | W17: 0.019644998 | X17: 0.009233869 | Y17: 0.0093074439 | Z17: 0.0081205067
A19: Females^ | B19: Total | C19: 0.34252319 | D19: 0.23197323 | E19: 0.19764794 | F19: 0.16485633 | G19: 0.1766781 | H19: 0.18639699 | I19: 0.12569639 | J19: 0.082435844 | K19: 0.066367294 | L19: 0.054081026 | M19: 0.036934908 | N19: 0.066311221 | O19: 0.043506416 | P19: 0.026268335 | Q19: 0.034918021 | R19: 0.030652935 | S19: 0.031881263 | T19: 0.02396245 | U19: 0.028923487 | V19: 0.028246882 | W19: 0.015030374 | X19: 0.017979554 | Y19: 0.018597085 | Z19: 0.0091953327
C20: Estimated number of non-participants
A21: All# | B21: Total | C21: 226338.17 | D21: 150741.57 | E21: 122569.13 | F21: 121554.37 | G21: 120851.59 | H21: 112519.87 | I21: 97750.634 | J21: 58438.007 | K21: 43259.748 | L21: 52170.98 | M21: 41007.765 | N21: 44477.193 | O21: 34632.859 | P21: 19793.391 | Q21: 21949.118 | R21: 29584.594 | S21: 16472.916 | T21: 16576.636 | U21: 23193.913 | V21: 19345.105 | W21: 12719.126 | X21: 10292.41 | Y21: 10561.871 | Z21: 6436.3548
A23: Males^ | B23: Total | C23: 85063.393 | D23: 59056.1 | E23: 42316.505 | F23: 54707.903 | G23: 50470.62 | H23: 38297.59 | I23: 48070.187 | J23: 25027.265 | K23: 13890.185 | L23: 30795.907 | M23: 24336.506 | N23: 18268.238 | O23: 16551.476 | P23: 9411.0519 | Q23: 8148.0626 | R23: 15949.59 | S23: 3872.1138 | T23: 6581.9665 | U23: 11316.603 | V23: 8180.7617 | W23: 6778.4963 | X23: 3186.1416 | Y23: 3211.5286 | Z23: 2801.9765
A25: Females^ | B25: Total | C25: 135379.42 | D25: 91685.475 | E25: 78118.692 | F25: 65158.084 | G25: 69830.541 | H25: 73671.85 | I25: 49680.447 | J25: 32582.077 | K25: 26231.117 | L25: 21375.073 | M25: 14598.213 | N25: 26208.955 | O25: 17195.547 | P25: 10382.339 | Q25: 13801.056 | R25: 12115.316 | S25: 12600.802 | T25: 9470.9577 | U25: 11431.766 | V25: 11164.344 | W25: 5940.6295 | X25: 7106.2682 | Y25: 7350.342 | Z25: 3634.3783
A27: NB. This table presents all the barriers presented to respondents in the online AusPlay questionnaire.
A28: NB. Estimated participant numbers have not been rounded but users must remember that they are estimates and are subject to margins of error. Refer to sheet number 27 for margin of error and relative margin of error statistics.
A29: ^ Age group data by gender has not been reported due to sample size
A30: * Estimate has relative margin of error between 50% and 100% and should be used with caution
A31: ** Estimate has relative margin of error greater than 100% and is considered too unreliable to use
A32: # AusPlay collects data on gender, including non-binary and self-described. Non-binary and self-described gender are included in Total columns but not reported separately due to sample size. The sum of male and female estimates is not therefore equal to the total.

Sheet 13
A8: =Index!A8 -> AusPlay survey results July 2024 - June 2025
A9: Released at: | C9: 13 November 2025
A10: Table number: | C10: 13
A11: Table name: | C11: Barriers to participation (children)
A12: Base: | C12: Child non-players
C13: Wrong age/too old/too young | D13: Doesn't like physical activity | E13: Can't afford it/ can't afford transport | F13: Already does enough | G13: Not a priority | H13: Not enough time/ too many other commitments | I13: Too lazy | J13: Disability | K13: Poor health or injury | L13: Not value for money/not worth it | M13: No opportunities/ facilities/clubs in my areas | N13: No longer interested | O13: Fear of injury | P13: Waiting list | Q13: The weather | R13: Nobody to do it with | S13: Not familiar with activity/rules | T13: No transport/can't get there | U13: Too competitve | V13: Not good enough | W13: Fear of discrimination | X13: Not culturally appropriate | Y13: Focus on or move to a different activity/sport
C14: Proportion of non-participants
A15: All | B15: Total | C15: 0.44685679 | D15: 0.071129957 | E15: 0.073031458 | F15: 0.058691152 | G15: 0.076310275 | H15: 0.056218542 | I15: 0.034586446 | J15: 0.038775903 | K15: 0.038387445 | L15: 0.031740897 | M15: 0.01299258 | N15: 0.01770531 | O15: 0.023103194 | P15: 0.022615796 | Q15: 0.025349015 | R15: 0.019917559 | S15: 0.028793551 | T15: 0.0162754 | U15: 0.019481352 | V15: 0.017427633 | W15: 0.0087228487 | X15: 0.014603224 | Y15: 0.0069026653
A17: Males^ | B17: Total | C17: 0.48164437 | D17: 0.077493054 | E17: 0.057045031 | F17: 0.071547584 | G17: 0.062132771 | H17: 0.040378797 | I17: 0.029571503 | J17: 0.04655161 | K17: 0.040499049 | L17: 0.032588837 | M17: 0.01407181 | N17: 0.014418181 | O17: 0.016614599 | P17: 0.023516803 | Q17: 0.02913938 | R17: 0.012968132 | S17: 0.030684611 | T17: 0.010254989 | U17: 0.019269734 | V17: 0.019724923 | W17: 0.012170409 | X17: 0.0029990618 | Y17: 0.0081200269
A19: Females^ | B19: Total | C19: 0.41326036 | D19: 0.064847656 | E19: 0.092068542 | F19: 0.044899036 | G19: 0.093342429 | H19: 0.07487231 | I19: 0.034140742 | J19: 0.028117083 | K19: 0.033212934 | L19: 0.031191459 | M19: 0.011939052 | N19: 0.021654464 | O19: 0.030745478 | P19: 0.021888357 | Q19: 0.021386777 | R19: 0.028040233 | S19: 0.027025433 | T19: 0.023299555 | U19: 0.016897152 | V19: 0.015052849 | W19: 0.0049337002 | X19: 0.02792536 | Y19: 0.0056140921
C20: Estimated number of participants
A21: All# | B21: Total | C21: 146465.5 | D21: 23314.147 | E21: 23937.398 | F21: 19237.1 | G21: 25012.091 | H21: 18426.657 | I21: 11336.341 | J21: 12709.513 | K21: 12582.189 | L21: 10403.66 | M21: 4258.556 | N21: 5803.2397 | O21: 7572.495 | P21: 7412.7415 | Q21: 8308.6042 | R21: 6528.345 | S21: 9437.6138 | T21: 5334.5605 | U21: 6385.3701 | V21: 5712.2261 | W21: 2859.0735 | X21: 4786.4742 | Y21: 2262.475
A23: Males^ | B23: Total | C23: 83308.336 | D23: 13403.702 | E23: 9866.8788 | F23: 12375.334 | G23: 10746.887 | H23: 6984.1788 | I23: 5114.879 | J23: 8051.8686 | K23: 7004.9783 | L23: 5636.7767 | M23: 2433.9516 | N23: 2493.8621 | O23: 2873.7689 | P23: 4067.6189 | Q23: 5040.1363 | R23: 2243.0523 | S23: 5307.4096 | T23: 1773.7694 | U23: 3333.0184 | V23: 3411.7508 | W23: 2105.073 | X23: 518.7372 | Y23: 1404.4926
A25: Females^ | B25: Total | C25: 63157.164 | D25: 9910.445 | E25: 14070.52 | F25: 6861.7659 | G25: 14265.204 | H25: 11442.479 | I25: 5217.6125 | J25: 4297.0374 | K25: 5075.8189 | L25: 4766.8838 | M25: 1824.6044 | N25: 3309.3776 | O25: 4698.726 | P25: 3345.1227 | Q25: 3268.4679 | R25: 4285.2927 | S25: 4130.2043 | T25: 3560.7911 | U25: 2582.3339 | V25: 2300.4753 | W25: 754.0005 | X25: 4267.737 | Y25: 857.98246
A27: NB. Please note that for children 0-14 years, data was collected via the child's parent/guardian for organised participation outside of school hours
A28: NB. This table presents all the barriers presented to respondents in the online AusPlay questionnaire.
A29: NB. Estimated participant numbers have not been rounded but users must remember that they are estimates and are subject to margins of error. Refer to sheet number 27 for margin of error and relative margin of error statistics.
A30: ^ Age group data by gender has not been reported due to sample size
A31: * Estimate has relative margin of error between 50% and 100% and should be used with caution
A32: ** Estimate has relative margin of error greater than 100% and is considered too unreliable to use
A33: # AusPlay collects data on gender, including non-binary and self-described. Non-binary and self-described gender are included in Total columns but not reported separately due to sample size. The sum of male and female estimates is not therefore equal to the total.

Sheet 14
A8: =Index!A8 -> AusPlay survey results July 2024 - June 2025
A9: Released at: | C9: 13 November 2025
A10: Table number: | C10: 14
A11: Table name: | C11: Sport or non-sport related participation (adults)
A12: Base: | C12: Adult population
C13: Total | D13: Sport-related activities only | E13: Non-sport related activities only | F13: Both sport and non-sport related activities
C14: Participation rate
A15: All# | B15: Total | C15: 0.86963983 | D15: 0.14694136 | E15: 0.35403483 | F15: 0.36866364
A16: Age group | B16: 15-17 | C16: 0.84583468 | D16: 0.22673129 | E16: 0.13853886 | F16: 0.48056453
B17: 18-24 | C17: 0.88919859 | D17: 0.23501446 | E17: 0.20348316 | F17: 0.45070097
B18: 25-34 | C18: 0.91865092 | D18: 0.21148445 | E18: 0.25751205 | F18: 0.44965442
B19: 35-44 | C19: 0.89233389 | D19: 0.17399174 | E19: 0.32382582 | F19: 0.39451632
B20: 45-54 | C20: 0.89145479 | D20: 0.12662478 | E20: 0.38929427 | F20: 0.37553575
B21: 55-64 | C21: 0.8752102 | D21: 0.060100071 | E21: 0.46332736 | F21: 0.35178277
B22: 65+ | C22: 0.78038467 | D22: 0.068792237 | E22: 0.50213812 | F22: 0.20945431
A24: Males | B24: Total | C24: 0.87734998 | D24: 0.21432735 | E24: 0.2780116 | F24: 0.38501103
A25: Age group | B25: 15-17 | C25: 0.81985642 | D25: 0.32047672 | E25: 0.04588322 | F25: 0.45349648
B26: 18-24 | C26: 0.88133157 | D26: 0.33472051 | E26: 0.1556582 | F26: 0.39095286
B27: 25-34 | C27: 0.92020703 | D27: 0.31279581 | E27: 0.1677234 | F27: 0.43968782
B28: 35-44 | C28: 0.88795492 | D28: 0.2498407 | E28: 0.23679955 | F28: 0.40131466
B29: 45-54 | C29: 0.90325368 | D29: 0.19020406 | E29: 0.33311048 | F29: 0.37993915
B30: 55-64 | C30: 0.87325812 | D30: 0.090623181 | E30: 0.36494961 | F30: 0.41768534
B31: 65+ | C31: 0.81769266 | D31: 0.092365305 | E31: 0.44153717 | F31: 0.28379018
A33: Females | B33: Total | C33: 0.8644377 | D33: 0.083152157 | E33: 0.42837026 | F33: 0.35291527
A34: Age group | B34: 15-17 | C34: 0.88504676 | D34: 0.16523937 | E34: 0.20816434 | F34: 0.51164305
B35: 18-24 | C35: 0.90036213 | D35: 0.12123427 | E35: 0.2587939 | F35: 0.52033395
B36: 25-34 | C36: 0.91694021 | D36: 0.1200953 | E36: 0.34075235 | F36: 0.45609256
B37: 35-44 | C37: 0.89883808 | D37: 0.095819159 | E37: 0.41278247 | F37: 0.39023645
B38: 45-54 | C38: 0.87860481 | D38: 0.065553946 | E38: 0.44328171 | F38: 0.36976915
B39: 55-64 | C39: 0.87649254 | D39: 0.030084052 | E39: 0.56093262 | F39: 0.28547586
B40: 65+ | C40: 0.75356774 | D40: 0.048482501 | E40: 0.55758402 | F40: 0.14750122
C41: Estimated number of participants
A42: All# | B42: Total | C42: 5015652.8 | D42: 847485.14 | E42: 2041898 | F42: 2126269.7
A43: Age group | B43: 15-17 | C43: 203601.17 | D43: 54576.57 | E43: 33347.739 | F43: 115676.86
B44: 18-24 | C44: 603392.95 | D44: 159476.26 | E44: 138079.73 | F44: 305836.95
B45: 25-34 | C45: 970562.03 | D45: 223435.01 | E45: 272063.53 | F45: 475063.49
B46: 35-44 | C46: 896984.71 | D46: 174898.59 | E46: 325513.6 | F46: 396572.53
B47: 45-54 | C47: 769097.39 | D47: 109244.79 | E47: 335861.35 | F47: 323991.26
B48: 55-64 | C48: 652990.96 | D48: 44840.431 | E48: 345686.76 | F48: 262463.77
B49: 65+ | C49: 919023.6 | D49: 81013.496 | E49: 591345.28 | F49: 246664.83
A51: Males | B51: Total | C51: 2468235.6 | D51: 602963.93 | E51: 782125.88 | F51: 1083145.8
A52: Age group | B52: 15-17 | C52: 81119.411 | D52: 31709.067 | E52: 4539.8434 | F52: 44870.5
B53: 18-24 | C53: 321407.44 | D53: 122067.18 | E53: 56766.04 | F53: 142574.21
B54: 25-34 | C54: 465225.36 | D54: 158138.92 | E54: 84795.246 | F54: 222291.2
B55: 35-44 | C55: 449706.14 | D55: 126532.21 | E55: 119927.5 | F55: 203246.43
B56: 45-54 | C56: 384156.93 | D56: 80894.447 | E56: 141673.04 | F56: 161589.44
B57: 55-64 | C57: 323892.01 | D57: 33612.197 | E57: 135360.05 | F57: 154919.77
B58: 65+ | C58: 442728.31 | D58: 50009.909 | E58: 239064.16 | F58: 153654.25
A60: Females | B60: Total | C60: 2520330.1 | D60: 242436.08 | E60: 1248944.3 | F60: 1028949.8
A61: Age group | B61: 15-17 | C61: 122481.76 | D61: 22867.502 | E61: 28807.895 | F61: 70806.361
B62: 18-24 | C62: 274016 | D62: 36896.41 | E62: 78761.276 | F62: 158358.31
B63: 25-34 | C63: 498542.5 | D63: 65296.089 | E63: 185267.84 | F63: 247978.57
B64: 35-44 | C64: 443003.41 | D64: 47225.652 | E64: 203444.92 | F64: 192332.84
B65: 45-54 | C65: 379973.22 | D65: 28350.339 | E65: 191707.55 | F65: 159915.33
B66: 55-64 | C66: 327132.25 | D66: 11228.234 | E66: 209356.2 | F66: 106547.81
B67: 65+ | C67: 475181 | D67: 30571.855 | E67: 351598.56 | F67: 93010.587
A69: NB. Estimated participant numbers have not been rounded but users must remember that they are estimates and are subject to margins of error. Refer to sheet number 27 for margin of error and relative margin of error statistics.
A70: * Estimate has relative margin of error between 50% and 100% and should be used with caution
A71: ** Estimate has relative margin of error greater than 100% and is considered too unreliable to use
A72: # AusPlay collects data on gender, including non-binary and self-described. Non-binary and self-described gender are included in Total columns but not reported separately due to sample size. The sum of male and female estimates is not therefore equal to the total.

Sheet 15
A8: =Index!A8 -> AusPlay survey results July 2024 - June 2025
A9: Released at: | C9: 13 November 2025
A10: Table number: | C10: 15
A11: Table name: | C11: Sport or non-sport related participation (children)
A12: Base: | C12: Child population
C13: Total | D13: Sport-related activities only | E13: Non-sport related activities only | F13: Both sport and non-sport related activities
C14: Participation rate
A15: All# | B15: Total | C15: 0.73214143 | D15: 0.60153011 | E15: 0.057285157 | F15: 0.073326162
A16: Age group | B16: 0-4 | C16: 0.49966693 | D16: 0.37837689 | E16: 0.07699239 | F16: 0.044297655
B17: 5-8 | C17: 0.82201643 | D17: 0.6821578 | E17: 0.045765207 | F17: 0.094093427
B18: 9-11 | C18: 0.85018509 | D18: 0.71064032 | E18: 0.046960687 | F18: 0.092584083
B19: 12-14 | C19: 0.84408334 | D19: 0.72031237 | E19: 0.053144883 | F19: 0.070626093
A21: Males | B21: Total | C21: 0.73432868 | D21: 0.63434649 | E21: 0.048864811 | F21: 0.051117379
A22: Age group | B22: 0-4 | C22: 0.47976559 | D22: 0.37454752 | E22: 0.068556057 | F22: 0.03666201
B23: 5-8 | C23: 0.82510263 | D23: 0.71465609 | E23: 0.050127797 | F23: 0.06031875
B24: 9-11 | C24: 0.87466939 | D24: 0.78291769 | E24: 0.019418474 | F24: 0.072333233
B25: 12-14 | C25: 0.85830895 | D25: 0.77047289 | E25: 0.046146201 | F25: 0.041689853
A27: Females | B27: Total | C27: 0.73189896 | D27: 0.56571531 | E27: 0.067160986 | F27: 0.099022662
A28: Age group | B28: 0-4 | C28: 0.52100406 | D28: 0.38069688 | E28: 0.08701996 | F28: 0.053287222
B29: 5-8 | C29: 0.82368095 | D29: 0.65236643 | E29: 0.041494158 | F29: 0.12982036
B30: 9-11 | C30: 0.82780859 | D30: 0.63477394 | E30: 0.077603412 | F30: 0.11543123
B31: 12-14 | C31: 0.82821936 | D31: 0.65712683 | E31: 0.06245452 | F31: 0.10863801
C32: Estimated number of participants
A33: All# | B33: Total | C33: 895893.56 | D33: 736069.47 | E33: 70097.663 | F33: 89726.43
A34: Age group | B34: 0-4 | C34: 190197.74 | D34: 144028.8 | E34: 29307.079 | F34: 16861.86
B35: 5-8 | C35: 275470.33 | D35: 228601.55 | E35: 15336.624 | F35: 31532.152
B36: 9-11 | C36: 211466.22 | D36: 176757.3 | E36: 11680.514 | F36: 23028.404
B37: 12-14 | C37: 218759.28 | D37: 186681.82 | E37: 13773.446 | F37: 18304.014
A39: Males | B39: Total | C39: 478087.93 | D39: 412994.08 | E39: 31813.651 | F39: 33280.195
A40: Age group | B40: 0-4 | C40: 97826.679 | D40: 76372.172 | E40: 13978.934 | F40: 7475.573
B41: 5-8 | C41: 140638.57 | D41: 121812.98 | E41: 8544.2724 | F41: 10281.318
B42: 9-11 | C42: 113824.18 | D42: 101884.17 | E42: 2527.0027 | F42: 9413.009
B43: 12-14 | C43: 125798.5 | D43: 112924.77 | E43: 6763.4423 | F43: 6110.2952
A45: Females | B45: Total | C45: 417206.92 | D45: 322476.68 | E45: 38284.012 | F45: 56446.234
A46: Age group | B46: 0-4 | C46: 91772.349 | D46: 67057.916 | E46: 15328.146 | F46: 9386.2868
B47: 5-8 | C47: 134831.76 | D47: 106788.57 | E47: 6792.3511 | F47: 21250.834
B48: 9-11 | C48: 97642.039 | D48: 74873.132 | E48: 9153.5114 | F48: 13615.395
B49: 12-14 | C49: 92960.778 | D49: 73757.055 | E49: 7010.0036 | F49: 12193.719
A51: NB. Please note that for children 0-14 years, data was collected via the child's parent/guardian for organised participation outside of school hours
A52: NB. Estimated participant numbers have not been rounded but users must remember that they are estimates and are subject to margins of error. Refer to sheet number 27 for margin of error and relative margin of error statistics.
A53: * Estimate has relative margin of error between 50% and 100% and should be used with caution
A54: ** Estimate has relative margin of error greater than 100% and is considered too unreliable to use
A55: # AusPlay collects data on gender, including non-binary and self-described. Non-binary and self-described gender are included in Total columns but not reported separately due to sample size. The sum of male and female estimates is not therefore equal to the total.

Sheet 16
A8: =Index!A8 -> AusPlay survey results July 2024 - June 2025
A9: Released at: | B9: 13 November 2025
A10: Table number: | B10: 16
A11: Table name: | B11: Participation by activity (adults)
A12: Base: | B12: Adult population
G13: Age group
B14: Total# | D14: Males | E14: Females | G14: 15-17 | H14: 18-24 | I14: 25-34 | J14: 35-44 | K14: 45-54 | L14: 55-64 | M14: 65+
B15: Participation rate
A16: Adventure racing | B16: 0.0014011198 | D16: 0.0022006672 | E16: 0.00064819614 | G16: 0 | H16: 0.0039616805 | I16: 0.0018313612 | J16: 0.0024474283 | K16: 0.0011563278 | L16: 0 | M16: 0
A17: Air sports | B17: 0.0039644977 | D17: 0.0061822446 | E17: 0.0018771095 | G17: 0.014044025 | H17: 0.0090046003 | I17: 0.0091072311 | J17: 0.0015994723 | K17: 0.0014522615 | L17: 0.0011952524 | M17: 0
A18: Archery | B18: 0.0020585148 | D18: 0.0029559075 | E18: 0.001219893 | G18: 0.0058824185 | H18: 0.0041941819 | I18: 0.001442566 | J18: 0.0037290417 | K18: 0.0011164547 | L18: 0.001328985 | M18: 0.00032532544
A19: Athletics, track and field | B19: 0.015369188 | D19: 0.020713359 | E19: 0.010416241 | G19: 0.049037756 | H19: 0.032176072 | I19: 0.023885593 | J19: 0.019221118 | K19: 0.0083744828 | L19: 0.003835504 | M19: 0.00030621696
A20: Australian football | B20: 0.04125113 | D20: 0.065943484 | E20: 0.017971883 | G20: 0.11656741 | H20: 0.096273006 | I20: 0.07195617 | J20: 0.041535806 | K20: 0.021387338 | L20: 0.0097754229 | M20: 0.00085626654
A21: Badminton | B21: 0.021625797 | D21: 0.027742243 | E21: 0.016010607 | G21: 0.078271171 | H21: 0.047857417 | I21: 0.038119184 | J21: 0.017346189 | K21: 0.0093196836 | L21: 0.0049516153 | M21: 0.0033680609
A22: Baseball | B22: 0.0036916534 | D22: 0.0053929255 | E22: 0.0020990037 | G22: 0.036316882 | H22: 0.007404152 | I22: 0.0037052891 | J22: 0.0021657573 | K22: 0.0016618556 | L22: 0 | M22: 0
A23: Basketball | B23: 0.058554651 | D23: 0.082939535 | E23: 0.035618778 | G23: 0.14387126 | H23: 0.14865536 | I23: 0.085014782 | J23: 0.061048149 | K23: 0.046058251 | L23: 0.0092146289 | M23: 0.0037462017
A24: Baton twirling | B24: 0.00039284043 | D24: 0.00053587539 | E24: 0.00026003108 | G24: 0 | H24: 0.00075662589 | I24: 0.0013347351 | J24: 0 | K24: 0 | L24: 0 | M24: 0.00029050925
A25: Biathlon | B25: 0 | D25: 0 | E25: 0 | G25: 0 | H25: 0 | I25: 0 | J25: 0 | K25: 0 | L25: 0 | M25: 0
A26: Billiards/Snooker/Pool | B26: 0.0027090734 | D26: 0.0041990344 | E26: 0.0013072961 | G26: 0 | H26: 0.0044675488 | I26: 0.0069313687 | J26: 0.00055371453 | K26: 0.0017599889 | L26: 0.0012386305 | M26: 0.0019282394
A27: BMX | B27: 0.00018129876 | D27: 0.00037167994 | E27: 0 | G27: 0 | H27: 0.0015409247 | I27: 0 | J27: 0 | K27: 0 | L27: 0 | M27: 0
... A157: Yoga | B157: 0.051003367 | D157: 0.013846421 | E157: 0.086874247 | G157: 0.039249231 | H157: 0.030789099 | I157: 0.07219745 | J157: 0.066244235 | K157: 0.065507629 | L157: 0.042898841 | M157: 0.027539458
B158: Estimated number of participants
A159: Adventure racing | B159: 8080.9666 | D159: 6191.1042 | E159: 1889.8624 | G159: 0 | H159: 2688.3197 | I159: 1934.8477 | J159: 2460.1842 | K159: 997.61501 | L159: 0 | M159: 0
A160: Air sports | B160: 22865.264 | D160: 17392.416 | E160: 5472.8475 | G160: 3380.5422 | H160: 6110.3474 | I160: 9621.8624 | J160: 1607.8087 | K160: 1252.9301 | L160: 891.7732 | M160: 0
A161: Archery | B161: 11872.496 | D161: 8315.8104 | E161: 3556.6855 | G161: 1415.9591 | H161: 2846.0906 | I161: 1524.0825 | J161: 3748.4774 | K161: 963.21471 | L161: 991.55061 | M161: 383.12101
A162: Athletics, track and field | B162: 88641.882 | D162: 58272.583 | E162: 30369.299 | G162: 11803.896 | H162: 21834.059 | I162: 25235.32 | J162: 19321.298 | K162: 7225.0359 | L162: 2861.6548 | M162: 360.61781
A163: Australian football | B163: 237916.13 | D163: 185517.82 | E163: 52398.314 | G163: 28058.984 | H163: 65328.998 | I163: 76022.268 | J163: 41752.29 | K163: 18451.8 | L163: 7293.4054 | M163: 1008.3862
A164: Badminton | B164: 124726.91 | D164: 78046.839 | E164: 46680.075 | G164: 18840.682 | H164: 32475.117 | I164: 40273.222 | J164: 17436.597 | K164: 8040.5023 | L164: 3694.3811 | M164: 3966.4125
A165: Baseball | B165: 21291.633 | D165: 15171.837 | E165: 6119.7959 | G165: 8741.8497 | H165: 5024.3142 | I165: 3914.6675 | J165: 2177.0452 | K165: 1433.7561 | L165: 0 | M165: 0
A166: Basketball | B166: 337714.29 | D166: 233332.56 | E166: 103849.1 | G166: 34631.303 | H166: 100874.65 | I166: 89818.796 | J166: 61366.331 | K166: 39736.486 | L166: 6874.9991 | M166: 4411.7317
A167: Baton twirling | B167: 2265.7095 | D167: 1507.5702 | E167: 758.13927 | G167: 0 | H167: 513.43168 | I167: 1410.1583 | J167: 0 | K167: 0 | L167: 0 | M167: 342.11956
A168: Biathlon | B168: 0 | D168: 0 | E168: 0 | G168: 0 | H168: 0 | I168: 0 | J168: 0 | K168: 0 | L168: 0 | M168: 0
A169: Billiards/Snooker/Pool | B169: 15624.596 | D169: 11813.081 | E169: 3811.5155 | G169: 0 | H169: 3031.5921 | I169: 7323.0463 | J169: 556.60047 | K169: 1518.4201 | L169: 924.13742 | M169: 2270.8
A170: BMX | B170: 1045.6416 | D170: 1045.6416 | E170: 0 | G170: 0 | H170: 1045.6416 | I170: 0 | J170: 0 | K170: 0 | L170: 0 | M170: 0
... A300: Yoga | B300: 294162.22 | D300: 38953.929 | E300: 253288.1 | G300: 9447.6965 | H300: 20892.887 | I300: 76277.182 | J300: 66589.499 | K300: 56516.323 | L300: 32006.66 | M300: 32431.97
A302: NB. Estimated participant numbers have not been rounded but users must remember that they are estimates and are subject to margins of error. Refer to sheet number 27 for margin of error and relative margin of error statistics.
A303: * Estimate has relative margin of error between 50% and 100% and should be used with caution
A304: ** Estimate has relative margin of error greater than 100% and is considered too unreliable to use
A305: # AusPlay collects data on gender, including non-binary and self-described. Non-binary and self-described gender are included in Total columns but not reported separately due to sample size. The sum of male and female estimates is not therefore equal to the total.

Sheet 17
A8: =Index!A8 -> AusPlay survey results July 2024 - June 2025
A9: Released at: | B9: 13 November 2025
A10: Table number: | B10: 17
A11: Table name: | B11: Participation by activity (children) (organised outside of school hours)
A12: Base: | B12: Child population
G13: Age group
B14: Total# | D14: Males | E14: Females | G14: 0-4 | H14: 5-8 | I14: 9-11 | J14: 12-14
B15: Participation rate
A16: Adventure racing | B16: 0.0022954124 | D16: 0.0019965239 | E16: 0.002647148 | G16: 0.0051715139 | H16: 0.0015979064 | I16: 0 | J16: 0.0011760481
A17: Air sports | B17: 0.0023386153 | D17: 0.0027288418 | E17: 0.0019034844 | G17: 0.0027726614 | H17: 0.0019775373 | I17: 0 | J17: 0.004412431
A18: Archery | B18: 0.0014523067 | D18: 0.0018100198 | E18: 0.0010503082 | G18: 0.0015728685 | H18: 0 | I18: 0.002177455 | J18: 0.0024571868
A19: Athletics, track and field | B19: 0.028408375 | D19: 0.024473224 | E19: 0.033031122 | G19: 0.0072636977 | H19: 0.032243012 | I19: 0.047584064 | J19: 0.036102592
A20: Australian football | B20: 0.10873556 | D20: 0.15208433 | E20: 0.05866616 | G20: 0.033079224 | H20: 0.14842558 | I20: 0.14911694 | J20: 0.12977882
A21: Badminton | B21: 0.012352338 | D21: 0.01293037 | E21: 0.011747924 | G21: 0.012179916 | H21: 0.0030247146 | I21: 0.017675057 | J21: 0.019558261
A22: Baseball | B22: 0.0064455948 | D22: 0.0079295729 | E22: 0.0047797984 | G22: 0.0018981593 | H22: 0.011286913 | I22: 0 | J22: 0.013050531
A23: Basketball | B23: 0.10393312 | D23: 0.13244787 | E23: 0.071834768 | G23: 0.0084808624 | H23: 0.11282845 | I23: 0.15008815 | J23: 0.18832909
A24: Baton twirling | B24: 0.00083523544 | D24: 0.0015698316 | E24: 0 | G24: 0.0013863307 | H24: 0 | I24: 0.0019874606 | J24: 0
A25: Biathlon | B25: 0.00054157371 | D25: 0 | E25: 0.0011625687 | G25: 0 | H25: 0.0019775373 | I25: 0 | J25: 0
A26: Billiards/Snooker/Pool | B26: 0.00092084948 | D26: 0.00081053971 | E26: 0.001050996 | G26: 0.0029602292 | H26: 0 | I26: 0 | J26: 0
A27: BMX | B27: 0.00027080678 | D27: 0.00050898346 | E27: 0 | G27: 0 | H27: 0 | I27: 0 | J27: 0.001278615
... A157: Yoga | B157: 0.0027857025 | D157: 0.0026441594 | E157: 0.0029599425 | G157: 0.00328449 | H157: 0.0034469923 | I157: 0.0020450477 | J157: 0.0019088633
B158: Estimated number of participants
A159: Adventure racing | B159: 2808.8087 | D159: 1299.8457 | E159: 1508.963 | G159: 1968.5318 | H159: 535.48298 | I159: 0 | J159: 304.79389
A160: Air sports | B160: 2861.6744 | D160: 1776.6245 | E160: 1085.0499 | G160: 1055.4109 | H160: 662.70311 | I160: 0 | J160: 1143.5603
A161: Archery | B161: 1777.1323 | D161: 1178.4214 | E161: 598.71087 | G161: 598.71087 | H161: 0 | I161: 541.59755 | J161: 636.82387
A162: Athletics, track and field | B162: 34762.246 | D162: 15933.4 | E162: 18828.846 | G162: 2764.9196 | H162: 10805.128 | I162: 11835.566 | J162: 9356.6318
A163: Australian football | B163: 133055.57 | D163: 99015.179 | E163: 33441.676 | G163: 12591.575 | H163: 49739.692 | I163: 37089.799 | J163: 33634.499
A164: Badminton | B164: 15115.085 | D164: 8418.3745 | E164: 6696.7103 | G164: 4636.2734 | H164: 1013.6283 | I164: 4396.3103 | J164: 5068.8728
A165: Baseball | B165: 7887.2287 | D165: 5162.5835 | E165: 2724.6452 | G165: 722.53252 | H165: 3782.4179 | I165: 0 | J165: 3382.2783
A166: Basketball | B166: 127179 | D166: 86230.773 | E166: 40948.224 | G166: 3228.2321 | H166: 37810.546 | I166: 37331.37 | J166: 48808.849
A167: Baton twirling | B167: 1022.0458 | D167: 1022.0458 | E167: 0 | G167: 527.70546 | H167: 0 | I167: 494.34032 | J167: 0
A168: Biathlon | B168: 662.70311 | D168: 0 | E168: 662.70311 | G168: 0 | H168: 662.70311 | I168: 0 | J168: 0
A169: Billiards/Snooker/Pool | B169: 1126.8084 | D169: 527.70546 | E169: 599.10295 | G169: 1126.8084 | H169: 0 | I169: 0 | J169: 0
A170: BMX | B170: 331.37593 | D170: 331.37593 | E170: 0 | G170: 0 | H170: 0 | I170: 0 | J170: 331.37593
... A300: Yoga | B300: 3408.758 | D300: 1721.4916 | E300: 1687.2664 | G300: 1250.238 | H300: 1155.14 | I300: 508.66395 | J300: 494.71603
A302: NB. Please note that for children 0-14 years, data was collected via the child's parent/guardian for organised participation outside of school hours
A303: NB. Estimated participant numbers have not been rounded but users must remember that they are estimates and are subject to margins of error. Refer to sheet number 27 for margin of error and relative margin of error statistics.
A304: * Estimate has relative margin of error between 50% and 100% and should be used with caution
A305: ** Estimate has relative margin of error greater than 100% and is considered too unreliable to use
A306: # AusPlay collects data on gender, including non-binary and self-described. Non-binary and self-described gender are included in Total columns but not reported separately due to sample size. The sum of male and female estimates is not therefore equal to the total.

Sheet 18
A8: =Index!A8 -> AusPlay survey results July 2024 - June 2025
A9: Released at: | B9: 13 November 2025
A10: Table number: | B10: 18
A11: Table name: | B11: Organised participation by activity (adults)
A12: Base: | B12: Adult population
B13: Total organised# | G13: Age group
D14: Males | E14: Females | G14: 15-17 | H14: 18-24 | I14: 25-34 | J14: 35-44 | K14: 45-54 | L14: 55-64 | M14: 65+
B15: Participation rate
A16: Adventure racing | B16: 0.00068062501 | D16: 0.0010545695 | E16: 0.00032882203 | G16: 0 | H16: 0.00074083241 | I16: 0.00047952341 | J16: 0.0024474283 | K16: 0.00052853409 | L16: 0 | M16: 0
A17: Air sports | B17: 0.0027081739 | D17: 0.0039521983 | E17: 0.0015436932 | G17: 0.0068869152 | H17: 0.0051209921 | I17: 0.0075598758 | J17: 0.0015994723 | K17: 0 | L17: 0.0011952524 | M17: 0
A18: Archery | B18: 0.0012208503 | D18: 0.0017604941 | E18: 0.0007163224 | G18: 0 | H18: 0.0028944463 | I18: 0.00049255935 | J18: 0.0026609873 | K18: 0.00058792056 | L18: 0.001328985 | M18: 0.00032532544
A19: Athletics, track and field | B19: 0.0087655332 | D19: 0.012117809 | E19: 0.0056470611 | G19: 0.028022597 | H19: 0.022374957 | I19: 0.014500301 | J19: 0.0098467961 | K19: 0.0018625773 | L19: 0.0019318889 | M19: 0.00030621696
A20: Australian football | B20: 0.028780636 | D20: 0.046992174 | E20: 0.011589529 | G20: 0.090805699 | H20: 0.05948218 | I20: 0.053805965 | J20: 0.029163902 | K20: 0.014274424 | L20: 0.0065829483 | M20: 0.00032448722
A21: Badminton | B21: 0.010348621 | D21: 0.015114413 | E21: 0.0058872091 | G21: 0.064268763 | H21: 0.018840714 | I21: 0.015516304 | J21: 0.0048008382 | K21: 0.0048162484 | L21: 0.0036838545 | M21: 0.0028089503
A22: Baseball | B22: 0.0026234773 | D22: 0.0039338223 | E22: 0.0013938801 | G22: 0.029310866 | H22: 0.0037263815 | I22: 0.0028799058 | J22: 0.0010648918 | K22: 0.0016618556 | L22: 0 | M22: 0
A23: Basketball | B23: 0.033366301 | D23: 0.045851776 | E23: 0.021761158 | G23: 0.11471965 | H23: 0.078280788 | I23: 0.047145365 | J23: 0.033896271 | K23: 0.02610058 | L23: 0.0032364765 | M23: 0.0024549351
A24: Baton twirling | B24: 0.00030665599 | D24: 0.00035918897 | E24: 0.00026003108 | G24: 0 | H24: 0.00075662589 | I24: 0.00086425186 | J24: 0 | K24: 0 | L24: 0 | M24: 0.00029050925
A25: Biathlon | B25: 0 | D25: 0 | E25: 0 | G25: 0 | H25: 0 | I25: 0 | J25: 0 | K25: 0 | L25: 0 | M25: 0
A26: Billiards/Snooker/Pool | B26: 0.00095213573 | D26: 0.0017718744 | E26: 0.00017377747 | G26: 0 | H26: 0.00078429877 | I26: 0.0039830753 | J26: 0 | K26: 0 | L26: 0 | M26: 0.00063778256
A27: BMX | B27: 0 | D27: 0 | E27: 0 | G27: 0 | H27: 0 | I27: 0 | J27: 0 | K27: 0 | L27: 0 | M27: 0
... A157: Yoga | B157: 0.028625266 | D157: 0.0063363184 | E157: 0.050511711 | G157: 0.015070932 | H157: 0.014038662 | I157: 0.043584686 | J157: 0.03713936 | K157: 0.032689231 | L157: 0.02354952 | M157: 0.019351301
B158: Estimated number of participants
A159: Adventure racing | B159: 3925.5087 | D159: 2966.8045 | E159: 958.70422 | G159: 0 | H159: 502.71453 | I159: 506.62031 | J159: 2460.1842 | K159: 455.98969 | L159: 0 | M159: 0
A160: Air sports | B160: 15619.409 | D160: 11118.661 | E160: 4500.7484 | G160: 1657.7518 | H160: 3475.0061 | I160: 7987.0692 | J160: 1607.8087 | K160: 0 | L160: 891.7732 | M160: 0
A161: Archery | B161: 7041.2611 | D161: 4952.7717 | E161: 2088.4894 | G161: 0 | H161: 1964.1152 | I161: 520.39289 | J161: 2674.8563 | K161: 507.22502 | L161: 991.55061 | M161: 383.12101
A162: Athletics, track and field | B162: 50555.264 | D162: 34090.852 | E162: 16464.412 | G162: 6745.3294 | H162: 15183.213 | I162: 15319.684 | J162: 9898.1174 | K162: 1606.9276 | L162: 1441.3748 | M162: 360.61781
A163: Australian football | B163: 165992.49 | D163: 132202.38 | E163: 33790.104 | G163: 21857.872 | H163: 40363.456 | I163: 56846.432 | J163: 29315.904 | K163: 12315.176 | L163: 4911.5124 | M163: 382.13387
A164: Badminton | B164: 59685.733 | D164: 42521.153 | E164: 17164.581 | G164: 15470.157 | H164: 12784.944 | I164: 16393.1 | J164: 4825.8601 | K164: 4155.19 | L164: 2748.5097 | M164: 3307.9733
A165: Baseball | B165: 15130.921 | D165: 11066.964 | E165: 4063.9574 | G165: 7055.429 | H165: 2528.6503 | I165: 3042.6435 | J165: 1070.442 | K165: 1433.7561 | L165: 0 | M165: 0
A166: Basketball | B166: 192440.34 | D166: 128994.12 | E166: 63446.219 | G166: 27614.207 | H166: 53119.827 | I166: 49809.454 | J166: 34072.937 | K166: 22518.122 | L166: 2414.7227 | M166: 2891.0656
A167: Baton twirling | B167: 1768.6402 | D167: 1010.501 | E167: 758.13927 | G167: 0 | H167: 513.43168 | I167: 913.08899 | J167: 0 | K167: 0 | L167: 0 | M167: 342.11956
A168: Biathlon | B168: 0 | D168: 0 | E168: 0 | G168: 0 | H168: 0 | I168: 0 | J168: 0 | K168: 0 | L168: 0 | M168: 0
A169: Billiards/Snooker/Pool | B169: 5491.4484 | D169: 4984.7877 | E169: 506.66068 | G169: 0 | H169: 532.20996 | I169: 4208.1509 | J169: 0 | K169: 0 | L169: 0 | M169: 751.08758
A170: BMX | B170: 0 | D170: 0 | E170: 0 | G170: 0 | H170: 0 | I170: 0 | J170: 0 | K170: 0 | L170: 0 | M170: 0
... A300: Yoga | B300: 165096.39 | D300: 17825.87 | E300: 147270.52 | G300: 3627.7295 | H300: 9526.3639 | I300: 46047.569 | J300: 37332.929 | K300: 28202.442 | L300: 17570.206 | M300: 22789.149
A302: NB. Estimated participant numbers have not been rounded but users must remember that they are estimates and are subject to margins of error. Refer to sheet number 27 for margin of error and relative margin of error statistics.
A303: * Estimate has relative margin of error between 50% and 100% and should be used with caution
A304: ** Estimate has relative margin of error greater than 100% and is considered too unreliable to use
A305: # AusPlay collects data on gender, including non-binary and self-described. Non-binary and self-described gender are included in Total columns but not reported separately due to sample size. The sum of male and female estimates is not therefore equal to the total.

Sheet 19
A8: =Index!A8 -> AusPlay survey results July 2024 - June 2025
A9: Released at: | B9: 13 November 2025
A10: Table number: | B10: 19
A11: Table name: | B11: Type of organising entity by activity (adults)
A12: Base: | B12: Adult population
C13: Type of entity organising the activity
B14: Total organised | C14: Sports club or association | D14: Recreation club or association | E14: Gym/fitness club/sports/ leisure centre | F14: Private or commercial business | G14: Individual personal trainer or coach | H14: Educational institution
B15: Participation rate
A16: Adventure racing | B16: 0.00068062501 | C16: 0.0001669023 | D16: 0.00021949991 | E16: 0 | F16: 0.00011198646 | G16: 0.0001888118 | H16: 7.9061851e-05
A17: Air sports | B17: 0.0027081739 | C17: 0.00039662205 | D17: 0.00053034868 | E17: 0.00052510513 | F17: 0.00090506186 | G17: 0.00062973151 | H17: 0.00040854914
A18: Archery | B18: 0.0012208503 | C18: 0.00059471541 | D18: 0.00036855342 | E18: 0 | F18: 0.00019710388 | G18: 0.00017020862 | H18: 0.00018566195
A19: Athletics, track and field | B19: 0.0087655332 | C19: 0.002519422 | D19: 0.0018900503 | E19: 0.0019450905 | F19: 0.0016530026 | G19: 0.0018487855 | H19: 0.0021472142
A20: Australian football | B20: 0.028780636 | C20: 0.017005302 | D20: 0.0043016889 | E20: 0.0027680191 | F20: 0.0014224901 | G20: 0.0016747049 | H20: 0.0028487955
A21: Badminton | B21: 0.010348621 | C21: 0.0025714628 | D21: 0.0013810498 | E21: 0.00068478523 | F21: 0.00088123432 | G21: 0.00085781951 | H21: 0.0031261965
A22: Baseball | B22: 0.0026234773 | C22: 0.0011058984 | D22: 0.00023927002 | E22: 0.00061683534 | F22: 0.00023927002 | G22: 7.213165e-05 | H22: 0.00068631189
A23: Basketball | B23: 0.033366301 | C23: 0.01541028 | D23: 0.0054296723 | E23: 0.0046116128 | F23: 0.0019333682 | G23: 0.0019752227 | H23: 0.0057200847
A24: Baton twirling | B24: 0.00030665599 | C24: 7.213165e-05 | D24: 7.213165e-05 | E24: 7.213165e-05 | F24: 0.00016115309 | G24: 0.00016115309 | H24: 7.213165e-05
A25: Biathlon | B25: 0 | C25: 0 | D25: 0 | E25: 0 | F25: 0 | G25: 0 | H25: 0
A26: Billiards/Snooker/Pool | B26: 0.00095213573 | C26: 0.00037764333 | D26: 0.00026479111 | E26: 0.00041734872 | F26: 0 | G26: 0.00017373842 | H26: 0
A27: BMX | B27: 0 | C27: 0 | D27: 0 | E27: 0 | F27: 0 | G27: 0 | H27: 0
... A157: Yoga | B157: 0.028625266 | C157: 0.00087063957 | D157: 0.0010563395 | E157: 0.0071034413 | F157: 0.01685001 | G157: 0.0016386346 | H157: 0.0011597034
B158: Estimated number of participants
A159: Adventure racing | B159: 3925.5087 | C159: 962.61 | D159: 1265.967 | E159: 0 | F159: 645.88258 | G159: 1088.9732 | H159: 455.98969
A160: Air sports | B160: 15619.409 | C160: 2287.52 | D160: 3058.7891 | E160: 3028.5469 | F160: 5219.9496 | G160: 3631.9802 | H160: 2356.3096
A161: Archery | B161: 7041.2611 | C161: 3430.0246 | D161: 2125.634 | E161: 0 | F161: 1136.7978 | G161: 981.67919 | H161: 1070.8064
A162: Athletics, track and field | B162: 50555.264 | C162: 14530.781 | D162: 10900.876 | E162: 11218.321 | F162: 9533.7024 | G162: 10662.881 | H162: 12384.07
A163: Australian football | B163: 165992.49 | C163: 98078.177 | D163: 24810.016 | E163: 15964.566 | F163: 8204.2202 | G163: 9658.8702 | H163: 16430.445
A164: Badminton | B164: 59685.733 | C164: 14830.927 | D164: 7965.2126 | E164: 3949.5028 | F164: 5082.5241 | G164: 4947.479 | H164: 18030.357
A165: Baseball | B165: 15130.921 | C165: 6378.2757 | D165: 1379.9912 | E165: 3557.6014 | F165: 1379.9912 | G165: 416.01971 | H165: 3958.3079
A166: Basketball | B166: 192440.34 | C166: 88878.881 | D166: 31315.667 | E166: 26597.504 | F166: 11150.713 | G166: 11392.109 | H166: 32990.622
A167: Baton twirling | B167: 1768.6402 | C167: 416.01971 | D167: 416.01971 | E167: 416.01971 | F167: 929.45139 | G167: 929.45139 | H167: 416.01971
A168: Biathlon | B168: 0 | C168: 0 | D168: 0 | E168: 0 | F168: 0 | G168: 0 | H168: 0
A169: Billiards/Snooker/Pool | B169: 5491.4484 | C169: 2178.0601 | D169: 1527.1843 | E169: 2407.0612 | F169: 0 | G169: 1002.0374 | H169: 0
A170: BMX | B170: 0 | C170: 0 | D170: 0 | E170: 0 | F170: 0 | G170: 0 | H170: 0
... A300: Yoga | B300: 165096.39 | C300: 5021.4188 | D300: 6092.4443 | E300: 40969.139 | F300: 97182.529 | G300: 9450.8344 | H300: 6688.5962
A302: NB. Estimated participant numbers have not been rounded but users must remember that they are estimates and are subject to margins of error. Refer to sheet number 27 for margin of error and relative margin of error statistics.
A303: * Estimate has relative margin of error between 50% and 100% and should be used with caution
A304: ** Estimate has relative margin of error greater than 100% and is considered too unreliable to use

Sheet 20
A8: =Index!A8 -> AusPlay survey results July 2024 - June 2025
A9: Released at: | B9: 13 November 2025
A10: Table number: | B10: 20
A11: Table name: | B11: Type of organising entity by activity (children)
A12: Base: | B12: Child population
C13: Type of entity organising the activity
B14: Total | C14: Sports club or association | D14: Recreation club or association | E14: Gym/fitness club/sports/ leisure centre | F14: Private or commercial business | G14: Individual personal trainer or coach | H14: Educational institution
B15: Participation rate
A16: Adventure racing | B16: 0.0022954124 | C16: 0.00064268609 | D16: 0.00081317545 | E16: 0 | F16: 0.0006866904 | G16: 0 | H16: 0
A17: Air sports | B17: 0.0023386153 | C17: 0.0011571969 | D17: 0.00072594583 | E17: 0.00077640093 | F17: 0.00029469479 | G17: 0.00083626851 | H17: 0.0011571969
A18: Archery | B18: 0.0014523067 | C18: 0 | D18: 0.00044260392 | E18: 0.0014523067 | F18: 0 | G18: 0.0011814999 | H18: 0
A19: Athletics, track and field | B19: 0.028408375 | C19: 0.013390267 | D19: 0.0043675727 | E19: 0.0032907651 | F19: 0.0019829303 | G19: 0.0052620348 | H19: 0.0086110215
A20: Australian football | B20: 0.10873556 | C20: 0.071713622 | D20: 0.016850488 | E20: 0.0046086087 | F20: 0.0029592068 | G20: 0.0062191265 | H20: 0.014563949
A21: Badminton | B21: 0.012352338 | C21: 0.0017086872 | D21: 0.002723758 | E21: 0.002195763 | F21: 0.00067849428 | G21: 0.0031554066 | H21: 0.0028939573
A22: Baseball | B22: 0.0064455948 | C22: 0.0020177526 | D22: 0.0022653104 | E22: 0 | F22: 0.00054157371 | G22: 0.0013538432 | H22: 0.00030470867
A23: Basketball | B23: 0.10393312 | C23: 0.069573887 | D23: 0.015591134 | E23: 0.008295679 | F23: 0.002979934 | G23: 0.0082340856 | H23: 0.017085762
A24: Baton twirling | B24: 0.00083523544 | C24: 0.00043125104 | D24: 0 | E24: 0.00043125104 | F24: 0.0004039844 | G24: 0.00043125104 | H24: 0.00083523544
A25: Biathlon | B25: 0.00054157371 | C25: 0 | D25: 0 | E25: 0 | F25: 0.00054157371 | G25: 0 | H25: 0
A26: Billiards/Snooker/Pool | B26: 0.00092084948 | C26: 0.00048959844 | D26: 0 | E26: 0 | F26: 0.00048959844 | G26: 0.00048959844 | H26: 0
A27: BMX | B27: 0.00027080678 | C27: 0 | D27: 0 | E27: 0 | F27: 0 | G27: 0 | H27: 0.00027080678
... A157: Yoga | B157: 0.0027857025 | C157: 0.0010061574 | D157: 0.00055989505 | E157: 0.0010061574 | F157: 0.00040429145 | G157: 0 | H157: 0.00043125104
B158: Estimated number of participants
A159: Adventure racing | B159: 2808.8087 | C159: 786.43048 | D159: 995.0518 | E159: 0 | F159: 840.27687 | G159: 0 | H159: 0
A160: Air sports | B160: 2861.6744 | C160: 1416.0177 | D160: 888.31225 | E160: 950.05222 | F160: 360.60679 | G160: 1023.3099 | H160: 1416.0177
A161: Archery | B161: 1777.1323 | C161: 0 | D161: 541.59755 | E161: 1777.1323 | F161: 0 | G161: 1445.7564 | H161: 0
A162: Athletics, track and field | B162: 34762.246 | C162: 16385.159 | D162: 5344.4322 | E162: 4026.7838 | F162: 2426.4362 | G162: 6438.9515 | H162: 10536.979
A163: Australian football | B163: 133055.57 | C163: 87753.227 | D163: 20619.3 | E163: 5639.3788 | F163: 3621.0686 | G163: 7610.108 | H163: 17821.349
A164: Badminton | B164: 15115.085 | C164: 2090.8554 | D164: 3332.9588 | E164: 2686.8715 | F164: 830.24759 | G164: 3861.1508 | H164: 3541.2253
A165: Baseball | B165: 7887.2287 | C165: 2469.047 | D165: 2771.974 | E165: 0 | F165: 662.70311 | G165: 1656.6464 | H165: 372.86038
A166: Basketball | B166: 127179 | C166: 85134.914 | D166: 19078.276 | E166: 10151.106 | F166: 3646.4317 | G166: 10075.737 | H166: 20907.195
A167: Baton twirling | B167: 1022.0458 | C167: 527.70546 | D167: 0 | E167: 527.70546 | F167: 494.34032 | G167: 527.70546 | H167: 1022.0458
A168: Biathlon | B168: 662.70311 | C168: 0 | D168: 0 | E168: 0 | F168: 662.70311 | G168: 0 | H168: 0
A169: Billiards/Snooker/Pool | B169: 1126.8084 | C169: 599.10295 | D169: 0 | E169: 0 | F169: 599.10295 | G169: 599.10295 | H169: 0
A170: BMX | B170: 331.37593 | C170: 0 | D170: 0 | E170: 0 | F170: 0 | G170: 0 | H170: 331.37593
... A300: Yoga | B300: 3408.758 | C300: 1231.1965 | D300: 685.12223 | E300: 1231.1965 | F300: 494.71603 | G300: 0 | H300: 527.70546
A302: NB. Please note that for children 0-14 years, data was collected via the child's parent/guardian for organised participation outside of school hours
A303: NB. Estimated participant numbers have not been rounded but users must remember that they are estimates and are subject to margins of error. Refer to sheet number 27 for margin of error and relative margin of error statistics.
A304: * Estimate has relative margin of error between 50% and 100% and should be used with caution
A305: ** Estimate has relative margin of error greater than 100% and is considered too unreliable to use

Sheet 21
A8: =Index!A8 -> AusPlay survey results July 2024 - June 2025
A9: Released at: | C9: 13 November 2025
A10: Table number: | C10: 21
A11: Table name: | C11: Non-playing roles (adults)
A12: Base: | C12: Adult population
E13: Type of non-playing role
C14: Any non-playing role | E14: Coach, instructor, trainer or teacher | F14: Official | G14: General/ miscellaneous ad hoc assistance | H14: Administrator or committee member | I14: Team manager or coordinator | J14: Driving team members to training or matches | K14: Fundraising | L14: Medical support or health and safety | M14: Financial support/ helping pay for others | N14: Other
C15: Participation rate
A16: All# | B16: Total | C16: 0.15368309 | E16: 0.046571638 | F16: 0.049071279 | G16: 0.039590045 | H16: 0.032579253 | I16: 0.030291905 | J16: 0.028783855 | K16: 0.022793453 | L16: 0.01419246 | M16: 0.013249151 | N16: 0.0019149198
A17: Age group | B17: 15-17 | C17: 0.085677605 | E17: 0.030945835 | F17: 0.019332107 | G17: 0.0058755751 | H17: 0 | I17: 0.0086169836 | J17: 0.0070060161 | K17: 0.0068869152 | L17: 0.0053037614 | M17: 0.007014173 | N17: 0
B18: 18-24 | C18: 0.24391958 | E18: 0.088752222 | F18: 0.073892431 | G18: 0.038511394 | H18: 0.030309589 | I18: 0.045674973 | J18: 0.036754286 | K18: 0.040956057 | L18: 0.030904307 | M18: 0.015612405 | N18: 0.0022783798
B19: 25-34 | C19: 0.18335902 | E19: 0.062419477 | F19: 0.042120864 | G19: 0.043054614 | H19: 0.034806067 | I19: 0.03816192 | J19: 0.030633555 | K19: 0.032427264 | L19: 0.025436649 | M19: 0.021037275 | N19: 0.0021562188
B20: 35-44 | C20: 0.15647722 | E20: 0.055765965 | F20: 0.049552573 | G20: 0.043483477 | H20: 0.02882244 | I20: 0.035278619 | J20: 0.03089765 | K20: 0.023879323 | L20: 0.014387932 | M20: 0.012801593 | N20: 0.00049129054
B21: 45-54 | C21: 0.18818546 | E21: 0.04655447 | F21: 0.073901998 | G21: 0.058069268 | H21: 0.033635372 | I21: 0.045914191 | J21: 0.051435688 | K21: 0.025384325 | L21: 0.013360855 | M21: 0.017897961 | N21: 0.0029080588
B22: 55-64 | C22: 0.1076362 | E22: 0.023930898 | F22: 0.038728974 | G22: 0.039097967 | H22: 0.029212831 | I22: 0.016186469 | J22: 0.020485138 | K22: 0.013916904 | L22: 0.0057012578 | M22: 0.009822436 | N22: 0.002623882
B23: 65+ | C23: 0.09047614 | E23: 0.017751412 | F23: 0.035033664 | G23: 0.027445229 | H23: 0.04311424 | I23: 0.012032956 | J23: 0.013841819 | K23: 0.0097351684 | L23: 0.0021141464 | M23: 0.0053221802 | N23: 0.0019188598
A25: Males | B25: Total | C25: 0.1887885 | E25: 0.062240653 | F25: 0.060996734 | G25: 0.046165852 | H25: 0.040995468 | I25: 0.033882621 | J25: 0.030945552 | K25: 0.028258617 | L25: 0.016633306 | M25: 0.016452061 | N25: 0.0020572161
A26: Age group | B26: 15-17 | C26: 0.14988233 | E26: 0.054448456 | F26: 0.047031301 | G26: 0.014294145 | H26: 0 | I26: 0 | J26: 0.01704429 | K26: 0 | L26: 0.012903032 | M26: 0.017064135 | N26: 0
B27: 18-24 | C27: 0.27554703 | E27: 0.09594862 | F27: 0.078263086 | G27: 0.04582113 | H27: 0.037918695 | I27: 0.056339415 | J27: 0.042064418 | K27: 0.046736407 | L27: 0.039285651 | M27: 0.023673718 | N27: 0.0014891128
B28: 25-34 | C28: 0.22737591 | E28: 0.079372129 | F28: 0.043184411 | G28: 0.049867105 | H28: 0.034536131 | I28: 0.045948398 | J28: 0.037272325 | K28: 0.042132059 | L28: 0.028405408 | M28: 0.028799721 | N28: 0.0023713741
B29: 35-44 | C29: 0.17371919 | E29: 0.069336231 | F29: 0.056029439 | G29: 0.046313027 | H29: 0.032006128 | I29: 0.039648288 | J29: 0.028258926 | K29: 0.030141496 | L29: 0.014069598 | M29: 0.013797407 | N29: 0
B30: 45-54 | C30: 0.20358455 | E30: 0.068381589 | F30: 0.084954086 | G30: 0.055958595 | H30: 0.037137317 | I30: 0.03267539 | J30: 0.042273618 | K30: 0.02760582 | L30: 0.01376434 | M30: 0.016016185 | N30: 0.0037526083
B31: 55-64 | C31: 0.13184624 | E31: 0.038030206 | F31: 0.056065797 | G31: 0.048801109 | H31: 0.037245343 | I31: 0.02013908 | J31: 0.024195798 | K31: 0.015639157 | L31: 0.0063796184 | M31: 0.010242658 | N31: 0.002568601
B32: 65+ | C32: 0.14291155 | E32: 0.030088166 | F32: 0.057756774 | G32: 0.039131116 | H32: 0.07059892 | I32: 0.018652166 | J32: 0.018327691 | K32: 0.015418925 | L32: 0.0027410662 | M32: 0.0070255833 | N32: 0.0027646859
A34: Females | B34: Total | C34: 0.12065862 | E34: 0.031507463 | F34: 0.037903685 | G34: 0.033769745 | H34: 0.024890177 | I34: 0.027058938 | J34: 0.026764894 | K34: 0.017822175 | L34: 0.012025383 | M34: 0.01033424 | N34: 0.0016276495
A35: Age group | B35: 15-17 | C35: 0.041864356 | E35: 0.014897489 | F35: 0 | G35: 0 | H35: 0 | I35: 0.01498804 | J35: 0 | K35: 0.011978828 | L35: 0 | M35: 0 | N35: 0
B36: 18-24 | C36: 0.20742296 | E36: 0.081289498 | F36: 0.067996082 | G36: 0.030961638 | H36: 0.02214355 | I36: 0.032703841 | J36: 0.029893617 | K36: 0.0353157 | L36: 0.021831587 | M36: 0.0064429702 | N36: 0.0032956882
B37: 25-34 | C37: 0.14410834 | E37: 0.047487067 | F37: 0.04169278 | G37: 0.037293261 | H37: 0.035520533 | I37: 0.031429749 | J37: 0.024105595 | K37: 0.02383497 | L37: 0.023014828 | M37: 0.014099424 | N37: 0.0019848662
B38: 35-44 | C38: 0.13934814 | E38: 0.041204594 | F38: 0.043490127 | G38: 0.04109628 | H38: 0.025895892 | I38: 0.031210653 | J38: 0.033978883 | K38: 0.017730254 | L38: 0.014887224 | M38: 0.011931521 | N38: 0.0010020063
B39: 45-54 | C39: 0.17520311 | E39: 0.02562393 | F39: 0.063881955 | G39: 0.060811913 | H39: 0.03057781 | I39: 0.059460863 | J39: 0.061036633 | K39: 0.023491215 | L39: 0.013117517 | M39: 0.019954109 | N39: 0.0021109119
B40: 55-64 | C40: 0.082774562 | E40: 0.0086758451 | F40: 0.021704374 | G40: 0.029661374 | H40: 0.02138436 | I40: 0.012343806 | J40: 0.016905569 | K40: 0.012278728 | L40: 0.005057171 | M40: 0.0094565935 | N40: 0.00132285
B41: 65+ | C41: 0.046262809 | E41: 0.0073174698 | F41: 0.015836267 | G41: 0.017656903 | H41: 0.019900694 | I41: 0.0064571388 | J41: 0.010113957 | K41: 0.0049420028 | L41: 0.00159477 | M41: 0.0039072048 | N41: 0.0012097742
C42: Estimated number of adults undertaking non-playing roles
A43: All# | B43: Total | C43: 886368.14 | E43: 268602.19 | F43: 283018.89 | G43: 228335.82 | H43: 187901.03 | I43: 174708.74 | J43: 166011.05 | K43: 131461.38 | L43: 81855.099 | M43: 76414.556 | N43: 11044.311
A44: Age group | B44: 15-17 | C44: 20623.487 | E44: 7448.9831 | F44: 4653.4385 | G44: 1414.3118 | H44: 0 | I44: 2074.1972 | J44: 1686.4206 | K44: 1657.7518 | L44: 1276.6703 | M44: 1688.3841 | N44: 0
B45: 18-24 | C45: 165519.1 | E45: 60225.539 | F45: 50141.973 | G45: 26133.086 | H45: 20567.5 | I45: 30994.152 | J45: 24940.747 | K45: 27791.987 | L45: 20971.065 | M45: 10594.276 | N45: 1546.0644
B46: 25-34 | C46: 193720.27 | E46: 65946.676 | F46: 44501.03 | G46: 45487.544 | H46: 36772.888 | I46: 40318.374 | J46: 32364.595 | K46: 34259.664 | L46: 26874.023 | M46: 22226.049 | N46: 2278.0624
B47: 35-44 | C47: 157292.78 | E47: 56056.616 | F47: 49810.84 | G47: 43710.112 | H47: 28972.662 | I47: 35462.491 | J47: 31058.688 | K47: 24003.781 | L47: 14462.921 | M47: 12868.315 | N47: 493.85114
B48: 45-54 | C48: 162355.9 | E48: 40164.596 | F48: 63758.515 | G48: 50098.921 | H48: 29018.72 | I48: 39612.199 | J48: 44375.838 | K48: 21900.177 | L48: 11526.999 | M48: 15441.361 | N48: 2508.9107
B49: 55-64 | C49: 80306.954 | E49: 17854.75 | F49: 28895.538 | G49: 29170.842 | H49: 21795.581 | I49: 12076.662 | J49: 15283.883 | K49: 10383.348 | L49: 4253.6865 | M49: 7328.4816 | N49: 1957.6683
B50: 65+ | C50: 106549.64 | E50: 20905.033 | F50: 41257.556 | G50: 32321 | H50: 50773.683 | I50: 14170.666 | J50: 16300.882 | K50: 11464.666 | L50: 2489.7343 | M50: 6267.6901 | N50: 2259.7541
A52: Males | B52: Total | C52: 531115.86 | E52: 175100.7 | F52: 171601.2 | G52: 129877.7 | H52: 115331.94 | I52: 95321.471 | J52: 87058.661 | K52: 79499.546 | L52: 46794.23 | M52: 46284.337 | N52: 5787.5354
A53: Age group | B53: 15-17 | C53: 14829.872 | E53: 5387.3173 | F53: 4653.4385 | G53: 1414.3118 | H53: 0 | I53: 0 | J53: 1686.4206 | K53: 0 | L53: 1276.6703 | M53: 1688.3841 | N53: 0
B54: 18-24 | C54: 100487.57 | E54: 34990.917 | F54: 28541.288 | G54: 16710.229 | H54: 13828.338 | I54: 20546.078 | J54: 15340.216 | K54: 17044.015 | L54: 14326.844 | M54: 8633.4238 | N54: 543.05546
B55: 25-34 | C55: 114953.52 | E55: 40127.848 | F55: 21832.569 | G55: 25211.112 | H55: 17460.293 | I55: 23229.946 | J55: 18843.619 | K55: 21300.536 | L55: 14360.808 | M55: 14560.159 | N55: 1198.8861
B56: 35-44 | C56: 87980.352 | E56: 35115.441 | F56: 28376.196 | G56: 23455.304 | H56: 16209.553 | I56: 20079.936 | J56: 14311.777 | K56: 15265.207 | L56: 7125.5694 | M56: 6987.7179 | N56: 0
B57: 45-54 | C57: 86585.217 | E57: 29082.928 | F57: 36131.269 | G57: 23799.385 | H57: 15794.63 | I57: 13896.957 | J57: 17979.117 | K57: 11740.851 | L57: 5854.0216 | M57: 6811.7393 | N57: 1595.9974
B58: 55-64 | C58: 48901.858 | E58: 14105.429 | F58: 20794.841 | G58: 18100.363 | H58: 13814.322 | I58: 7469.5981 | J58: 8974.2374 | K58: 5800.5735 | L58: 2366.2047 | M58: 3799.0087 | N58: 952.6958
B59: 65+ | C59: 77377.472 | E59: 16290.819 | F59: 31271.601 | G59: 21186.998 | H59: 38224.803 | I59: 10098.956 | J59: 9923.2734 | K59: 8348.3625 | L59: 1484.1121 | M59: 3803.9043 | N59: 1496.9007
A61: Females | B61: Total | C61: 351788.86 | E61: 91862.268 | F61: 110510.92 | G61: 98458.114 | H61: 72569.097 | I61: 78892.275 | J61: 78034.97 | K61: 51961.83 | L61: 35060.868 | M61: 30130.219 | N61: 4745.5288
A62: Age group | B62: 15-17 | C62: 5793.6148 | E62: 2061.6658 | F62: 0 | G62: 0 | H62: 0 | I62: 2074.1972 | J62: 0 | K62: 1657.7518 | L62: 0 | M62: 0 | N62: 0
B63: 18-24 | C63: 63127.053 | E63: 24739.627 | F63: 20693.912 | G63: 9422.8576 | H63: 6739.1627 | I63: 9953.0791 | J63: 9097.8164 | K63: 10747.972 | L63: 6644.2201 | M63: 1960.852 | N63: 1003.009
B64: 25-34 | C64: 78352.036 | E64: 25818.828 | F64: 22668.46 | G64: 20276.432 | H64: 19312.595 | I64: 17088.427 | J64: 13106.267 | K64: 12959.128 | L64: 12513.215 | M64: 7665.8893 | N64: 1079.1763
B65: 35-44 | C65: 68679.444 | E65: 20308.191 | F65: 21434.644 | G65: 20254.808 | H65: 12763.109 | I65: 15382.555 | J65: 16746.911 | K65: 8738.5738 | L65: 7337.3519 | M65: 5880.5969 | N65: 493.85114
B66: 45-54 | C66: 75770.687 | E66: 11081.668 | F66: 27627.247 | G66: 26299.535 | H66: 13224.09 | I66: 25715.242 | J66: 26396.721 | K66: 10159.326 | L66: 5672.9773 | M66: 8629.6215 | N66: 912.91328
B67: 55-64 | C67: 30893.85 | E67: 3238.0752 | F67: 8100.6974 | G67: 11070.479 | H67: 7981.2588 | I67: 4607.0639 | J67: 6309.6452 | K67: 4582.7749 | L67: 1887.4818 | M67: 3529.4729 | N67: 493.72569
B68: 65+ | C68: 29172.172 | E68: 4614.2138 | F68: 9985.9545 | G68: 11134.002 | H68: 12548.881 | I68: 4071.7105 | J68: 6377.6088 | K68: 3116.3036 | L68: 1005.6221 | M68: 2463.7858 | N68: 762.85341
A70: NB. Please note that non-playing roles were collected for adults (15 years and over) only
A71: NB. Estimated participant numbers have not been rounded but users must remember that they are estimates and are subject to margins of error. Refer to sheet number 27 for margin of error and relative margin of error statistics.
A72: * Estimate has relative margin of error between 50% and 100% and should be used with caution
A73: ** Estimate has relative margin of error greater than 100% and is considered too unreliable to use
A74: # AusPlay collects data on gender, including non-binary and self-described. Non-binary and self-described gender are included in Total columns but not reported separately due to sample size. The sum of male and female estimates is not therefore equal to the total.

Sheet 22
A8: =Index!A8 -> AusPlay survey results July 2024 - June 2025
A9: Released at: | C9: 13 November 2025
A10: Table number: | C10: 22
A11: Table name: | C11: Volunteers^ in non-playing roles (adults)
A12: Base: | C12: Adult population
E13: Type of non-playing role
C14: Any volunteer role | E14: Official | F14: Coach, instructor, trainer or teacher | G14: General/ miscellaneous ad hoc assistance | H14: Administrator or committee member | I14: Team manager or coordinator | J14: Driving team members to training or matches | K14: Fundraising | L14: Medical support or health and safety | M14: Financial support/ helping pay for others | N14: Other
C15: Participation rate
A16: All# | B16: Total | C16: 0.13688196 | E16: 0.044712805 | F16: 0.038564285 | G16: 0.037704162 | H16: 0.030711899 | I16: 0.027638727 | J16: 0.027363307 | K16: 0.021135699 | L16: 0.012159251 | M16: 0.012018696 | N16: 0.0017158061
A17: Age group | B17: 15-17 | C17: 0.068860014 | E17: 0.019332107 | F17: 0.014128243 | G17: 0.0058755751 | H17: 0 | I17: 0.0086169836 | J17: 0.0070060161 | K17: 0.0068869152 | L17: 0.0053037614 | M17: 0.007014173 | N17: 0
B18: 18-24 | C18: 0.19348416 | E18: 0.055787097 | F18: 0.066908461 | G18: 0.03616184 | H18: 0.028768664 | I18: 0.036549826 | J18: 0.032827165 | K18: 0.034334115 | L18: 0.024864553 | M18: 0.012037892 | N18: 0.0015639705
B19: 25-34 | C19: 0.15391814 | E19: 0.036542514 | F19: 0.0493453 | G19: 0.039058176 | H19: 0.028866575 | I19: 0.033002755 | J19: 0.026896116 | K19: 0.02863129 | L19: 0.020294247 | M19: 0.019092068 | N19: 0.0015281069
B20: 35-44 | C20: 0.14082057 | E20: 0.046285763 | F20: 0.04654758 | G20: 0.041427557 | H20: 0.026206713 | I20: 0.032475285 | J20: 0.029865141 | K20: 0.023879323 | L20: 0.014387932 | M20: 0.010695942 | N20: 0.00049129054
B21: 45-54 | C21: 0.1793844 | E21: 0.07212317 | F21: 0.043001519 | G21: 0.055804482 | H21: 0.033635372 | I21: 0.045335444 | J21: 0.050807894 | K21: 0.02415904 | L21: 0.011618941 | M21: 0.017319214 | N21: 0.0029080588
B22: 55-64 | C22: 0.10506237 | E22: 0.037464932 | F22: 0.023930898 | G22: 0.037704519 | H22: 0.028611262 | I22: 0.016186469 | J22: 0.020485138 | K22: 0.013916904 | L22: 0.0057012578 | M22: 0.009822436 | N22: 0.002623882
B23: 65+ | C23: 0.088547044 | E23: 0.034017732 | F23: 0.016760593 | G23: 0.027445229 | H23: 0.042799183 | I23: 0.011742447 | J23: 0.013841819 | K23: 0.0097351684 | L23: 0.0015263073 | M23: 0.0053221802 | N23: 0.0019188598
A25: Males^^ | B25: Total | C25: 0.1679639 | E25: 0.05606351 | F25: 0.052942249 | G25: 0.043747847 | H25: 0.039199179 | I25: 0.030556642 | J25: 0.028742676 | K25: 0.025932115 | L25: 0.014492568 | M25: 0.014613155 | N25: 0.0018213335
A27: Females^^ | B27: Total | C27: 0.1076895 | E27: 0.034042022 | F27: 0.02463972 | G27: 0.032372316 | H27: 0.022929496 | I27: 0.025019784 | J27: 0.026252821 | K27: 0.016787732 | L27: 0.010068978 | M27: 0.0096745784 | N27: 0.0014613753
C28: Estimated number of adult volunteers
A29: All# | B29: Total | C29: 789467.51 | E29: 257881.37 | F29: 222419.74 | G29: 217458.97 | H29: 177131.06 | I29: 159406.52 | J29: 157818.04 | K29: 121900.27 | L29: 70128.552 | M29: 69317.898 | N29: 9895.9215
A30: Age group | B30: 15-17 | C30: 16575.319 | E30: 4653.4385 | F30: 3400.8145 | G30: 1414.3118 | H30: 0 | I30: 2074.1972 | J30: 1686.4206 | K30: 1657.7518 | L30: 1276.6703 | M30: 1688.3841 | N30: 0
B31: 18-24 | C31: 131294.6 | E31: 37856.044 | F31: 45402.786 | G31: 24538.725 | H31: 19521.859 | I31: 24802.004 | J31: 22275.878 | K31: 23298.466 | L31: 16872.604 | M31: 8168.6803 | N31: 1061.2801
B32: 25-34 | C32: 162615.75 | E32: 38607.458 | F32: 52133.703 | G32: 41265.275 | H32: 30497.767 | I32: 34867.674 | J32: 28415.961 | K32: 30249.187 | L32: 21441.034 | M32: 20170.922 | N32: 1614.4572
B33: 35-44 | C33: 141554.53 | E33: 46527.004 | F33: 46790.186 | G33: 41643.477 | H33: 26343.302 | I33: 32644.546 | J33: 30020.798 | K33: 24003.781 | L33: 14462.921 | M33: 10751.689 | N33: 493.85114
B34: 45-54 | C34: 154762.84 | E34: 62223.842 | F34: 37099.308 | G34: 48144.99 | H34: 29018.72 | I34: 39112.888 | J34: 43834.213 | K34: 20843.07 | L34: 10024.173 | M34: 14942.05 | N34: 2508.9107
B35: 55-64 | C35: 78386.63 | E35: 27952.441 | F35: 17854.75 | G35: 28131.196 | H35: 21346.752 | I35: 12076.662 | J35: 15283.883 | K35: 10383.348 | L35: 4253.6865 | M35: 7328.4816 | N35: 1957.6683
B36: 65+ | C36: 104277.84 | E36: 40061.139 | F36: 19738.189 | G36: 32321 | H36: 50402.655 | I36: 13828.547 | J36: 16300.882 | K36: 11464.666 | L36: 1797.4629 | M36: 6267.6901 | N36: 2259.7541
A38: Males^^ | B38: Total | C38: 472530.32 | E38: 157722.63 | F38: 148941.64 | G38: 123075.16 | H38: 110278.46 | I38: 85964.546 | J38: 80861.342 | K38: 72954.432 | L38: 40771.725 | M38: 41110.97 | N38: 5123.9302
A40: Females^^ | B40: Total | C40: 313976.48 | E40: 99251.958 | F40: 71838.871 | G40: 94383.809 | H40: 66852.591 | I40: 72946.977 | J40: 76541.985 | K40: 48945.838 | L40: 29356.827 | M40: 28206.928 | N40: 4260.7444
A42: NB. Please note that non-playing roles were collected for adults (15 years and over) only
A43: NB. Estimated participant numbers have not been rounded but users must remember that they are estimates and are subject to margins of error. Refer to sheet number 27 for margin of error and relative margin of error statistics.
A44: ^ Includes adults involved in non-playing roles as a volunteer, or who considered themselves a volunteer even if they received some form of compensation
A45: * Estimate has relative margin of error between 50% and 100% and should be used with caution
A46: ** Estimate has relative margin of error greater than 100% and is considered too unreliable to use
A47: # AusPlay collects data on gender, including non-binary and self-described. Non-binary and self-described gender are included in Total columns but not reported separately due to sample size. The sum of male and female estimates is not therefore equal to the total.
A48: ^^ Age group data by gender has not been reported due to sample size

Sheet 23
A8: =Index!A8 -> AusPlay survey results July 2024 - June 2025
A9: Released at: | B9: 13 November 2025
A10: Table number: | B10: 23
A11: Table name: | B11: Volunteers^ in non-playing roles by activity - top 10 activities (adults)
A12: Base: | B12: Adult population
B14: Total# | D14: Males | E14: Females
B15: Participation rate
A16: Australian football | B16: 0.025416172 | D16: 0.035769166 | E16: 0.015546205
A17: Basketball | B17: 0.018430323 | D17: 0.019282595 | E17: 0.017709604
A18: Football/soccer | B18: 0.012823917 | D18: 0.018110921 | E18: 0.0077240404
A19: Cricket | B19: 0.011911961 | D19: 0.019255783 | E19: 0.0049836875
A20: Netball | B20: 0.010614496 | D20: 0.0045815225 | E20: 0.016576522
A21: Tennis | B21: 0.0074703726 | D21: 0.0093857334 | E21: 0.0057212359
A22: Running/jogging | B22: 0.0051514936 | D22: 0.0052325181 | E22: 0.0051416003
A23: Golf | B23: 0.0040813709 | D23: 0.0058585541 | E23: 0.0024206394
A24: Athletics, track and field | B24: 0.0037259262 | D24: 0.003433943 | E24: 0.004057057
A25: Fitness/Gym | B25: 0.0036661346 | D25: 0.0039497234 | E25: 0.0034410934
B26: Estimated number of adult volunteers
A27: Australian football | B27: 146587.92 | D27: 100628.86 | E27: 45326.078
A28: Basketball | B28: 106297 | D28: 54247.438 | E28: 51633.623
A29: Football/soccer | B29: 73962.018 | D29: 50951.185 | E29: 22519.994
A30: Cricket | B30: 68702.306 | D30: 54172.008 | E30: 14530.299
A31: Netball | B31: 61219.17 | D31: 12889.129 | E31: 48330.041
A32: Tennis | B32: 43085.418 | D32: 26404.744 | E32: 16680.674
A33: Running/jogging | B33: 29711.27 | D33: 14720.565 | E33: 14990.705
A34: Golf | B34: 23539.331 | D34: 16481.783 | E34: 7057.5479
A35: Athletics, track and field | B35: 21489.301 | D35: 9660.6605 | E35: 11828.641
A36: Fitness/Gym | B36: 21144.453 | D36: 11111.698 | E36: 10032.755
A38: NB. Please note that non-playing roles were collected for adults (15 years and over) only
A39: NB. Estimated participant numbers have not been rounded but users must remember that they are estimates and are subject to margins of error. Refer to sheet number 27 for margin of error and relative margin of error statistics.
A40: ^ Includes adults involved in non-playing roles as a volunteer, or who considered themselves a volunteer even if they received some form of compensation
A41: * Estimate has relative margin of error between 50% and 100% and should be used with caution
A42: ** Estimate has relative margin of error greater than 100% and is considered too unreliable to use
A43: # AusPlay collects data on gender, including non-binary and self-described. Non-binary and self-described gender are included in Total columns but not reported separately due to sample size. The sum of male and female estimates is not therefore equal to the total.

Sheet 24
A8: =Index!A8 -> AusPlay survey results July 2024 - June 2025
A9: Released at: | B9: 13 November 2025
A10: Table number: | B10: 24
A11: Table name: | B11: Volunteers^ in non-playing roles by activity - top roles and top 5 activities (adults)
A12: Base: | B12: Adult population
B13: Coach, instructor, trainer or teacher | C13: Official | D13: Administrator or committee member | E13: Team manager or coordinator
B14: Participation rate
A15: Australian football | B15: 0.006177296 | C15: 0.010191301 | D15: 0.0033533401 | E15: 0.0035884016
A16: Basketball | B16: 0.0066267263 | C16: 0.006695418 | D16: 0.0019332565 | E16: 0.0050145914
A17: Football/soccer | B17: 0.0043400682 | C17: 0.0029425981 | D17: 0.002013197 | E17: 0.002493909
A18: Cricket | B18: 0.0032582911 | C18: 0.0044317363 | D18: 0.003358869 | E18: 0.001888523
A19: Netball | B19: 0.0027866454 | C19: 0.0040695838 | D19: 0.0019702138 | E19: 0.0027410727
B20: Estimated number of adult volunteers
A21: Australian football | B21: 35627.591 | C21: 58778.386 | D21: 19340.409 | E21: 20696.127
A22: Basketball | B22: 38219.683 | C22: 38615.862 | D22: 11150.068 | E22: 28921.685
A23: Football/soccer | B23: 25031.369 | C23: 16971.452 | D23: 11611.126 | E23: 14383.635
A24: Cricket | B24: 18792.213 | C24: 25560.065 | D24: 19372.296 | E24: 10892.068
A25: Netball | B25: 16071.994 | C25: 23471.349 | D25: 11363.22 | E25: 15809.153
A27: NB. Please note that non-playing roles were collected for adults (15 years and over) only
A28: NB. Estimated participant numbers have not been rounded but users must remember that they are estimates and are subject to margins of error. Refer to sheet number 27 for margin of error and relative margin of error statistics.
A29: ^ Includes adults involved in non-playing roles as a volunteer, or who considered themselves a volunteer even if they received some form of compensation
A30: * Estimate has relative margin of error between 50% and 100% and should be used with caution
A31: ** Estimate has relative margin of error greater than 100% and is considered too unreliable to use

Sheet 25
A8: =Index!A8 -> AusPlay survey results July 2024 - June 2025
A9: Released at: | C9: 13 November 2025
A10: Table number: | C10: 25
A11: Table name: | C11: Demographics of non-participants (adults)
A12: Base: | C12: Adult population
C13: Non-Participation rate | G13: Estimated number of non-participants
C14: Total | D14: Males | E14: Females | G14: Total# | H14: Males | I14: Females
A15: Total | C15: 0.13036017 | D15: 0.12265002 | E15: 0.1355623 | G15: 751853.05 | H15: 345049.47 | I15: 395241.63
A16: Age group
B17: 15-17 | C17: 0.15416532 | D17: 0.18014358 | E17: 0.11495324 | G17: 37109.189 | H17: 17824.024 | I17: 15908.397
B18: 18-24 | C18: 0.11080141 | D18: 0.11866843 | E18: 0.09963787 | G18: 75187.692 | H18: 43276.468 | I18: 30323.766
B19: 25-34 | C19: 0.081349085 | D19: 0.079792974 | E19: 0.083059794 | G19: 85945.958 | H19: 40340.613 | I19: 45159.801
B20: 35-44 | C20: 0.10766611 | D20: 0.11204508 | E20: 0.10116192 | G20: 108227.27 | H20: 56745.406 | I20: 49858.899
B21: 45-54 | C21: 0.10854521 | D21: 0.09674632 | E21: 0.12139519 | G21: 93646.74 | H21: 41146.547 | I21: 52500.193
B22: 55-64 | C22: 0.1247898 | D22: 0.12674188 | E22: 0.12350746 | G22: 93105.186 | H22: 47008.645 | I22: 46096.541
B23: 65+ | C23: 0.21961533 | D23: 0.18230734 | E23: 0.24643226 | G23: 258631.01 | H23: 98707.771 | I23: 155394.03
A24: Remoteness
B25: Major cities | C25: 0.12341538 | D25: 0.11159247 | E25: 0.13174104 | G25: 549294.95 | H25: 241867.53 | I25: 296957.34
B26: Inner regional | C26: 0.15225893 | D26: 0.15839606 | E26: 0.14657742 | G26: 164565.65 | H26: 84194.2 | I26: 79279.58
B27: Outer regional | C27: 0.16278694 | D27: 0.16981241 | E27: 0.15758318 | G27: 37992.447 | H27: 18987.741 | I27: 19004.706
B28: Remote or very remote | C28: 0 | D28: 0 | E28: 0 | G28: 0 | H28: 0 | I28: 0
A29: Employment status
B30: Employed full-time | C30: 0.088175048 | D30: 0.08654222 | E30: 0.089743815 | G30: 230220.88 | H30: 133493.13 | I30: 95104.784
B31: Employed part-time | C31: 0.11382478 | D31: 0.14145571 | E31: 0.096822684 | G31: 99224.881 | H31: 42723.749 | I31: 54429.627
B32: Employed casual | C32: 0.086079306 | D32: 0.078881895 | E32: 0.089626113 | G32: 28765.569 | H32: 10042.612 | I32: 18181.268
B33: Total employed | C33: 0.093849706 | D33: 0.094458711 | E33: 0.091911544 | G33: 358211.33 | H33: 186259.5 | I33: 167715.68
B34: Full-time student | C34: 0.094574234 | D34: 0.092750835 | E34: 0.084564623 | G34: 28212.223 | H34: 13504.653 | I34: 12516.471
B35: Engaged in home duties | C35: 0.19380923 | D35: 0.29144621 | E35: 0.1771474 | G35: 36909.551 | H35: 8342.91 | I35: 28566.641
B36: Unemployed | C36: 0.21743482 | D36: 0.2332946 | E36: 0.20518798 | G36: 53323.173 | H36: 26236.933 | I36: 26640.697
B37: Retired or on a pension | C37: 0.22226415 | D37: 0.18952454 | E37: 0.24563265 | G37: 254702 | H37: 97870.878 | I37: 152685.03
A38: Highest education completed
B39: University degree or higher (including postgraduate diploma) | C39: 0.069941939 | D39: 0.074293376 | E39: 0.064905453 | G39: 172414.13 | H39: 95454.952 | I39: 75885.029
B40: Undergraduate diploma or associate diploma | C40: 0.13156626 | D40: 0.12798776 | E40: 0.12966103 | G40: 104583.73 | H40: 49611.459 | I40: 51973.045
B41: Certificate, trade qualification or apprenticeship | C41: 0.16449006 | D41: 0.15606028 | E41: 0.17182457 | G41: 153615.51 | H41: 65750.515 | I41: 87316.173
B42: Highest level of secondary school | C42: 0.15766507 | D42: 0.15958369 | E42: 0.15262708 | G42: 144631.15 | H42: 71087.683 | I42: 70867.849
B43: Did not complete highest level of school | C43: 0.31849483 | D43: 0.22201028 | E43: 0.38086156 | G43: 116562.69 | H43: 30366.28 | I43: 85693.7
B44: Still at secondary school | C44: 0.12123487 | D44: 0.11533589 | E44: 0.095732239 | G44: 24148.891 | H44: 10164.339 | I44: 10223.122
A45: Household structure
B46: Younger family (most children under 15 years) | C46: 0.086363141 | D46: 0.072805648 | E46: 0.095749608 | G46: 93123.152 | H46: 39151.392 | I46: 51351.435
B47: Mature family (most children 15 years or over) | C47: 0.12475063 | D47: 0.12454829 | E47: 0.12345819 | G47: 171096.52 | H47: 83161.634 | I47: 85704.816
B48: Mid family (equal number of children 15 years and over and under 15 years) | C48: 0.084553737 | D48: 0.083391698 | E48: 0.086903371 | G48: 16716.37 | H48: 7821.2127 | I48: 8895.1573
B49: Adult shared house | C49: 0.13539004 | D49: 0.12911434 | E49: 0.14185948 | G49: 91046.247 | H49: 45804.019 | I49: 44189.081
B50: Single/couple - no children | C50: 0.14823572 | D50: 0.13481554 | E50: 0.15806355 | G50: 352599.61 | H50: 151148.61 | I50: 196335.65
A51: Aboriginal or Torres Strait Islander origin^
B52: Yes | C52: 0.19452875 | D52: 0.1619376 | E52: 0.24225252 | G52: 34283.16 | H52: 17720.839 | I52: 15733.657
B53: No | C53: 0.12490445 | D53: 0.11572778 | E53: 0.13257086 | G53: 653462.98 | H53: 292611.3 | I53: 354540.93
B54: Refused / don't know | C54: 0.22714757 | D54: 0.22092339 | E54: 0.2391158 | G54: 26997.72 | H54: 16893.309 | I54: 9058.6413
A55: Language spoken at home^
B56: Speaks only English at home | C56: 0.12715271 | D56: 0.11736018 | E56: 0.1359476 | G56: 567387.11 | H56: 250995.06 | I56: 312782.95
B57: Speaks language other than English at home | C57: 0.12591224 | D57: 0.11859553 | E57: 0.12711356 | G57: 124772.09 | H57: 62359.529 | I57: 57836.475
A58: Disability or physical condition that restricts life in some way^
B59: Yes | C59: 0.27269057 | D59: 0.27285526 | E59: 0.27589775 | G59: 238861.82 | H59: 97930.498 | I59: 139049.51
B60: No | C60: 0.097196716 | D60: 0.091834381 | E60: 0.10074359 | G60: 439791.3 | H60: 210162.78 | I60: 223325.15
B61: Refused / don't know | C61: 0.28621593 | D61: 0.28583741 | E61: 0.30055303 | G61: 36090.734 | H61: 19132.168 | I61: 16958.565
A62: Annual household income~^
B63: <$40,000 | C63: 0.26650837 | D63: 0.21475458 | E63: 0.30634262 | G63: 188806.09 | H63: 62121.535 | I63: 126301.44
B64: $40,000 - $69,999 | C64: 0.17544474 | D64: 0.1898516 | E64: 0.15987007 | G64: 137566.44 | H64: 64657.653 | I64: 69866.491
B65: $70,000 - $99,999 | C65: 0.12456206 | D65: 0.12176158 | E65: 0.12170709 | G65: 101692.49 | H65: 51460.282 | I65: 47107.631
B66: $100,000 - $149,999 | C66: 0.075449341 | D66: 0.064728892 | E66: 0.087495759 | G66: 83056.324 | H66: 38407.782 | I66: 44106.853
B67: $150,000 - $199,999 | C67: 0.066083868 | D67: 0.076497116 | E67: 0.053017346 | G67: 39435.057 | H67: 24230.382 | I67: 14654.242
B68: $200,000+ | C68: 0.066729318 | D68: 0.071418037 | E68: 0.060396124 | G68: 44307.229 | H68: 27609.086 | I68: 16698.143
B69: Not stated | C69: 0.13999771 | D69: 0.16085041 | E69: 0.12524708 | G69: 119880.22 | H69: 58738.727 | I69: 60598.433
A70: Sexual orientation^
B71: Straight (heterosexual) | C71: 0.1296968 | D71: 0.1177181 | E71: 0.1402643 | G71: 630025.74 | H71: 276311.01 | I71: 351098.63
B72: Gay or Lesbian | C72: 0.098655112 | D72: 0.098594622 | E72: 0.098123299 | G72: 25242.414 | H72: 19347.256 | I72: 5371.4465
B73: Bisexual | C73: 0.11137754 | D73: 0.14942186 | E73: 0.082783677 | G73: 20552.613 | H73: 10158.801 | I73: 8957.5443
B74: Other | C74: 0.13309111 | D74: 0 | E74: 0.19543532 | G74: 3338.426 | H74: 0 | I74: 2344.0629
A76: NB. Estimated participant numbers have not been rounded but users must remember that they are estimates and are subject to margins of error. Refer to sheet number 27 for margin of error and relative margin of error statistics.
A77: ~ As is common in population surveys, a large proportion of respondents refused to provide or did not know their household income
A78: ^ Question asked of 18+ year olds only
A79: # AusPlay collects data on gender, including non-binary and self-described. Non-binary and self-described gender are included in Total columns but not reported separately due to sample size. The sum of male and female estimates is not therefore equal to the total.
A80: * Estimate has relative margin of error between 50% and 100% and should be used with caution
A81: ** Estimate has relative margin of error greater than 100% and is considered too unreliable to use

Sheet 26
A8: =Index!A8 -> AusPlay survey results July 2024 - June 2025
A9: Released at: | C9: 13 November 2025
A10: Table number: | C10: 26
A11: Table name: | C11: Demographics of non-participants (children)
A12: Base: | C12: Child population
C13: Non-Participation rate | G13: Estimated number of non-participants
C14: Total | D14: Males | E14: Females | G14: Total# | H14: Males | I14: Females
A15: Total | C15: 0.26785857 | D15: 0.26567132 | E15: 0.26810104 | G15: 327768.32 | H15: 172966.49 | I15: 152826.57
A16: Age group
B17: 0-4 | C17: 0.50033307 | D17: 0.52023441 | E17: 0.47899594 | G17: 190451.3 | H17: 106078.48 | I17: 84372.822
B18: 5-8 | C18: 0.17798357 | D18: 0.17489737 | E18: 0.17631905 | G18: 59645.026 | H18: 29811.219 | I18: 28862.398
B19: 9-11 | C19: 0.14981491 | D19: 0.12533061 | E19: 0.17219141 | G19: 37263.406 | H19: 16309.766 | I19: 20310.397
B20: 12-14 | C20: 0.15591666 | D20: 0.14169105 | E20: 0.17178064 | G20: 40408.587 | H20: 20767.024 | I20: 19280.956
A21: Remoteness
B22: Major cities | C22: 0.26336843 | D22: 0.25086639 | E22: 0.27469761 | G22: 250544.05 | H22: 126802.8 | I22: 121765.99
B23: Inner regional | C23: 0.27309546 | D23: 0.31981837 | E23: 0.2210637 | G23: 62035.045 | H23: 38276.913 | I23: 23758.131
B24: Outer regional | C24: 0.33604184 | D24: 0.30437201 | E24: 0.37858558 | G24: 15189.226 | H24: 7886.7743 | I24: 7302.4516
B25: Remote or very remote | C25: 0 | D25: 0 | E25: 0 | G25: 0 | H25: 0 | I25: 0
A26: Household structure
B27: Younger family (most children under 15 years) | C27: 0.28188145 | D27: 0.28329769 | E27: 0.27820046 | G27: 291679.51 | H27: 156179.1 | I27: 133885.76
B28: Mature family (most children 15 years or over) | C28: 0.23175565 | D28: 0.19845454 | E28: 0.2790955 | G28: 17565.888 | H28: 8830.2303 | I28: 8735.6578
B29: Mid family (equal number of children 15 years and over and under 15 years) | C29: 0.16376385 | D29: 0.14396961 | E29: 0.17755142 | G29: 18522.921 | H29: 7957.1629 | I29: 10205.152
A30: Aboriginal or Torres Strait Islander origin of parent/guardian interviewed^
B31: Yes | C31: 0.2315217 | D31: 0.18672927 | E31: 0.27077865 | G31: 18238.739 | H31: 7632.1146 | I31: 10136.607
B32: No | C32: 0.27001593 | D32: 0.27248183 | E32: 0.26542265 | G32: 301942.9 | H32: 161716.45 | I32: 138721.21
B33: Refused / don't know | C33: 0.28475188 | D33: 0.2168062 | E33: 0.39863944 | G33: 7586.6803 | H33: 3617.9279 | I33: 3968.7525
A34: Language spoken at home by parent/guardian interviewed^
B35: Speaks only English at home | C35: 0.27461852 | D35: 0.27689673 | E35: 0.27127246 | G35: 261586.71 | H35: 141835.72 | I35: 119107.74
B36: Speaks language other than English at home | C36: 0.24187494 | D36: 0.22291554 | E36: 0.25968714 | G36: 62332.364 | H36: 29445.478 | I36: 32526.278
A37: Annual household income~^
B38: <$40,000 | C38: 0.41320146 | D38: 0.34813515 | E38: 0.45457863 | G38: 24755.251 | H38: 9255.1072 | I38: 14856.901
B39: $40,000 - $69,999 | C39: 0.27924376 | D39: 0.25199163 | E39: 0.30333184 | G39: 25641.694 | H39: 12571.076 | I39: 12569.227
B40: $70,000 - $99,999 | C40: 0.30754866 | D40: 0.31267734 | E40: 0.29906959 | G40: 52289.746 | H40: 27317.481 | I40: 24611.659
B41: $100,000 - $149,999 | C41: 0.25556198 | D41: 0.25947415 | E41: 0.25151737 | G41: 90195.274 | H41: 51460.862 | I41: 38734.412
B42: $150,000 - $199,999 | C42: 0.31614726 | D42: 0.34111194 | E42: 0.28391259 | G42: 64348.195 | H42: 39126.953 | I42: 25221.241
B43: $200,000+ | C43: 0.18049643 | D43: 0.16054684 | E43: 0.19988287 | G43: 41710.962 | H43: 18284.831 | I43: 23426.131
B44: Not stated | C44: 0.25210405 | D44: 0.24795563 | E44: 0.25021165 | G44: 28827.2 | H44: 14950.18 | I44: 13407.002
A46: NB. Please note that for children 0-14 years, data was collected via the child's parent/guardian for organised participation outside of school hours
A47: NB. Estimated participant numbers have not been rounded but users must remember that they are estimates and are subject to margins of error. Refer to sheet number 27 for margin of error and relative margin of error statistics.
A48: ~ As is common in population surveys, a large proportion of respondents refused to provide or did not know their household income
A49: ^ Question asked of 18+ year olds only
A50: # AusPlay collects data on gender, including non-binary and self-described. Non-binary and self-described gender are included in Total columns but not reported separately due to sample size. The sum of male and female estimates is not therefore equal to the total.
A51: * Estimate has relative margin of error between 50% and 100% and should be used with caution
A52: ** Estimate has relative margin of error greater than 100% and is considered too unreliable to use

Sheet 27
A8: AusPlay survey results July 2024 - June 2025
A9: Released at: | C9: 13 November 2025
A10: Table number: | C10: 27
A11: Table name: | C11: Margins of error
A12: Relative margins of error for adult estimates
A13: Size of estimate | C13: NSW (%) | D13: Vic (%) | E13: Qld (%) | F13: SA (%) | G13: WA (%) | H13: Tas (%) | I13: NT (%) | J13: ACT (%) | K13: Australia (%)
A14: 1000 | C14: 1.6539393 | D14: 1.6131532 | E14: 1.6822414 | F14: 1.6946597 | G14: 1.5893685 | H14: 1.2932359 | I14: 1.3108712 | J14: 1.2485139 | K14: 1.6294276
A15: 2000 | C15: 1.1693934 | D15: 1.140538 | E15: 1.1893341 | F15: 1.1977373 | G15: 1.123703 | H15: 0.91321484 | I15: 0.92492607 | J15: 0.88147754 | K15: 1.152144
A16: 5000 | C16: 0.73943971 | D16: 0.72117055 | E16: 0.75196032 | F16: 0.75679653 | G16: 0.71021683 | H16: 0.57599473 | I16: 0.58052607 | J16: 0.55549047 | K16: 0.72863522
A17: 10000 | C17: 0.52267763 | D17: 0.50970551 | E17: 0.53141835 | F17: 0.53437239 | G17: 0.50172819 | H17: 0.405056 | I17: 0.40550155 | J17: 0.39014462 | K17: 0.51516766
A18: 20000 | C18: 0.36932684 | D18: 0.36009904 | E18: 0.37537801 | F18: 0.3765955 | G18: 0.35406075 | H18: 0.28336582 | I18: 0.2792075 | J18: 0.27238537 | K18: 0.36419483
A19: 50000 | C19: 0.23308489 | D19: 0.22715717 | E19: 0.23662728 | F19: 0.23588304 | G19: 0.22253587 | H19: 0.17329651 | I19: 0.1619264 | J19: 0.16528344 | K19: 0.23018518
A20: 100000 | C20: 0.16422742 | D20: 0.15992092 | E20: 0.16639887 | F20: 0.16403805 | G20: 0.155717 | H20: 0.1152908 | I20: 0.094864598 | J20: 0.10816132 | K20: 0.16258304
A21: 200000 | C21: 0.11528358 | D21: 0.11208651 | E21: 0.11635679 | F21: 0.1119925 | G21: 0.10775235 | H21: 0.070049905 | I21: 0.019244252 | J21: 0.06236183 | K21: 0.11470865
A22: 500000 | C22: 0.071296607 | D22: 0.06895924 | E22: 0.071037879 | F22: 0.062652571 | G22: 0.063468411 | H22: - | I22: - | J22: - | K22: 0.072060013
A23: 800000 | C23: 0.055058438 | D23: 0.052946905 | E23: 0.054072312 | F23: 0.042084448 | G23: 0.046180697 | H23: - | I23: - | J23: - | K23: 0.056579031
A24: 1000000 | C24: 0.048450123 | D24: 0.046398373 | E24: 0.047079125 | F24: 0.032436278 | G24: 0.038740108 | H24: - | I24: - | J24: - | K24: 0.050373092
A25: 1500000 | C25: 0.037885346 | D25: 0.035850891 | E25: 0.035676748 | F25: 0.0097609095 | G25: 0.025648873 | H25: - | I25: - | J25: - | K25: 0.040650178
A26: 2000000 | C26: 0.031295052 | D26: 0.029178292 | E26: 0.028302359 | F26: - | G26: 0.015386251 | H26: - | I26: - | J26: - | K26: 0.034783482
A27: 5000000 | C27: 0.012596444 | D27: 0.0084079605 | E27: - | F27: - | G27: - | H27: - | I27: - | J27: - | K27: 0.020331156
A28: 8000000 | C28: - | D28: - | E28: - | F28: - | G28: - | H28: - | I28: - | J28: - | K28: 0.01463668
A29: 10000000 | C29: - | D29: - | E29: - | F29: - | G29: - | H29: - | I29: - | J29: - | K29: 0.01215946
A30: 20000000 | C30: - | D30: - | E30: - | F30: - | G30: - | H30: - | I30: - | J30: - | K30: 0.0038854467
A32: Margins of error for adult estimates
A33: Size of estimate | C33: NSW (no.) | D33: Vic (no.) | E33: Qld (no.) | F33: SA (no.) | G33: WA (no.) | H33: Tas (no.) | I33: NT (no.) | J33: ACT (no.) | K33: Australia (no.)
A34: 1000 | C34: 1653.9393 | D34: 1613.1532 | E34: 1682.2414 | F34: 1694.6597 | G34: 1589.3685 | H34: 1293.2359 | I34: 1310.8712 | J34: 1248.5139 | K34: 1629.4276
